Workbook
Name DATOS1: [1]!CODPARADA[[#All],[1: Procesos ]]
Name DATOS1: [1]!CODPARADA[[#All],[1: Procesos ]]

Sheet Calculo de Troquelado
A1: 2013 | B1: Venta Normal | C1: Semiautomaticas | D1: 12 VELAS DE NOCHE | E1: 2000 | F1: 0.0048 | G1: 0.0035 | H1: =(F1-G1)/F1 -> 0.27083333 | I1: PAI | J1: PAI BLANCO 650 x 200 | K1: CAJA Nº 3 | L1: BOLSAS DE 120 X 80 | M1: 35 | N1: 14 | O1: =IFERROR(60*60*7.5*M1/E1/N1,"") -> 33.75 | P1: =IFERROR(60*60*7.5*M1/E1/O1,"") -> 14 | Q1: =IFERROR(P1/8,"") -> 1.75 | R1: =IFERROR(IF(P1>2,Q1,""),"") -> 1.75 | T1: =IF(V1>10,V1*M1/E1,"") -> 18.243243 | U1: 25.9 | V1: =60*60*7.5/U1 -> 1042.471 | W1: 45553 | X1: Christian
B4: Ciclo por golpe | C4: Cantidad de ´plancha por vez | D4: ciclo por plancha | E4: Seg/hora | F4: Min/seg | G4: Horas efectivas disponibles | H4: Cavidades | I4: Un x cajas | J4: META | K4: OEE 80% ( En 6 horas)
B5: 52.3 | C5: 3 | D5: =B5/C5 -> 17.433333 | E5: 60 | F5: 60 | G5: 7.5 | H5: 35 | I5: 2000 | J5: =(E5*F5*G5*H5)/(D5*I5) -> 27.10325 | K5: =J5*0.8 -> 21.6826
B13: Ciclo por golpe | C13: Cantidad de ´plancha por vez | D13: ciclo por plancha | J13: Meta | K13: OEE 80% ( En 6 horas)
B14: =D14*C$14 -> 101.25 | C14: 3 | D14: =E14*F14*G14*H14/(I14*J14) -> 33.75 | E14: 60 | F14: 60 | G14: 7.5 | H14: =M$1 -> 35 | I14: =E$1 -> 2000 | J14: 14 | K14: =J14*0.8 -> 11.2
B15: =D15*C$14 -> 94.5 | D15: =E15*F15*G15*H15/(I15*J15) -> 31.5 | E15: 60 | F15: 60 | G15: 7.5 | H15: =M$1 -> 35 | I15: =E$1 -> 2000 | J15: 15 | K15: =J15*0.8 -> 12
B16: =D16*C$14 -> 88.59375 | D16: =E16*F16*G16*H16/(I16*J16) -> 29.53125 | E16: 60 | F16: 60 | G16: 7.5 | H16: =M$1 -> 35 | I16: =E$1 -> 2000 | J16: 16 | K16: =J16*0.8 -> 12.8
B17: =D17*C$14 -> 83.382353 | D17: =E17*F17*G17*H17/(I17*J17) -> 27.794118 | E17: 60 | F17: 60 | G17: 7.5 | H17: =M$1 -> 35 | I17: =E$1 -> 2000 | J17: 17 | K17: =J17*0.8 -> 13.6
B18: =D18*C$14 -> 78.75 | D18: =E18*F18*G18*H18/(I18*J18) -> 26.25 | E18: 60 | F18: 60 | G18: 7.5 | H18: =M$1 -> 35 | I18: =E$1 -> 2000 | J18: 18 | K18: =J18*0.8 -> 14.4
B19: =D19*C$14 -> 74.605263 | D19: =E19*F19*G19*H19/(I19*J19) -> 24.868421 | E19: 60 | F19: 60 | G19: 7.5 | H19: =M$1 -> 35 | I19: =E$1 -> 2000 | J19: 19 | K19: =J19*0.8 -> 15.2
B20: =D20*C$14 -> 74.605263 | D20: =E20*F20*G20*H20/(I20*J20) -> 24.868421 | E20: 60 | F20: 60 | G20: 7.5 | H20: =M$1 -> 35 | I20: =E$1 -> 2000 | J20: 19 | K20: =J20*0.8 -> 15.2
B21: =D21*C$14 -> 70.875 | D21: =E21*F21*G21*H21/(I21*J21) -> 23.625 | E21: 60 | F21: 60 | G21: 7.5 | H21: =M$1 -> 35 | I21: =E$1 -> 2000 | J21: 20 | K21: =J21*0.8 -> 16
B22: =D22*C$14 -> 67.5 | D22: =E22*F22*G22*H22/(I22*J22) -> 22.5 | E22: 60 | F22: 60 | G22: 7.5 | H22: =M$1 -> 35 | I22: =E$1 -> 2000 | J22: 21 | K22: =J22*0.8 -> 16.8
B23: =D23*C$14 -> 64.431818 | D23: =E23*F23*G23*H23/(I23*J23) -> 21.477273 | E23: 60 | F23: 60 | G23: 7.5 | H23: =M$1 -> 35 | I23: =E$1 -> 2000 | J23: 22 | K23: =J23*0.8 -> 17.6
B24: =D24*C$14 -> 61.630435 | D24: =E24*F24*G24*H24/(I24*J24) -> 20.543478 | E24: 60 | F24: 60 | G24: 7.5 | H24: =M$1 -> 35 | I24: =E$1 -> 2000 | J24: 23 | K24: =J24*0.8 -> 18.4
B25: =D25*C$14 -> 59.0625 | D25: =E25*F25*G25*H25/(I25*J25) -> 19.6875 | E25: 60 | F25: 60 | G25: 7.5 | H25: =M$1 -> 35 | I25: =E$1 -> 2000 | J25: 24 | K25: =J25*0.8 -> 19.2
B26: =D26*C$14 -> 56.7 | D26: =E26*F26*G26*H26/(I26*J26) -> 18.9 | E26: 60 | F26: 60 | G26: 7.5 | H26: =M$1 -> 35 | I26: =E$1 -> 2000 | J26: 25 | K26: =J26*0.8 -> 20
... B34: =D34*C$14 -> 42.954545 | D34: =E34*F34*G34*H34/(I34*J34) -> 14.318182 | E34: 60 | F34: 60 | G34: 7.5 | H34: =M$1 -> 35 | I34: =E$1 -> 2000 | J34: 33 | K34: =J34*0.8 -> 26.4

Sheet Masterdata
W1: SEMI - TOTAL | X1: =COUNT(O246:O783) -> 538 | Y1: REG | Z1: =COUNT(W246:W783) -> 88 | AD1: =Z1/X1 -> 0.16356877 | AG1: GN | AH1: =COUNT(A4:A237) -> 234 | AI1: REG | AJ1: =COUNT(AE4:AE237) -> 43 | AK1: =AJ1/AH1 -> 0.18376068
A2: 338 | D2: Con mi pad no lo hace | X2: Semiautomáticas
A3: 7 | B3: Estado | C3: Maquina | D3: ARTICULO | E3: UN por CAJA | F3: PESO BR. | G3: PESO NET. | H3: % SCRAP | I3: MATERIAL | J3: MATERIAL DETALLE | K3: CAJAS | L3: BOLSA | M3: Paquete por Caja | N3: Unidades por Paquete | O3: CAV | P3: META | Q3: CICLO Master Darta | R3: Cajas en 8 Horas | S3: Cajas x hora | T3: Cajas x hora | U3: Turnos para fabricar 1000 cajas | V3: Cajas que se fabricarían con las planchas | W3: Seg/ciclo | X3: META | Y3: FECHA | Z3: Registrado por | AD3: FECHA | AE3: MAQ | AF3: Calentamiento | AG3: Ventilador de calor | AH3: Fomación | AI3: Ventilador de forma | AJ3: intervalo de corte | AK3: Retraso de expulsión | AL3: Expulsión | AM3: Transporte | AN3: Retraso de cierre | AO3: Promedio de ciclo | AP3: Molde | AQ3: Zona1 | AR3: Zona2 | AS3: Zona3 | AT3: Precalentador | AU3: Presión de calentamiento | AV3: Presión de formación | AW3: Presión de expusión | AX3: Velocidad | AY3: Recorrido | AZ3: Modo | BA3: Acel/ Desacel | BB3: Velocidad del paso | BC3: Zona4 | BD3: Zona5 | BF3: Registrado por | BG3: FECHA | BH3: MAQ | BI3: Calentamiento | BJ3: Ventilador de calor | BK3: Fomación | BL3: Ventilador de forma | BM3: intervalo de corte | BN3: Retraso de expulsión | BO3: Expulsión | BP3: Transporte | BQ3: Retraso de cierre | BR3: Promedio de ciclo | BS3: Molde | BT3: Zona1 | BU3: Zona2 | BV3: Zona3 | BW3: Precalentador | BX3: Presión de calentamiento | BY3: Presión de formación | BZ3: Presión de expusión | CA3: Velocidad | CB3: Recorrido | CC3: Modo | CD3: Acel/ Desacel | CE3: Velocidad del paso | CF3: Zona4 | CG3: Zona5 | CH3: ZONA | CI3: CANTIDAD X PALLET
A4: 338 | B4: Venta Normal | C4: GN | D4: AP-12 | E4: 1200 | F4: 0.0162 | G4: 0.0135 | H4: =(F4-G4)/F4 -> 0.16666667 | I4: PET | J4: PET CRISTAL 580 x 250 | K4: CAJA Nº 4/1 SIN LOGO | L4: BOLSAS DE 120 X 125 | M4: 6 paq de 174 + 1 paq de 156 unid | O4: 6 | P4: 17 | Q4: =IFERROR(IF(AO4>1,AO4,60*60*8*O4/P4/E4),"") -> 6.3 | R4: =IFERROR(60*60*8*O4/E4/Q4,"") -> 22.857143 | S4: =IFERROR(R4/8,"") -> 2.8571429 | T4: =IFERROR(IF(R4>2,S4,""),"") -> 2.8571429 | AD4: 45612 | AE4: 12 | AF4: 1.6 | AG4: 0.3 | AH4: 1.6 | AI4: 0.4 | AJ4: 0.12 | AK4: 0.18 | AL4: 0.7 | AM4: 0.6 | AN4: 0.3 | AO4: 6.3 | AP4: 56 | AQ4: 110 | AR4: 115 | AS4: 110 | AT4: 37 | AU4: 30 | AV4: 35 | AW4: 42 | AX4: 51 | AY4: 451 | AZ4: Normal | BA4: 2000 | BB4: 14 | CH4: 5 | CI4: 78
A5: 398 | B5: Venta Normal | C5: GN | D5: AP-6 | E5: 1600 | F5: 0.0128 | G5: 0.0103 | H5: =(F5-G5)/F5 -> 0.1953125 | I5: PET | J5: PET CRISTAL 520 x 220 | K5: CAJA Nº 4/1 SIN LOGO | L5: BOLSAS DE 120 X 125 | O5: 6 | P5: 12 | Q5: 6.3 | R5: =IFERROR(60*60*8*O5/E5/Q5,"") -> 17.142857 | S5: =IFERROR(R5/8,"") -> 2.1428571 | T5: =IFERROR(IF(R5>2,S5,""),"") -> 2.1428571 | AD5: 45622 | AE5: 12 | AF5: 1.7 | AG5: 0.5 | AH5: 1.5 | AI5: 0.5 | AJ5: 0.17 | AK5: 0.25 | AL5: 0.5 | AM5: 0.6 | AN5: 0.45 | AO5: 6.6 | AP5: 46 | AQ5: 104 | AR5: 105 | AS5: 105 | AT5: 45 | AU5: 30 | AV5: 35 | AW5: 42 | AX5: 51 | AY5: 459 | AZ5: Normal | BA5: 1400 | BB5: 14 | CH5: 1 | CI5: 41
A6: 723 | B6: Venta Normal | C6: GN | D6: ART. 1445 | E6: 1320 | F6: 0.0084 | G6: 0.0063 | H6: =(F6-G6)/F6 -> 0.25 | I6: PVC | J6: PVC CRISTAL 500 x 300 | K6: CAJA Nº 3 | L6: BOLSAS DE 120 X 80 | O6: 12 | P6: 18 | Q6: =IFERROR(IF(AO6>1,AO6,60*60*8*O6/P6/E6),"") -> 14.545455 | R6: =IFERROR(60*60*8*O6/E6/Q6,"") -> 18 | S6: =IFERROR(R6/8,"") -> 2.25 | T6: =IFERROR(IF(R6>2,S6,""),"") -> 2.25 | CH6: 1 | CI6: 44
A7: 724 | B7: Discontinuado | C7: GN | D7: ART. 1445 OPS | E7: 1320 | F7: 0.0074 | G7: 0.0056 | H7: =(F7-G7)/F7 -> 0.24324324 | I7: OPS | J7: UNICLEAR CRISTAL OPS 480 x 400 | K7: CAJA Nº 3 | L7: BOLSAS DE 120 X 80 | O7: 12 | Q7: =IFERROR(IF(AO7>1,AO7,60*60*8*O7/P7/E7),"") | R7: =IFERROR(60*60*8*O7/E7/Q7,"") | S7: =IFERROR(R7/8,"") | T7: =IFERROR(IF(R7>2,S7,""),"") | CH7: 5 | CI7: 53
A8: 1909 | B8: Venta Normal | C8: GN | D8: ART. 1510 | E8: 400 | F8: 0.0109 | G8: 0.0084 | H8: =(F8-G8)/F8 -> 0.2293578 | I8: PVC | J8: PVC CRISTAL 460 x 300 | K8: CAJA Nº 2 | L8: BOLSAS DE 120 X 80 | O8: 9 | P8: 90 | Q8: =IFERROR(IF(AO8>1,AO8,60*60*8*O8/P8/E8),"") -> 5 | R8: =IFERROR(60*60*8*O8/E8/Q8,"") -> 129.6 | S8: =IFERROR(R8/8,"") -> 16.2 | T8: =IFERROR(IF(R8>2,S8,""),"") -> 16.2 | AD8: 45519 | AE8: 14 | AF8: 1 | AG8: 0.1 | AH8: 1 | AI8: 0.2 | AJ8: 0.75 | AK8: 0.15 | AL8: 0.19 | AM8: 0.75 | AN8: 0.4 | AO8: 5 | AP8: 58 | AQ8: 110 | AR8: 112 | AS8: 112 | AT8: 40 | AU8: 20 | AV8: 40 | AW8: 20 | AX8: 70 | AY8: 465 | AZ8: Normal | BA8: 1100 | BB8: 10 | CH8: 3 | CI8: 82
A9: 1934 | B9: Venta Normal | C9: GN | D9: ART. 1510 NEGRO | E9: 400 | F9: 0.01 | G9: 0.0068 | H9: =(F9-G9)/F9 -> 0.32 | I9: PVC | J9: PAI NEGRO 460 x 350 | K9: CAJA Nº 2 | L9: BOLSAS DE 120 X 80 | M9: 4 | N9: 100 | O9: 9 | P9: 25 | Q9: =IFERROR(IF(AO9>1,AO9,60*60*8*O9/P9/E9),"") -> 25.92 | R9: =IFERROR(60*60*8*O9/E9/Q9,"") -> 25 | S9: =IFERROR(R9/8,"") -> 3.125 | T9: =IFERROR(IF(R9>2,S9,""),"") -> 3.125 | CH9: 3 | CI9: 77
A10: 727 | B10: Venta Normal | C10: GN | D10: ART. 1510 OPS | E10: 800 | F10: 0.0086 | G10: 0.006 | H10: =(F10-G10)/F10 -> 0.30232558 | I10: OPS | J10: UNICLEAR CRISTAL OPS 460 x 300 | K10: CAJA Nº 12 | L10: BOLSAS DE 120 X 110 | O10: 9 | P10: 20 | Q10: =IFERROR(IF(AO10>1,AO10,60*60*8*O10/P10/E10),"") -> 16.2 | R10: =IFERROR(60*60*8*O10/E10/Q10,"") -> 20 | S10: =IFERROR(R10/8,"") -> 2.5 | T10: =IFERROR(IF(R10>2,S10,""),"") -> 2.5 | CH10: 3 | CI10: 59
A11: 728 | B11: Venta Normal | C11: GN | D11: ART. 1510 PAI NEGRO | E11: 800 | F11: 0.0131 | G11: 0.0068 | H11: =(F11-G11)/F11 -> 0.48091603 | I11: HIPST | J11: PAI NEGRO 600 x 350 | K11: CAJA Nº 12 | L11: BOLSAS DE 120 X 110 | O11: 9 | P11: 20 | Q11: =IFERROR(IF(AO11>1,AO11,60*60*8*O11/P11/E11),"") -> 16.2 | R11: =IFERROR(60*60*8*O11/E11/Q11,"") -> 20 | S11: =IFERROR(R11/8,"") -> 2.5 | T11: =IFERROR(IF(R11>2,S11,""),"") -> 2.5 | CH11: 3 | CI11: 60
A12: 1910 | B12: Venta Normal | C12: GN | D12: ART. 1550 | E12: 400 | F12: 0.0146 | G12: 0.0105 | H12: =(F12-G12)/F12 -> 0.28082192 | I12: PVC | J12: PVC CRISTAL 460 x 400 | K12: CAJA Nº 2 | L12: BOLSAS DE 120 X 80 | O12: 9 | P12: 70 | Q12: =IFERROR(IF(AO12>1,AO12,60*60*8*O12/P12/E12),"") -> 6.6 | R12: =IFERROR(60*60*8*O12/E12/Q12,"") -> 98.181818 | S12: =IFERROR(R12/8,"") -> 12.272727 | T12: =IFERROR(IF(R12>2,S12,""),"") -> 12.272727 | AD12: 45519 | AE12: 14 | AF12: 1.4 | AG12: 0.4 | AH12: 1.4 | AI12: 0.4 | AJ12: 1 | AK12: 0.15 | AL12: 0.19 | AM12: 0.6 | AN12: 0.4 | AO12: 6.6 | AP12: 58 | AQ12: 109 | AR12: 109 | AS12: 109 | AT12: 40 | AU12: 20 | AV12: 40 | AW12: 20 | AX12: 7' | AY12: 465 | AZ12: Normal | BA12: 1100 | BB12: 10 | CH12: 1 | CI12: 75
A13: 726 | B13: Venta Normal | C13: GN | D13: ART. 1550 OPS | E13: 800 | F13: 0.0115 | G13: 0.008 | H13: =(F13-G13)/F13 -> 0.30434783 | I13: OPS | J13: DEXTON PS 825EH | K13: CAJA Nº 4/1 | L13: BOLSAS DE 120 X 125 | O13: 9 | P13: 24 | Q13: =IFERROR(IF(AO13>1,AO13,60*60*8*O13/P13/E13),"") -> 13.5 | R13: =IFERROR(60*60*8*O13/E13/Q13,"") -> 24 | S13: =IFERROR(R13/8,"") -> 3 | T13: =IFERROR(IF(R13>2,S13,""),"") -> 3 | CH13: 4 | CI13: 77
A14: 1914 | B14: Venta Normal | C14: GN | D14: ART. 1560 | E14: 300 | F14: 0.0262 | G14: 0.0214 | H14: =(F14-G14)/F14 -> 0.18320611 | I14: PVC | J14: PVC CRISTAL 575 x 250 | K14: CAJA Nº 2 | L14: BOLSAS DE 120 X 80 | M14: 1 | N14: 300 | O14: 3 | P14: 45 | Q14: =IFERROR(IF(AO14>1,AO14,60*60*8*O14/P14/E14),"") -> 4.4 | R14: =IFERROR(60*60*8*O14/E14/Q14,"") -> 65.454545 | S14: =IFERROR(R14/8,"") -> 8.1818182 | T14: =IFERROR(IF(R14>2,S14,""),"") -> 8.1818182 | AD14: 45538 | AE14: 15 | AF14: 0.9 | AG14: 0.2 | AH14: 1 | AI14: 0.2 | AJ14: 0.55 | AK14: 0.17 | AL14: 0.17 | AM14: 0.4 | AN14: 0.3 | AO14: 4.4 | AP14: 61 | AQ14: 103 | AR14: 103 | AS14: 103 | AT14: 38 | AU14: 20 | AV14: 40 | AW14: 20 | AX14: 100 | AY14: 365 | AZ14: Normal | BA14: 1500 | BB14: 10 | BE14: =AO14/4.5-1 -> -0.022222222 | BF14: 20/3/2024 / 22/7/24 | BG14: 13/15 | BH14: 1 / 1,5 | BI14: 0,1 / 0,2 | BJ14: 1,1 /1,3 | BK14: 0,1 / 0,2 | BL14: 0,8 / 1,00 | BM14: 0,2 / 0,18 | BN14: 0,22 / 0,15 | BO14: 0,4 / 0,45 | BP14: 0,3 /0,2 | BQ14: 4,5 / 5,6 | BR14: 59 / 62 | BS14: 104 / 103 | BT14: 104 / 103 | BU14: 104 / 103 | BV14: 45 / 38 | BW14: 20 / 20 | BX14: 40 / 40 | BY14: 20 / 20 | BZ14: 100 / 100 | CA14: 359 / 365 | CB14: Normal | CC14: 700 / 1500 | CD14: 10 / 10 | CH14: 6 | CI14: 53
A15: 1825 | B15: Venta Normal | C15: GN | D15: ART. 1560 - OBSOLETO | E15: 500 | F15: 0.0262 | G15: 0.0214 | H15: =(F15-G15)/F15 -> 0.18320611 | I15: PVC | J15: PVC CRISTAL 575 x 250 | K15: CAJA Nº 15 | L15: BOLSAS DE 120 X 110 | O15: 3 | P15: 33 | Q15: =IFERROR(IF(AO15>1,AO15,60*60*8*O15/P15/E15),"") -> 5.2363636 | R15: =IFERROR(60*60*8*O15/E15/Q15,"") -> 33 | S15: =IFERROR(R15/8,"") -> 4.125 | T15: =IFERROR(IF(R15>2,S15,""),"") -> 4.125 | CH15: 6 | CI15: 81
A16: 1813 | B16: Discontinuado | C16: GN | D16: ART. 1560 PVC (300M) | E16: 500 | F16: 0.0311 | G16: 0.0254 | H16: =(F16-G16)/F16 -> 0.18327974 | I16: PVC | J16: PVC CRISTAL 570 x 300 | K16: CAJA Nº 16 | L16: BOLSAS DE 120 X 125 | O16: 3 | Q16: =IFERROR(IF(AO16>1,AO16,60*60*8*O16/P16/E16),"") | R16: =IFERROR(60*60*8*O16/E16/Q16,"") | S16: =IFERROR(R16/8,"") | T16: =IFERROR(IF(R16>2,S16,""),"") | CH16: 4 | CI16: 41
A17: 104 | B17: Venta Normal | C17: GN | D17: ART. 1610 (200) | E17: 200 | F17: 0.0115 | G17: 0.0087 | H17: =(F17-G17)/F17 -> 0.24347826 | I17: PVC | J17: PVC CRISTAL 520 x 250 | O17: 6 | P17: 70 | Q17: =IFERROR(IF(AO17>1,AO17,60*60*8*O17/P17/E17),"") -> 7.9 | R17: =IFERROR(60*60*8*O17/E17/Q17,"") -> 109.36709 | S17: =IFERROR(R17/8,"") -> 13.670886 | T17: =IFERROR(IF(R17>2,S17,""),"") -> 13.670886 | AD17: 45607 | AE17: 14 | AF17: 2 | AG17: 0.45 | AH17: 2.7 | AI17: 0.45 | AJ17: 0.6 | AK17: 0.2 | AL17: 0.14 | AM17: 0.6 | AN17: 0.3 | AO17: 7.9 | AP17: 42 | AQ17: 102 | AR17: 102 | AS17: 102 | AT17: 40 | AU17: 20 | AV17: 40 | AW17: 20 | AX17: 70 | AY17: 360 | AZ17: Normal | BA17: 900 | BB17: 10 | CH17: 3 | CI17: 86
A18: 43 | B18: Discontinuado | C18: GN | D18: ART. 1610 OPS | E18: 300 | F18: 0.0091 | G18: 0.0064 | H18: =(F18-G18)/F18 -> 0.2967033 | I18: OPS | J18: UNICLEAR CRISTAL OPS 520 x 250 | K18: CAJA Nº 14 | L18: BOLSAS DE 120 X 110 | O18: 6 | Q18: =IFERROR(IF(AO18>1,AO18,60*60*8*O18/P18/E18),"") | R18: =IFERROR(60*60*8*O18/E18/Q18,"") | S18: =IFERROR(R18/8,"") | T18: =IFERROR(IF(R18>2,S18,""),"") | CH18: 1 | CI18: 71
A19: 105 | B19: Venta Normal | C19: GN | D19: ART. 1690 (200) | E19: 200 | F19: 0.0231 | G19: 0.0173 | H19: =(F19-G19)/F19 -> 0.25108225 | I19: PVC | J19: PVC CRISTAL 520 x 500 | K19: CAJA Nº 16 | L19: BOLSAS DE 120 X 110 | M19: 4 | N19: 50 | O19: 6 | P19: 46 | Q19: =IFERROR(IF(AO19>1,AO19,60*60*8*O19/P19/E19),"") -> 11.4 | R19: =IFERROR(60*60*8*O19/E19/Q19,"") -> 75.789474 | S19: =IFERROR(R19/8,"") -> 9.4736842 | T19: =IFERROR(IF(R19>2,S19,""),"") -> 9.4736842 | AD19: 45604 | AE19: 13 | AF19: 3.5 | AG19: 0.4 | AH19: 3.7 | AI19: 0.5 | AJ19: 1.2 | AK19: 0.19 | AL19: 0.16 | AM19: 0.9 | AN19: 0.35 | AO19: 11.4 | AP19: 50 | AQ19: 107 | AR19: 107 | AS19: 107 | AT19: 49 | AU19: 20 | AV19: 40 | AW19: 20 | AX19: 65 | AY19: 386 | AZ19: Normal | BA19: 1000 | CH19: 4 | CI19: 37
A20: 113 | B20: Venta Normal | C20: GN | D20: ART. 1690 BASE | E20: 300 | F20: 0.0231 | G20: 0.0173 | H20: =(F20-G20)/F20 -> 0.25108225 | I20: PVC | J20: PVC CRISTAL 520 x 500 | K20: CAJA Nº 15 | L20: BOLSAS DE 120 X 110 | O20: 6 | P20: 26 | Q20: =IFERROR(IF(AO20>1,AO20,60*60*8*O20/P20/E20),"") -> 22.153846 | R20: =IFERROR(60*60*8*O20/E20/Q20,"") -> 26 | S20: =IFERROR(R20/8,"") -> 3.25 | T20: =IFERROR(IF(R20>2,S20,""),"") -> 3.25 | CH20: 6 | CI20: 69
A21: 107 | B21: Venta Normal | C21: GN | D21: ART. 1690 BASE Y TAPA | E21: 200 | F21: 0.0346 | G21: 0.026 | H21: =(F21-G21)/F21 -> 0.24855491 | I21: PVC | J21: PVC CRISTAL 100 x 10000 | O21: 6 | P21: 55 | Q21: =IFERROR(IF(AO21>1,AO21,60*60*8*O21/P21/E21),"") -> 15.709091 | R21: =IFERROR(60*60*8*O21/E21/Q21,"") -> 55 | S21: =IFERROR(R21/8,"") -> 6.875 | T21: =IFERROR(IF(R21>2,S21,""),"") -> 6.875 | CH21: 5 | CI21: 33
A22: 44 | B22: Venta Normal | C22: GN | D22: ART. 1690 OPS | E22: 300 | F22: 0.0217 | G22: 0.015 | H22: =(F22-G22)/F22 -> 0.30875576 | I22: OPS | J22: UNICLEAR CRISTAL OPS 520 x 600 | K22: CAJA Nº 15 | L22: BOLSAS DE 120 X 110 | O22: 6 | P22: 40 | Q22: =IFERROR(IF(AO22>1,AO22,60*60*8*O22/P22/E22),"") -> 14.4 | R22: =IFERROR(60*60*8*O22/E22/Q22,"") -> 40 | S22: =IFERROR(R22/8,"") -> 5 | T22: =IFERROR(IF(R22>2,S22,""),"") -> 5 | CH22: 6 | CI22: 43
A23: 1911 | B23: Venta Normal | C23: GN | D23: ART. 1810 | E23: 300 | F23: 0.0168 | G23: 0.013 | H23: =(F23-G23)/F23 -> 0.22619048 | I23: PVC | J23: PVC CRISTAL 380 x 300 | K23: CAJA Nº 2 | L23: BOLSAS DE 120 X 80 | O23: 4 | P23: 25 | Q23: =IFERROR(IF(AO23>1,AO23,60*60*8*O23/P23/E23),"") -> 15.36 | R23: =IFERROR(60*60*8*O23/E23/Q23,"") -> 25 | S23: =IFERROR(R23/8,"") -> 3.125 | T23: =IFERROR(IF(R23>2,S23,""),"") -> 3.125 | CH23: 5 | CI23: 44
A24: 1935 | B24: Venta Normal | C24: GN | D24: ART. 1810 NEGRO | E24: 300 | F24: 0.0154 | G24: 0.0105 | H24: =(F24-G24)/F24 -> 0.31818182 | I24: PVC | J24: PAI NEGRO 380 x 350 | K24: CAJA Nº 2 | L24: BOLSAS DE 120 X 80 | O24: 4 | P24: 30 | Q24: =IFERROR(IF(AO24>1,AO24,60*60*8*O24/P24/E24),"") -> 12.8 | R24: =IFERROR(60*60*8*O24/E24/Q24,"") -> 30 | S24: =IFERROR(R24/8,"") -> 3.75 | T24: =IFERROR(IF(R24>2,S24,""),"") -> 3.75 | CH24: 5 | CI24: 71
A25: 731 | B25: Venta Normal | C25: GN | D25: ART. 1810 OPS | E25: 540 | F25: 0.0132 | G25: 0.0094 | H25: =(F25-G25)/F25 -> 0.28787879 | I25: OPS | J25: UNICLEAR CRISTAL OPS 455 x 400 | K25: CAJA Nº 4/1 | L25: BOLSAS DE 120 X 125 | O25: 4 | P25: 28 | Q25: =IFERROR(IF(AO25>1,AO25,60*60*8*O25/P25/E25),"") -> 7.6190476 | R25: =IFERROR(60*60*8*O25/E25/Q25,"") -> 28 | S25: =IFERROR(R25/8,"") -> 3.5 | T25: =IFERROR(IF(R25>2,S25,""),"") -> 3.5 | CH25: 4 | CI25: 90
A26: 732 | B26: Venta Normal | C26: GN | D26: ART. 1810 PAI NEGRO | E26: 540 | F26: 0.0243 | G26: 0.0105 | H26: =(F26-G26)/F26 -> 0.56790123 | I26: HIPST | J26: PAI NEGRO 600 x 350 | K26: CAJA Nº 4/1 | L26: BOLSAS DE 120 X 125 | O26: 4 | P26: 28 | Q26: =IFERROR(IF(AO26>1,AO26,60*60*8*O26/P26/E26),"") -> 7.6190476 | R26: =IFERROR(60*60*8*O26/E26/Q26,"") -> 28 | S26: =IFERROR(R26/8,"") -> 3.5 | T26: =IFERROR(IF(R26>2,S26,""),"") -> 3.5 | CH26: 5 | CI26: 72
A27: 1912 | B27: Venta Normal | C27: GN | D27: ART. 1845 | E27: 300 | F27: 0.0223 | G27: 0.0162 | H27: =(F27-G27)/F27 -> 0.2735426 | I27: PVC | J27: PVC CRISTAL 380 x 400 | K27: CAJA Nº 15 | L27: BOLSAS DE 120 X 110 | O27: 4 | P27: 25 | Q27: =IFERROR(IF(AO27>1,AO27,60*60*8*O27/P27/E27),"") -> 15.36 | R27: =IFERROR(60*60*8*O27/E27/Q27,"") -> 25 | S27: =IFERROR(R27/8,"") -> 3.125 | T27: =IFERROR(IF(R27>2,S27,""),"") -> 3.125 | CH27: 1 | CI27: 40
A28: 729 | B28: Venta Normal | C28: GN | D28: ART. 1845 OPS | E28: 540 | F28: 0.0176 | G28: 0.0128 | H28: =(F28-G28)/F28 -> 0.27272727 | I28: OPS | J28: UNICLEAR CRISTAL OPS 380 x 400 | K28: CAJA Nº 4/1 | L28: BOLSAS DE 120 X 125 | O28: 4 | P28: 30 | Q28: =IFERROR(IF(AO28>1,AO28,60*60*8*O28/P28/E28),"") -> 7.1111111 | R28: =IFERROR(60*60*8*O28/E28/Q28,"") -> 30 | S28: =IFERROR(R28/8,"") -> 3.75 | T28: =IFERROR(IF(R28>2,S28,""),"") -> 3.75 | CH28: 4 | CI28: 60
A29: 1913 | B29: Venta Normal | C29: GN | D29: ART. 1860 | E29: 300 | F29: 0.0251 | G29: 0.0182 | H29: =(F29-G29)/F29 -> 0.2749004 | I29: PVC | J29: PVC CRISTAL 380 x 450 | K29: CAJA Nº 15 | L29: BOLSAS DE 120 X 110 | O29: 4 | P29: 25 | Q29: =IFERROR(IF(AO29>1,AO29,60*60*8*O29/P29/E29),"") -> 15.36 | R29: =IFERROR(60*60*8*O29/E29/Q29,"") -> 25 | S29: =IFERROR(R29/8,"") -> 3.125 | T29: =IFERROR(IF(R29>2,S29,""),"") -> 3.125 | CH29: 5 | CI29: 41
A30: 730 | B30: Venta Normal | C30: GN | D30: ART. 1860 OPS | E30: 540 | F30: 0.0198 | G30: 0.0155 | H30: =(F30-G30)/F30 -> 0.21717172 | I30: OPS | J30: DEXTON PS945EH | K30: CAJA Nº 4/1 | L30: BOLSAS DE 120 X 125 | O30: 4 | P30: 28 | Q30: =IFERROR(IF(AO30>1,AO30,60*60*8*O30/P30/E30),"") -> 7.6190476 | R30: =IFERROR(60*60*8*O30/E30/Q30,"") -> 28 | S30: =IFERROR(R30/8,"") -> 3.5 | T30: =IFERROR(IF(R30>2,S30,""),"") -> 3.5 | CH30: 3 | CI30: 55
A31: 1814 | B31: Venta Normal | C31: GN | D31: ART. 2050 | E31: 520 | F31: 0.025 | G31: 0.0204 | H31: =(F31-G31)/F31 -> 0.184 | I31: PET | J31: PET CRISTAL 460 x 250 | K31: CAJA Nº 12 | L31: BOLSAS DE 120 X 110 | O31: 2 | P31: 34 | Q31: =IFERROR(IF(AO31>1,AO31,60*60*8*O31/P31/E31),"") -> 3.2579186 | R31: =IFERROR(60*60*8*O31/E31/Q31,"") -> 34 | S31: =IFERROR(R31/8,"") -> 4.25 | T31: =IFERROR(IF(R31>2,S31,""),"") -> 4.25 | CH31: 5 | CI31: 52
A32: 1915 | B32: Venta Normal | C32: GN | D32: ART. 2050 (X 300) | E32: 300 | F32: 0.025 | G32: 0.0204 | H32: =(F32-G32)/F32 -> 0.184 | I32: PET | J32: PET CRISTAL 460 x 250 | K32: CAJA Nº 1/2 | L32: BOLSAS DE 120 X 80 | M32: 1 | N32: 300 | O32: 2 | P32: 45 | Q32: =IFERROR(IF(AO32>1,AO32,60*60*8*O32/P32/E32),"") -> 4 | R32: =IFERROR(60*60*8*O32/E32/Q32,"") -> 48 | S32: =IFERROR(R32/8,"") -> 6 | T32: =IFERROR(IF(R32>2,S32,""),"") -> 6 | AD32: 45411 | AE32: 16 | AF32: 0.9 | AG32: 0.1 | AH32: 1 | AI32: 0.1 | AJ32: 0.3 | AK32: 0.36 | AL32: 0.2 | AM32: 0.14 | AN32: 0.5 | AO32: 4 | AP32: 45 | AQ32: 104 | AR32: 109 | AS32: 114 | AT32: 40 | AY32: 383 | BC32: 111 | BD32: 112 | CH32: 5 | CI32: 53
A33: 1815 | B33: Venta Normal | C33: GN | D33: ART. 2060 | E33: 520 | F33: 0.025 | G33: 0.0204 | H33: =(F33-G33)/F33 -> 0.184 | I33: PET | J33: PET CRISTAL 460 x 250 | K33: CAJA Nº 12 | L33: BOLSAS DE 120 X 110 | O33: 2 | P33: 34 | Q33: =IFERROR(IF(AO33>1,AO33,60*60*8*O33/P33/E33),"") -> 3.2579186 | R33: =IFERROR(60*60*8*O33/E33/Q33,"") -> 34 | S33: =IFERROR(R33/8,"") -> 4.25 | T33: =IFERROR(IF(R33>2,S33,""),"") -> 4.25 | CH33: 5 | CI33: 30
A34: 1916 | B34: Venta Normal | C34: GN | D34: ART. 2060 (X 300) | E34: 300 | F34: 0.025 | G34: 0.0204 | H34: =(F34-G34)/F34 -> 0.184 | I34: PET | J34: PET CRISTAL 460 x 250 | K34: CAJA Nº 1/2 | L34: BOLSAS DE 120 X 80 | M34: 1 | N34: 300 | O34: 2 | P34: 50 | Q34: =IFERROR(IF(AO34>1,AO34,60*60*8*O34/P34/E34),"") -> 3.6 | R34: =IFERROR(60*60*8*O34/E34/Q34,"") -> 53.333333 | S34: =IFERROR(R34/8,"") -> 6.6666667 | T34: =IFERROR(IF(R34>2,S34,""),"") -> 6.6666667 | U34: =1000/R34 -> 18.75 | V34: =R34*0.85 -> 45.333333 | AD34: 45378 | AE34: 14 / 15 | AF34: 0.8 | AG34: 0.1 | AH34: 1 | AI34: 0.13 | AJ34: 0.25 | AK34: 0.14 | AL34: 0.21 | AM34: 0.3 | AN34: 0.2 | AO34: 3.6 | AP34: 48 | AQ34: 103 | AR34: 103 | AS34: 103 | AT34: 40 | AU34: 20 | AV34: 40 | AW34: 20 | AX34: 100 | AY34: 294 | AZ34: Normal | BA34: 1200 | BB34: 10 | CH34: 2 | CI34: 44
A35: 1138 | B35: Venta Normal | C35: GN | D35: ART. 2060 (X 300) (DISCONTINUADO) | E35: 300 | F35: 0.025 | G35: 0.0204 | H35: =(F35-G35)/F35 -> 0.184 | I35: PET | J35: PET CRISTAL 460 x 250 | K35: CAJA Nº 1/2 | L35: BOLSAS DE 120 X 80 | O35: 2 | P35: 45 | Q35: =IFERROR(IF(AO35>1,AO35,60*60*8*O35/P35/E35),"") -> 4.2666667 | R35: =IFERROR(60*60*8*O35/E35/Q35,"") -> 45 | S35: =IFERROR(R35/8,"") -> 5.625 | T35: =IFERROR(IF(R35>2,S35,""),"") -> 5.625 | CH35: 6 | CI35: 80
A36: 1816 | B36: Venta Normal | C36: GN | D36: ART. 2060 MPH | E36: 520 | F36: 0.025 | G36: 0.0204 | H36: =(F36-G36)/F36 -> 0.184 | I36: PVC | J36: PVC CRISTAL 460 x 250 | K36: CAJA Nº 4/1 | L36: BOLSAS DE 120 X 125 | O36: 2 | P36: 28 | Q36: =IFERROR(IF(AO36>1,AO36,60*60*8*O36/P36/E36),"") -> 3.956044 | R36: =IFERROR(60*60*8*O36/E36/Q36,"") -> 28 | S36: =IFERROR(R36/8,"") -> 3.5 | T36: =IFERROR(IF(R36>2,S36,""),"") -> 3.5 | CH36: 2 | CI36: 32
A37: 2079 | B37: Venta Normal | C37: GN | D37: ART. 2060 MPH | E37: 200 | F37: 0.025 | G37: 0.0204 | H37: =(F37-G37)/F37 -> 0.184 | I37: PVC | J37: PVC CRISTAL 460 x 250 | K37: CAJA Nº 1/2 | L37: BOLSAS DE 120 X 80 | O37: 2 | P37: 73 | Q37: =IFERROR(IF(AO37>1,AO37,60*60*8*O37/P37/E37),"") -> 3.9452055 | R37: =IFERROR(60*60*8*O37/E37/Q37,"") -> 73 | S37: =IFERROR(R37/8,"") -> 9.125 | T37: =IFERROR(IF(R37>2,S37,""),"") -> 9.125 | CH37: 2 | CI37: 57
A38: 1817 | B38: Venta Normal | C38: GN | D38: ART. 2075 | E38: 200 | F38: 0.0403 | G38: 0.0348 | H38: =(F38-G38)/F38 -> 0.13647643 | I38: PVC | J38: PVC CRISTAL 480 x 250 | K38: CAJA Nº 4/1 | L38: BOLSAS DE 120 X 125 | O38: 2 | P38: 40 | Q38: =IFERROR(IF(AO38>1,AO38,60*60*8*O38/P38/E38),"") -> 7.2 | R38: =IFERROR(60*60*8*O38/E38/Q38,"") -> 40 | S38: =IFERROR(R38/8,"") -> 5 | T38: =IFERROR(IF(R38>2,S38,""),"") -> 5 | CH38: 6 | CI38: 82
A39: 1818 | B39: Venta Normal | C39: GN | D39: ART. 2095 | E39: 200 | F39: 0.0299 | G39: 0.0247 | H39: =(F39-G39)/F39 -> 0.17391304 | I39: PVC | J39: PVC CRISTAL 460 x 300 | K39: CAJA Nº 1/2 | L39: BOLSAS DE 120 X 80 | M39: 1 | N39: 200 | O39: 2 | P39: 58 | Q39: =IFERROR(IF(AO39>1,AO39,60*60*8*O39/P39/E39),"") -> 4.6 | R39: =IFERROR(60*60*8*O39/E39/Q39,"") -> 62.608696 | S39: =IFERROR(R39/8,"") -> 7.826087 | T39: =IFERROR(IF(R39>2,S39,""),"") -> 7.826087 | Z39: Christian | AD39: 45391 | AE39: 15 | AF39: 1 | AG39: 0.1 | AH39: 1 | AI39: 0.1 | AJ39: 0.5 | AK39: 0.2 | AL39: 0.16 | AM39: 0.7 | AN39: 0.3 | AO39: 4.6 | AP39: 45 | AQ39: 106 | AR39: 106 | AS39: 106 | AT39: 50 | AU39: 20 | AV39: 40 | AW39: 20 | AX39: 100 | AY39: 297 | AZ39: Normal | BA39: 1000 | BB39: 10 | CH39: 3 | CI39: 52
A40: 1819 | B40: Venta Normal | C40: GN | D40: ART. 2450 | E40: 360 | F40: 0.0343 | G40: 0.0283 | H40: =(F40-G40)/F40 -> 0.17492711 | I40: PVC | J40: PVC CRISTAL 560 x 250 | K40: CAJA Nº 17 | L40: BOLSAS DE 120 X 110 | M40: 2 | N40: 180 | O40: 2 | P40: 41 | Q40: =IFERROR(IF(AO40>1,AO40,60*60*8*O40/P40/E40),"") -> 3.6 | R40: =IFERROR(60*60*8*O40/E40/Q40,"") -> 44.444444 | S40: =IFERROR(R40/8,"") -> 5.5555556 | T40: =IFERROR(IF(R40>2,S40,""),"") -> 5.5555556 | Z40: Christian | AD40: 45504 | AE40: 12 | AF40: 0.8 | AG40: 0.15 | AH40: 0.8 | AI40: 0.15 | AJ40: 0.4 | AK40: 0.12 | AL40: 0.16 | AM40: 0.33 | AN40: 0.15 | AO40: 3.6 | AP40: 51 | AQ40: 104 | AR40: 104 | AS40: 104 | AT40: 40 | AU40: 30 | AV40: 40 | AW40: 40 | AX40: 100 | AY40: 330 | AZ40: Normal | BA40: 2400 | BB40: 10 | CH40: 3 | CI40: 48
A41: 1820 | B41: Venta Normal | C41: GN | D41: ART. 2465 | E41: 900 | F41: 0.0184 | G41: 0.0158 | H41: =(F41-G41)/F41 -> 0.14130435 | I41: PVC | J41: PVC CRISTAL 420 x 250 | K41: CAJA Nº 4/1 | L41: BOLSAS DE 120 X 125 | O41: 4 | P41: 20 | Q41: =IFERROR(IF(AO41>1,AO41,60*60*8*O41/P41/E41),"") -> 6.4 | R41: =IFERROR(60*60*8*O41/E41/Q41,"") -> 20 | S41: =IFERROR(R41/8,"") -> 2.5 | T41: =IFERROR(IF(R41>2,S41,""),"") -> 2.5 | CH41: 5 | CI41: 33
A42: 1922 | B42: Venta Normal | C42: GN | D42: ART. 2465 | E42: 300 | F42: 0.0184 | G42: 0.0158 | H42: =(F42-G42)/F42 -> 0.14130435 | I42: PVC | J42: PVC CRISTAL 420 x 250 | K42: CAJA Nº 2 | L42: BOLSAS DE 120 X 80 | M42: 3 | N42: 100 | O42: 4 | P42: 60 | Q42: =IFERROR(IF(AO42>1,AO42,60*60*8*O42/P42/E42),"") -> 5.1 | R42: =IFERROR(60*60*8*O42/E42/Q42,"") -> 75.294118 | S42: =IFERROR(R42/8,"") -> 9.4117647 | T42: =IFERROR(IF(R42>2,S42,""),"") -> 9.4117647 | AD42: 45517 | AE42: 15 | AF42: 1.4 | AG42: 0.3 | AH42: 1.4 | AI42: 0.3 | AJ42: 0.5 | AK42: 0.18 | AL42: 0.18 | AM42: 0.4 | AN42: 0.17 | AO42: 5.1 | AP42: 52 | AQ42: 109 | AR42: 109 | AS42: 107 | AT42: 38 | AU42: 20 | AV42: 40 | AW42: 20 | AX42: 100 | AY42: 450 | AZ42: Normal | BA42: 2000 | BB42: 10 | BE42: =AO42/BQ42-1 -> -0.019230769 | BF42: 45404 | BG42: 12 | BH42: 1.3 | BI42: 0.3 | BJ42: 1.2 | BK42: 0.3 | BL42: 0.7 | BM42: 0.15 | BN42: 0.18 | BO42: 0.4 | BP42: 0.3 | BQ42: 5.2 | BR42: 49 | BS42: 106 | BT42: 106 | BU42: 106 | BV42: 40 | BW42: 38 | BX42: 40 | BY42: 40 | BZ42: 101 | CA42: 459 | CB42: Normal | CC42: 2000 | CD42: 10 | CH42: 1 | CI42: 41
A43: 1796 | B43: Discontinuado | C43: GN | D43: ART. 2465 OPS | E43: 900 | F43: 0.0101 | G43: 0.0114 | H43: =(F43-G43)/F43 -> -0.12871287 | I43: OPS | J43: UNICLEAR CRISTAL OPS 460 x 250 | K43: CAJA Nº 4/1 | L43: BOLSAS DE 120 X 125 | O43: 4 | Q43: =IFERROR(IF(AO43>1,AO43,60*60*8*O43/P43/E43),"") | R43: =IFERROR(60*60*8*O43/E43/Q43,"") | S43: =IFERROR(R43/8,"") | T43: =IFERROR(IF(R43>2,S43,""),"") | CH43: 5 | CI43: 69
A44: 2088 | B44: Venta Normal | C44: GN | D44: ART. 2465 PET | E44: 300 | F44: 0.0184 | G44: 0.0158 | H44: =(F44-G44)/F44 -> 0.14130435 | I44: PET | J44: PET CRISTAL 420 x 250 | K44: CAJA Nº 2 | L44: BOLSAS DE 120 X 80 | M44: 3 | N44: 100 | O44: 4 | P44: 60 | Q44: =IFERROR(IF(AO44>1,AO44,60*60*8*O44/P44/E44),"") -> 5.1 | R44: =IFERROR(60*60*8*O44/E44/Q44,"") -> 75.294118 | S44: =IFERROR(R44/8,"") -> 9.4117647 | T44: =IFERROR(IF(R44>2,S44,""),"") -> 9.4117647 | AD44: 45517 | AE44: 15 | AF44: 1.4 | AG44: 0.3 | AH44: 1.4 | AI44: 0.3 | AJ44: 0.5 | AK44: 0.18 | AL44: 0.18 | AM44: 0.4 | AN44: 0.17 | AO44: 5.1 | AP44: 52 | AQ44: 109 | AR44: 109 | AS44: 107 | AT44: 38 | AU44: 20 | AV44: 40 | AW44: 20 | AX44: 100 | AY44: 450 | AZ44: Normal | BA44: 2000 | BB44: 10 | BE44: =AO44/BQ44-1 -> -0.019230769 | BF44: 45404 | BG44: 12 | BH44: 1.3 | BI44: 0.3 | BJ44: 1.2 | BK44: 0.3 | BL44: 0.7 | BM44: 0.15 | BN44: 0.18 | BO44: 0.4 | BP44: 0.3 | BQ44: 5.2 | BR44: 49 | BS44: 106 | BT44: 106 | BU44: 106 | BV44: 40 | BW44: 38 | BX44: 40 | BY44: 40 | BZ44: 101 | CA44: 459 | CB44: Normal | CC44: 2000 | CD44: 10 | CH44: 5 | CI44: 77
A45: 1821 | B45: Venta Normal | C45: GN | D45: ART. 2475 | E45: 360 | F45: 0.0343 | G45: 0.0283 | H45: =(F45-G45)/F45 -> 0.17492711 | I45: PVC | J45: PVC CRISTAL 560 x 250 | K45: CAJA Nº 17 | L45: BOLSAS DE 120 X 110 | M45: 2 | N45: 180 | O45: 2 | P45: 41 | Q45: =IFERROR(IF(AO45>1,AO45,60*60*8*O45/P45/E45),"") -> 3.6 | R45: =IFERROR(60*60*8*O45/E45/Q45,"") -> 44.444444 | S45: =IFERROR(R45/8,"") -> 5.5555556 | T45: =IFERROR(IF(R45>2,S45,""),"") -> 5.5555556 | Z45: Christian | AD45: 45376 | AE45: 12 | AF45: 1.1 | AG45: 0.1 | AH45: 1.1 | AI45: 0.1 | AJ45: 0.45 | AK45: 0.12 | AL45: 0.22 | AM45: 0.4 | AN45: 0.18 | AO45: 3.6 | AP45: 46 | AQ45: 106 | AR45: 106 | AS45: 106 | AT45: 40 | AU45: 30 | AV45: 40 | AW45: 40 | AX45: 101 | AY45: 331 | AZ45: Normal | BA45: 2500 | BB45: 10 | CH45: 6 | CI45: 64
A46: 2090 | B46: Venta Normal | C46: GN | D46: ART. 2475 PET | E46: 360 | F46: 0.0343 | G46: 0.0283 | H46: =(F46-G46)/F46 -> 0.17492711 | I46: PET | J46: PET CRISTAL 560 x 250 | K46: CAJA Nº 17 | L46: BOLSAS DE 120 X 110 | M46: 2 | N46: 180 | O46: 2 | P46: 41 | Q46: =IFERROR(IF(AO46>1,AO46,60*60*8*O46/P46/E46),"") -> 3.6 | R46: =IFERROR(60*60*8*O46/E46/Q46,"") -> 44.444444 | S46: =IFERROR(R46/8,"") -> 5.5555556 | T46: =IFERROR(IF(R46>2,S46,""),"") -> 5.5555556 | Z46: Christian | AD46: 45376 | AE46: 12 | AF46: 1.1 | AG46: 0.1 | AH46: 1.1 | AI46: 0.1 | AJ46: 0.45 | AK46: 0.12 | AL46: 0.22 | AM46: 0.4 | AN46: 0.18 | AO46: 3.6 | AP46: 46 | AQ46: 106 | AR46: 106 | AS46: 106 | AT46: 40 | AU46: 30 | AV46: 40 | AW46: 40 | AX46: 101 | AY46: 331 | AZ46: Normal | BA46: 2500 | BB46: 10 | CH46: 6 | CI46: 55
A47: 1822 | B47: Venta Normal | C47: GN | D47: ART. 2508 | E47: 200 | F47: 0.0506 | G47: 0.0423 | H47: =(F47-G47)/F47 -> 0.16403162 | I47: PET | J47: PET CRISTAL 560 x 300 | K47: CAJA Nº 3 | L47: BOLSAS DE 120 X 80 | M47: 2 | N47: 100 | O47: 2 | P47: 55 | Q47: =IFERROR(IF(AO47>1,AO47,60*60*8*O47/P47/E47),"") -> 4.8 | R47: =IFERROR(60*60*8*O47/E47/Q47,"") -> 60 | S47: =IFERROR(R47/8,"") -> 7.5 | T47: =IFERROR(IF(R47>2,S47,""),"") -> 7.5 | AD47: 45559 | AE47: 13 | AF47: 0.9 | AG47: 0.2 | AH47: 1 | AI47: 0.33 | AJ47: 0.8 | AK47: 0.15 | AL47: 0.21 | AM47: 0.4 | AN47: 0.4 | AO47: 4.8 | AP47: 55 | AQ47: 112 | AR47: 108 | AS47: 109 | AT47: 45 | AU47: 30 | AV47: 80 | AW47: 30 | AX47: 100 | AY47: 400 | AZ47: Normal | BA47: 400 | BB47: 10 | CH47: 5 | CI47: 49
A48: 1823 | B48: Venta Normal | C48: GN | D48: ART. 2510 | E48: 200 | F48: 0.0506 | G48: 0.0423 | H48: =(F48-G48)/F48 -> 0.16403162 | I48: PET | J48: PET CRISTAL 560 x 300 | K48: CAJA Nº 3 | L48: BOLSAS DE 120 X 80 | M48: 2 | N48: 100 | O48: 2 | P48: 55 | Q48: =IFERROR(IF(AO48>1,AO48,60*60*8*O48/P48/E48),"") -> 4.6 | R48: =IFERROR(60*60*8*O48/E48/Q48,"") -> 62.608696 | S48: 7,8 | T48: =IFERROR(IF(R48>2,S48,""),"") -> 7,8 | Z48: Christian | AD48: 45419 | AE48: 12 | AF48: 0.9 | AG48: 0.3 | AH48: 1 | AI48: 0.1 | AJ48: 0.14 | AK48: 0.19 | AL48: 0.7 | AM48: 0.6 | AN48: 0.25 | AO48: 4.6 | AP48: 50 | AQ48: 110 | AR48: 110 | AS48: 108 | AT48: 40 | AU48: 30 | AV48: 40 | AW48: 40 | AX48: 100 | AY48: 406 | AZ48: Normal | BA48: 1500 | BB48: 10 | CH48: 4 | CI48: 40
A49: 2021 | B49: Venta Normal | C49: GN | D49: ART. 2510 | E49: 200 | F49: 0.0506 | G49: 0.0423 | H49: =(F49-G49)/F49 -> 0.16403162 | I49: PVC | J49: PVC CRISTAL 560 x 300 | K49: CAJA Nº 3 | L49: BOLSAS DE 120 X 80 | M49: 2 | N49: 100 | O49: 2 | P49: 55 | Q49: =IFERROR(IF(AO49>1,AO49,60*60*8*O49/P49/E49),"") -> 4.6 | R49: =IFERROR(60*60*8*O49/E49/Q49,"") -> 62.608696 | S49: =IFERROR(R49/8,"") -> 7.826087 | T49: =IFERROR(IF(R49>2,S49,""),"") -> 7.826087 | Z49: Christian | AD49: 45419 | AE49: 12 | AF49: 0.9 | AG49: 0.3 | AH49: 1 | AI49: 0.1 | AJ49: 0.14 | AK49: 0.19 | AL49: 0.7 | AM49: 0.6 | AN49: 0.25 | AO49: 4.6 | AP49: 50 | AQ49: 110 | AR49: 110 | AS49: 108 | AT49: 40 | AU49: 30 | AV49: 40 | AW49: 40 | AX49: 100 | AY49: 406 | AZ49: Normal | BA49: 1500 | BB49: 10 | CH49: 3 | CI49: 86
A50: 1827 | B50: Venta Normal | C50: GN | D50: ART. 3110 | E50: 720 | F50: 0.0115 | G50: 0.009 | H50: =(F50-G50)/F50 -> 0.2173913 | I50: PVC | J50: PVC CRISTAL 520 x 250 | K50: CAJA Nº 4/1 | L50: BOLSAS DE 120 X 125 | O50: 3 | P50: 28 | Q50: =IFERROR(IF(AO50>1,AO50,60*60*8*O50/P50/E50),"") -> 4.2857143 | R50: =IFERROR(60*60*8*O50/E50/Q50,"") -> 28 | S50: =IFERROR(R50/8,"") -> 3.5 | T50: =IFERROR(IF(R50>2,S50,""),"") -> 3.5 | CH50: 6 | CI50: 59
A51: 2028 | B51: Venta Normal | C51: GN | D51: ART. 3110 CRISTAL (X 150) | E51: 150 | F51: 0.0115 | G51: 0.009 | H51: =(F51-G51)/F51 -> 0.2173913 | I51: PVC | J51: PVC CRISTAL 520 x 250 | O51: 3 | P51: 110 | Q51: =IFERROR(IF(AO51>1,AO51,60*60*8*O51/P51/E51),"") -> 4.2 | R51: =IFERROR(60*60*8*O51/E51/Q51,"") -> 137.14286 | S51: =IFERROR(R51/8,"") -> 17.142857 | T51: =IFERROR(IF(R51>2,S51,""),"") -> 17.142857 | Z51: Christian | AD51: 45605 | AE51: 12 | AF51: 1 | AG51: 0.2 | AH51: 1 | AI51: 0.2 | AJ51: 0.16 | AK51: 0.22 | AL51: 0.6 | AM51: 0.35 | AN51: 0.15 | AO51: 4.2 | AP51: 48 | AQ51: 100 | AR51: 102 | AS51: 102 | AT51: 36 | AU51: 20 | AV51: 40 | AW51: 20 | AX51: 101 | AY51: 189 | AZ51: Normal | BA51: 2200 | BB51: 10 | CH51: 3 | CI51: 36
A52: 2029 | B52: Venta Normal | C52: GN | D52: ART. 3110 CRISTAL (X 180) | E52: 180 | F52: 0.0115 | G52: 0.009 | H52: =(F52-G52)/F52 -> 0.2173913 | I52: PVC | J52: PVC CRISTAL 520 x 250 | O52: 3 | P52: 110 | Q52: =IFERROR(IF(AO52>1,AO52,60*60*8*O52/P52/E52),"") -> 4.2 | R52: =IFERROR(60*60*8*O52/E52/Q52,"") -> 114.28571 | S52: =IFERROR(R52/8,"") -> 14.285714 | T52: =IFERROR(IF(R52>2,S52,""),"") -> 14.285714 | Z52: Christian | AD52: 45605 | AE52: 12 | AF52: 1 | AG52: 0.2 | AH52: 1 | AI52: 0.2 | AJ52: 0.16 | AK52: 0.22 | AL52: 0.6 | AM52: 0.35 | AN52: 0.15 | AO52: 4.2 | AP52: 48 | AQ52: 100 | AR52: 102 | AS52: 102 | AT52: 36 | AU52: 20 | AV52: 40 | AW52: 20 | AX52: 101 | AY52: 189 | AZ52: Normal | BA52: 2200 | BB52: 10 | CH52: 6 | CI52: 79
A53: 2026 | B53: Venta Normal | C53: GN | D53: ART. 3110 NEGRO (X 150) | E53: 150 | F53: 0.0109 | G53: 0.0075 | H53: =(F53-G53)/F53 -> 0.31192661 | I53: HIPST | J53: PAI NEGRO 520 x 300 | M53: 6 | N53: 25 | O53: 3 | P53: 120 | Q53: =IFERROR(IF(AO53>1,AO53,60*60*8*O53/P53/E53),"") -> 4 | R53: =IFERROR(60*60*8*O53/E53/Q53,"") -> 144 | S53: =IFERROR(R53/8,"") -> 18 | T53: =IFERROR(IF(R53>2,S53,""),"") -> 18 | Z53: Christian | AD53: 45420 | AE53: 13 | AF53: 1 | AG53: 0.1 | AH53: 1 | AI53: 0.15 | AJ53: 0.45 | AK53: 0.28 | AL53: 0.12 | AM53: 0.41 | AN53: 0.1 | AO53: 4 | AP53: 44 | AQ53: 120 | AR53: 120 | AS53: 122 | AT53: 55 | AU53: 20 | AV53: 40 | AW53: 20 | AX53: 65 | AY53: 178 | AZ53: Normal | BA53: 500 | BB53: 10 | CH53: 1 | CI53: 71
A54: 1740 | B54: Discontinuado | C54: GN | D54: ART. 3110 OPS | E54: 720 | F54: 0.0132 | G54: 0.0088 | H54: =(F54-G54)/F54 -> 0.33333333 | I54: OPS | J54: UNICLEAR CRISTAL OPS 540 x 350 | K54: CAJA Nº 4/1 | L54: BOLSAS DE 120 X 125 | O54: 3 | Q54: =IFERROR(IF(AO54>1,AO54,60*60*8*O54/P54/E54),"") | R54: =IFERROR(60*60*8*O54/E54/Q54,"") | S54: =IFERROR(R54/8,"") | T54: =IFERROR(IF(R54>2,S54,""),"") | CH54: 4 | CI54: 53
A55: 1826 | B55: Venta Normal | C55: GN | D55: ART. 3110 PAI NEGRO | E55: 720 | F55: 0.0109 | G55: 0.0075 | H55: =(F55-G55)/F55 -> 0.31192661 | I55: HIPST | J55: PAI NEGRO 520 x 300 | K55: CAJA Nº 4/1 | L55: BOLSAS DE 120 X 125 | O55: 3 | P55: 25 | Q55: =IFERROR(IF(AO55>1,AO55,60*60*8*O55/P55/E55),"") -> 4 | R55: =IFERROR(60*60*8*O55/E55/Q55,"") -> 30 | S55: =IFERROR(R55/8,"") -> 3.75 | T55: =IFERROR(IF(R55>2,S55,""),"") -> 3.75 | Z55: Christian | AD55: 45420 | AE55: 13 | AF55: 1 | AG55: 0.1 | AH55: 1 | AI55: 0.15 | AJ55: 0.45 | AK55: 0.28 | AL55: 0.12 | AM55: 0.41 | AN55: 0.1 | AO55: 4 | AP55: 44 | AQ55: 120 | AR55: 120 | AS55: 122 | AT55: 55 | AU55: 20 | AV55: 40 | AW55: 20 | AX55: 65 | AY55: 178 | AZ55: Normal | BA55: 500 | BB55: 10 | CH55: 6 | CI55: 63
A56: 1828 | B56: Venta Normal | C56: GN | D56: ART. 3142 | E56: 720 | F56: 0.0138 | G56: 0.0109 | H56: =(F56-G56)/F56 -> 0.21014493 | I56: PVC | J56: PVC CRISTAL 520 x 300 | K56: CAJA Nº 8 | L56: BOLSAS DE 120 X 125 | O56: 3 | P56: 27 | Q56: =IFERROR(IF(AO56>1,AO56,60*60*8*O56/P56/E56),"") -> 4 | R56: =IFERROR(60*60*8*O56/E56/Q56,"") -> 30 | S56: =IFERROR(R56/8,"") -> 3.75 | T56: =IFERROR(IF(R56>2,S56,""),"") -> 3.75 | Z56: Christian | AD56: 45418 | AE56: 13 | AF56: 1 | AG56: 0.1 | AH56: 1 | AI56: 0.1 | AJ56: 0.46 | AK56: 0.28 | AL56: 0.12 | AM56: 0.4 | AN56: 0.1 | AO56: 4 | AP56: 49 | AQ56: 104 | AR56: 106 | AS56: 106 | AT56: 42 | AU56: 20 | AV56: 40 | AW56: 20 | AX56: 65 | AY56: 181 | AZ56: Normal | BA56: 500 | BB56: 10 | CH56: 4 | CI56: 48
A57: 2030 | B57: Venta Normal | C57: GN | D57: ART. 3142 ( X180 ) | E57: 180 | F57: 0.0138 | G57: 0.0109 | H57: =(F57-G57)/F57 -> 0.21014493 | I57: PVC | J57: PVC CRISTAL 520 x 300 | K57: CAJA Nº 14 | L57: BOLSAS DE 120 X 80 | O57: 3 | P57: 27 | Q57: =IFERROR(IF(AO57>1,AO57,60*60*8*O57/P57/E57),"") -> 4 | R57: =IFERROR(60*60*8*O57/E57/Q57,"") -> 120 | S57: =IFERROR(R57/8,"") -> 15 | T57: =IFERROR(IF(R57>2,S57,""),"") -> 15 | Z57: Christian | AD57: 45418 | AE57: 13 | AF57: 1 | AG57: 0.1 | AH57: 1 | AI57: 0.1 | AJ57: 0.46 | AK57: 0.28 | AL57: 0.12 | AM57: 0.4 | AN57: 0.1 | AO57: 4 | AP57: 49 | AQ57: 104 | AR57: 106 | AS57: 106 | AT57: 42 | AU57: 20 | AV57: 40 | AW57: 20 | AX57: 65 | AY57: 181 | AZ57: Normal | BA57: 500 | BB57: 10 | CH57: 4 | CI57: 83
A58: 1787 | B58: Discontinuado | C58: GN | D58: ART. 3142 OPS | E58: 720 | F58: 0.015 | G58: 0.0102 | H58: =(F58-G58)/F58 -> 0.32 | I58: OPS | J58: UNICLEAR CRISTAL OPS 540 x 400 | K58: CAJA Nº 8 | L58: BOLSAS DE 120 X 125 | O58: 3 | Q58: =IFERROR(IF(AO58>1,AO58,60*60*8*O58/P58/E58),"") | R58: =IFERROR(60*60*8*O58/E58/Q58,"") | S58: =IFERROR(R58/8,"") | T58: =IFERROR(IF(R58>2,S58,""),"") | CH58: 3 | CI58: 65
A59: 1829 | B59: Venta Normal | C59: GN | D59: ART. 3185 | E59: 720 | F59: 0.0207 | G59: 0.015 | H59: =(F59-G59)/F59 -> 0.27536232 | I59: PVC | J59: PVC CRISTAL 520 x 450 | K59: CAJA Nº 8 | L59: BOLSAS DE 120 X 125 | O59: 3 | P59: 21 | Q59: =IFERROR(IF(AO59>1,AO59,60*60*8*O59/P59/E59),"") -> 4.6 | R59: =IFERROR(60*60*8*O59/E59/Q59,"") -> 26.086957 | S59: =IFERROR(R59/8,"") -> 3.2608696 | T59: =IFERROR(IF(R59>2,S59,""),"") -> 3.2608696 | Z59: Christian | AD59: 45414 | AE59: 13 | AF59: 1 | AG59: 0.2 | AH59: 1 | AI59: 0.2 | AJ59: 0.6 | AK59: 0.28 | AL59: 0.12 | AM59: 0.6 | AN59: 0.2 | AO59: 4.6 | AP59: 48 | AQ59: 106 | AR59: 106 | AS59: 105 | AT59: 42 | AU59: 20 | AV59: 40 | AW59: 20 | AX59: 65 | AY59: 180 | AZ59: Normal | BA59: 400 | BB59: 10 | CH59: 1 | CI59: 55
A60: 2031 | B60: Venta Normal | C60: GN | D60: ART. 3185 (X 150) | E60: 150 | F60: 0.0207 | G60: 0.015 | H60: =(F60-G60)/F60 -> 0.27536232 | I60: PVC | J60: PVC CRISTAL 520 x 450 | K60: CAJA Nº 14 | L60: BOLSAS DE 120 X 80 | O60: 3 | P60: 101 | Q60: =IFERROR(IF(AO60>1,AO60,60*60*8*O60/P60/E60),"") -> 4.6 | R60: =IFERROR(60*60*8*O60/E60/Q60,"") -> 125.21739 | S60: =IFERROR(R60/8,"") -> 15.652174 | T60: =IFERROR(IF(R60>2,S60,""),"") -> 15.652174 | Z60: Christian | AD60: 45414 | AE60: 13 | AF60: 1 | AG60: 0.2 | AH60: 1 | AI60: 0.2 | AJ60: 0.6 | AK60: 0.28 | AL60: 0.12 | AM60: 0.6 | AN60: 0.2 | AO60: 4.6 | AP60: 48 | AQ60: 106 | AR60: 106 | AS60: 105 | AT60: 42 | AU60: 20 | AV60: 40 | AW60: 20 | AX60: 65 | AY60: 180 | AZ60: Normal | BA60: 400 | BB60: 10 | CH60: 5 | CI60: 33
A61: 2034 | B61: Venta Normal | C61: GN | D61: ART. 3185 / 3110 NEGRO | E61: 150 | F61: 0.0316 | G61: 0.0225 | H61: =(F61-G61)/F61 -> 0.28797468 | I61: PAI-PVC | J61: COMBO | P61: * | Q61: =IFERROR(IF(AO61>1,AO61,60*60*8*O61/P61/E61),"") | R61: =IFERROR(60*60*8*O61/E61/Q61,"") | S61: =IFERROR(R61/8,"") | T61: =IFERROR(IF(R61>2,S61,""),"") | CH61: 3 | CI61: 67
A62: 1739 | B62: Venta Normal | C62: GN | D62: ART. 3185 OPS | E62: 720 | F62: 0.0188 | G62: 0.0125 | H62: =(F62-G62)/F62 -> 0.33510638 | I62: PVC | J62: UNICLEAR CRISTAL OPS 540 x 500 | K62: CAJA Nº 13 | L62: BOLSAS DE 120 X 125 | O62: 3 | P62: 21 | Q62: =IFERROR(IF(AO62>1,AO62,60*60*8*O62/P62/E62),"") -> 5.7142857 | R62: =IFERROR(60*60*8*O62/E62/Q62,"") -> 21 | S62: =IFERROR(R62/8,"") -> 2.625 | T62: =IFERROR(IF(R62>2,S62,""),"") -> 2.625 | CH62: 4 | CI62: 62
A63: 1824 | B63: Venta Normal | C63: GN | D63: ART. 3208 | E63: 200 | F63: 0.0378 | G63: 0.0324 | H63: =(F63-G63)/F63 -> 0.14285714 | I63: PVC | J63: PVC CRISTAL 500 x 300 | K63: CAJA Nº 2 | L63: BOLSAS DE 120 X 80 | O63: 2 | P63: 50 | Q63: =IFERROR(IF(AO63>1,AO63,60*60*8*O63/P63/E63),"") -> 5.76 | R63: =IFERROR(60*60*8*O63/E63/Q63,"") -> 50 | S63: =IFERROR(R63/8,"") -> 6.25 | T63: =IFERROR(IF(R63>2,S63,""),"") -> 6.25 | CH63: 3 | CI63: 69
A64: 92 | B64: Discontinuado | C64: GN | D64: ART. 6 BASE | E64: 540 | F64: 0.0124 | G64: 0.0079 | H64: =(F64-G64)/F64 -> 0.36290323 | I64: OPS | J64: UNICLEAR CRISTAL OPS 580 x 300 | K64: CAJA Nº 4/1 | L64: BOLSAS DE 120 X 125 | O64: 6 | Q64: =IFERROR(IF(AO64>1,AO64,60*60*8*O64/P64/E64),"") | R64: =IFERROR(60*60*8*O64/E64/Q64,"") | S64: =IFERROR(R64/8,"") | T64: =IFERROR(IF(R64>2,S64,""),"") | CH64: 5 | CI64: 53
A65: 93 | B65: Discontinuado | C65: GN | D65: ART. 6 TAPA | E65: 540 | F65: 0.0104 | G65: 0.0066 | H65: =(F65-G65)/F65 -> 0.36538462 | I65: OPS | J65: UNICLEAR CRISTAL OPS 580 x 250 | K65: CAJA Nº 4/1 | L65: BOLSAS DE 120 X 125 | O65: 6 | Q65: =IFERROR(IF(AO65>1,AO65,60*60*8*O65/P65/E65),"") | R65: =IFERROR(60*60*8*O65/E65/Q65,"") | S65: =IFERROR(R65/8,"") | T65: =IFERROR(IF(R65>2,S65,""),"") | CH65: 3 | CI65: 41
A66: 98 | B66: Venta Normal | C66: GN | D66: ART. B 16 NEGRO | E66: 60 | F66: 0.0577 | G66: 0.046 | H66: =(F66-G66)/F66 -> 0.20277296 | I66: HIPST | J66: PAI NEGRO 320 x 400 | K66: CAJA Nº 4/1 | L66: BOLSAS DE 120 X 125 | O66: 1 | P66: 90 | Q66: 5.4 | R66: =IFERROR(60*60*8*O66/E66/Q66,"") -> 88.888889 | S66: =IFERROR(R66/8,"") -> 11.111111 | T66: =IFERROR(IF(R66>2,S66,""),"") -> 11.111111 | CH66: 1 | CI66: 72
A67: 99 | B67: Venta Normal | C67: GN | D67: ART. B 16 NEGRO X 160 | E67: 160 | F67: 0.0577 | G67: 0.046 | H67: =(F67-G67)/F67 -> 0.20277296 | I67: HIPST | J67: PAI NEGRO 320 x 400 | K67: CAJA Nº 4 | L67: BOLSAS DE 120 X 125 | O67: 1 | P67: 37 | Q67: =IFERROR(IF(AO67>1,AO67,60*60*8*O67/P67/E67),"") -> 5.4 | R67: =IFERROR(60*60*8*O67/E67/Q67,"") -> 33.333333 | S67: =IFERROR(R67/8,"") -> 4.1666667 | T67: =IFERROR(IF(R67>2,S67,""),"") -> 4.1666667 | AD67: 45495 | AE67: 13 | AF67: 1.5 | AG67: 0.5 | AH67: 1.5 | AI67: 0.5 | AJ67: 0.8 | AK67: 0.11 | AL67: 0.18 | AM67: 0.4 | AN67: 0.5 | AO67: 5.4 | AP67: 56 | AQ67: 119 | AR67: 128 | AS67: 128 | AT67: 65 | AU67: 20 | AV67: 40 | AW67: 20 | AX67: 65 | AY67: 387 | AZ67: Normal | BA67: 600 | BB67: 10 | CH67: 3 | CI67: 85
A68: 51 | B68: Discontinuado | C68: GN | D68: ART. B 21 M | E68: 160 | F68: 0.0528 | G68: 0.0437 | H68: =(F68-G68)/F68 -> 0.17234848 | I68: HIPST | J68: PAI NEGRO 320 x 400 | K68: CAJA Nº 4 | L68: BOLSAS DE 120 X 125 | O68: 1 | P68: 58 | Q68: =IFERROR(IF(AO68>1,AO68,60*60*8*O68/P68/E68),"") -> 3.1034483 | R68: =IFERROR(60*60*8*O68/E68/Q68,"") -> 58 | S68: =IFERROR(R68/8,"") -> 7.25 | T68: =IFERROR(IF(R68>2,S68,""),"") -> 7.25 | CH68: 1 | CI68: 64
A69: 628 | B69: Venta Normal | C69: GN | D69: ART. B-23 M | E69: 200 | F69: 0.0372 | G69: 0.026598 | H69: =(F69-G69)/F69 -> 0.285 | I69: HIPST | J69: PAI NEGRO 520 x 400 | K69: CAJA Nº 17 | L69: BOLSAS DE 120 X 110 | O69: 2 | P69: 40 | Q69: =IFERROR(IF(AO69>1,AO69,60*60*8*O69/P69/E69),"") -> 7.2 | R69: =IFERROR(60*60*8*O69/E69/Q69,"") -> 40 | S69: =IFERROR(R69/8,"") -> 5 | T69: =IFERROR(IF(R69>2,S69,""),"") -> 5 | CH69: 4 | CI69: 33
A70: 100 | B70: Venta Normal | C70: GN | D70: ART. BR 20 NEGRO | E70: 200 | F70: 0.0289 | G70: 0.0166 | H70: =(F70-G70)/F70 -> 0.42560554 | I70: HIPST | J70: PAI NEGRO 530 x 350 | K70: CAJA Nº 8 | L70: BOLSAS DE 120 X 125 | O70: 4 | P70: 60 | Q70: =IFERROR(IF(AO70>1,AO70,60*60*8*O70/P70/E70),"") -> 9.6 | R70: =IFERROR(60*60*8*O70/E70/Q70,"") -> 60 | S70: =IFERROR(R70/8,"") -> 7.5 | T70: =IFERROR(IF(R70>2,S70,""),"") -> 7.5 | CH70: 2 | CI70: 90
A71: 103 | B71: Venta Normal | C71: GN | D71: ART. BR 24 NEGRO | E71: 200 | F71: 0.0396 | G71: 0.0276 | H71: =(F71-G71)/F71 -> 0.3030303 | I71: HIPST | J71: PAI NEGRO 600 x 400 | K71: CAJA Nº 7 | L71: BOLSAS DE 120 X 125 | M71: 2 | N71: 100 | O71: 2 | P71: 40-60 | Q71: =IFERROR(IF(AO71>1,AO71,60*60*8*O71/P71/E71),"") -> 7,1 - 4,4 | R71: 41 / 65 | S71: =IFERROR(R71/8,"") | T71: 5,1 / 8,2 | U71: 65 | AD71: 24/7/2024 - 22/8/2024 | AE71: 17 - 14 | AF71: 1,9 - 1,3 | AG71: 0,15 - 0,25 | AH71: 1,8 - 1 | AI71: 0,15 - 0,25 | AJ71: 1,2 - 0,15 | AK71: 0,28 - 0,15 | AL71: 0,3 - 0,3 | AM71: 0,43 - 0,4 | AN71: 0,5 - 0,5 | AO71: 7,1 - 4,4 | AP71: 41 - 36 | AQ71: 129 - 138 | AR71: 131 - 136 | AS71: 135 -139 | AT71: 50 - 80 | AU71: ? - 20 | AV71: ? - 40 | AW71: ? - 20 | AX71: 200 - 70 | AY71: 309 - 274 | AZ71: Normal | BA71: ? - 1100 | BB71: ? - 10 | BC71: 134 | BD71: 133 | CH71: 5 | CI71: 83
A72: 106 | B72: Venta Normal | C72: GN | D72: ART. BR 26 NEGRO | E72: 200 | F72: 0.0479 | G72: 0.032 | H72: =(F72-G72)/F72 -> 0.33194154 | I72: HIPST | J72: PAI NEGRO 340 x 400 | K72: CAJA Nº 9 | L72: BOLSAS DE 120 X 125 | O72: 1 | P72: 40 | Q72: =IFERROR(IF(AO72>1,AO72,60*60*8*O72/P72/E72),"") -> 5.8 | R72: =IFERROR(60*60*8*O72/E72/Q72,"") -> 24.827586 | S72: =IFERROR(R72/8,"") -> 3.1034483 | T72: =IFERROR(IF(R72>2,S72,""),"") -> 3.1034483 | AD72: 45371 | AE72: 12 | AF72: 1.3 | AG72: 0.4 | AH72: 1.3 | AI72: 0.4 | AJ72: 1 | AK72: 0.12 | AL72: 0.22 | AM72: 0.55 | AN72: 0.2 | AO72: 5.8 | AP72: 51 | AQ72: 138 | AR72: 135 | AS72: 135 | AT72: 60 | AU72: 33 | AV72: 40 | AW72: 40 | AX72: 100 | AY72: 310 | AZ72: Normal | BA72: 1600 | BB72: 10 | CH72: 6 | CI72: 46
A73: 108 | B73: Venta Normal | C73: GN | D73: ART. BR 29 NEGRO | E73: 100 | F73: 0.0594 | G73: 0.0444 | H73: =(F73-G73)/F73 -> 0.25252525 | I73: HIPST | J73: PAI NEGRO 365 x 400 | K73: CAJA Nº 5 | L73: BOLSAS DE 120 X 125 | M73: 2 | N73: 50 | O73: 1 | P73: 50 | Q73: =IFERROR(IF(AO73>1,AO73,60*60*8*O73/P73/E73),"") -> 4.6 | R73: =IFERROR(60*60*8*O73/E73/Q73,"") -> 62.608696 | S73: =IFERROR(R73/8,"") -> 7.826087 | T73: =IFERROR(IF(R73>2,S73,""),"") -> 7.826087 | AD73: 45391 | AE73: 12 | AF73: 1.1 | AG73: 0.5 | AH73: 1.1 | AI73: 0.3 | AJ73: 0.6 | AK73: 0.11 | AL73: 0.17 | AM73: 0.2 | AN73: 0.12 | AO73: 4.6 | AP73: 45 | AQ73: 132 | AR73: 136 | AS73: 135 | AT73: 60 | AU73: 38 | AV73: 40 | AW73: 40 | AX73: 101 | AY73: 352 | AZ73: Normal | BA73: 3000 | BB73: 10 | CH73: 2 | CI73: 44
A74: 109 | B74: Discontinuado | C74: GN | D74: ART. BR 29 NEGRO X 160 | E74: 160 | F74: 0.0594 | G74: 0.0444 | H74: =(F74-G74)/F74 -> 0.25252525 | I74: HIPST | J74: PAI NEGRO 365 x 400 | K74: CAJA Nº 9 | L74: BOLSAS DE 120 X 125 | O74: 1 | P74: 32 | Q74: =IFERROR(IF(AO74>1,AO74,60*60*8*O74/P74/E74),"") -> 5.625 | R74: =IFERROR(60*60*8*O74/E74/Q74,"") -> 32 | S74: =IFERROR(R74/8,"") -> 4 | T74: =IFERROR(IF(R74>2,S74,""),"") -> 4 | CH74: 5 | CI74: 72
A75: 126 | B75: Venta Normal | C75: GN | D75: ART. BT 16 | E75: 60 | G75: 0.1065 | I75: HIPST-PET | J75: PAI/PET 100x10000 | O75: 1 | P75: 20 | Q75: =IFERROR(IF(AO75>1,AO75,60*60*8*O75/P75/E75),"") -> 24 | R75: =IFERROR(60*60*8*O75/E75/Q75,"") -> 20 | S75: =IFERROR(R75/8,"") -> 2.5 | T75: =IFERROR(IF(R75>2,S75,""),"") -> 2.5 | CH75: 6 | CI75: 66
A76: 1956 | B76: Venta Normal | C76: GN | D76: ART. OP 1445 | E76: 400 | F76: 0.0074 | G76: 0.0056 | H76: =(F76-G76)/F76 -> 0.24324324 | I76: OPS | J76: UNICLEAR CRISTAL OPS 480 x 350 | K76: CAJA Nº 2 | L76: BOLSAS DE 120 X 80 | O76: 12 | Q76: =IFERROR(IF(AO76>1,AO76,60*60*8*O76/P76/E76),"") | R76: =IFERROR(60*60*8*O76/E76/Q76,"") | S76: =IFERROR(R76/8,"") | T76: =IFERROR(IF(R76>2,S76,""),"") | CH76: 2 | CI76: 34
A77: 1957 | B77: Venta Normal | C77: GN | D77: ART. OP 1510 | E77: 400 | F77: 0.0086 | G77: 0.006 | H77: =(F77-G77)/F77 -> 0.30232558 | I77: OPS | J77: UNICLEAR CRISTAL OPS 460 x 300 | K77: CAJA Nº 2 | L77: BOLSAS DE 120 X 80 | O77: 9 | Q77: =IFERROR(IF(AO77>1,AO77,60*60*8*O77/P77/E77),"") | R77: =IFERROR(60*60*8*O77/E77/Q77,"") | S77: =IFERROR(R77/8,"") | T77: =IFERROR(IF(R77>2,S77,""),"") | CH77: 2 | CI77: 43
A78: 1958 | B78: Venta Normal | C78: GN | D78: ART. OP 1550 | E78: 400 | F78: 0.0115 | G78: 0.008 | H78: =(F78-G78)/F78 -> 0.30434783 | I78: OPS | J78: UNICLEAR CRISTAL OPS 460 x 400 | K78: CAJA Nº 2 | L78: BOLSAS DE 120 X 80 | O78: 9 | Q78: =IFERROR(IF(AO78>1,AO78,60*60*8*O78/P78/E78),"") | R78: =IFERROR(60*60*8*O78/E78/Q78,"") | S78: =IFERROR(R78/8,"") | T78: =IFERROR(IF(R78>2,S78,""),"") | CH78: 5 | CI78: 43
A79: 31 | B79: Discontinuado | C79: GN | D79: ART. OP 1560 | E79: 500 | F79: 0.0242 | G79: 0.02 | H79: =(F79-G79)/F79 -> 0.17355372 | I79: OPS | J79: UNICLEAR CRISTAL OPS 570 x 300 | K79: CAJA Nº 4/1 | L79: BOLSAS DE 120 X 125 | O79: 3 | Q79: =IFERROR(IF(AO79>1,AO79,60*60*8*O79/P79/E79),"") | R79: =IFERROR(60*60*8*O79/E79/Q79,"") | S79: =IFERROR(R79/8,"") | T79: =IFERROR(IF(R79>2,S79,""),"") | CH79: 6 | CI79: 37
A80: 1965 | B80: Venta Normal | C80: GN | D80: ART. OP 1560 | E80: 300 | F80: 0.0245 | G80: 0.02 | H80: =(F80-G80)/F80 -> 0.18367347 | I80: OPS | J80: UNICLEAR CRISTAL OPS 570 x 300 | K80: CAJA Nº 2 | L80: BOLSAS DE 120 X 80 | O80: 3 | P80: 50 | Q80: =IFERROR(IF(AO80>1,AO80,60*60*8*O80/P80/E80),"") -> 5.76 | R80: =IFERROR(60*60*8*O80/E80/Q80,"") -> 50 | S80: =IFERROR(R80/8,"") -> 6.25 | T80: =IFERROR(IF(R80>2,S80,""),"") -> 6.25 | CH80: 2 | CI80: 31
A81: 1960 | B81: Venta Normal | C81: GN | D81: ART. OP 1810 | E81: 300 | F81: 0.0132 | G81: 0.0094 | H81: =(F81-G81)/F81 -> 0.28787879 | I81: OPS | J81: UNICLEAR CRISTAL OPS 380 x 300 | K81: CAJA Nº 2 | L81: BOLSAS DE 120 X 80 | O81: 4 | Q81: =IFERROR(IF(AO81>1,AO81,60*60*8*O81/P81/E81),"") | R81: =IFERROR(60*60*8*O81/E81/Q81,"") | S81: =IFERROR(R81/8,"") | T81: =IFERROR(IF(R81>2,S81,""),"") | CH81: 2 | CI81: 42
A82: 1961 | B82: Venta Normal | C82: GN | D82: ART. OP 1845 | E82: 300 | F82: 0.0176 | G82: 0.0128 | H82: =(F82-G82)/F82 -> 0.27272727 | I82: OPS | J82: UNICLEAR CRISTAL OPS 380 x 400 | K82: CAJA Nº 15 | L82: BOLSAS DE 120 X 110 | O82: 4 | Q82: =IFERROR(IF(AO82>1,AO82,60*60*8*O82/P82/E82),"") | R82: =IFERROR(60*60*8*O82/E82/Q82,"") | S82: =IFERROR(R82/8,"") | T82: =IFERROR(IF(R82>2,S82,""),"") | CH82: 4 | CI82: 31
A83: 1962 | B83: Venta Normal | C83: GN | D83: ART. OP 1860 | E83: 300 | F83: 0.0198 | G83: 0.0155 | H83: =(F83-G83)/F83 -> 0.21717172 | I83: OPS | J83: UNICLEAR CRISTAL OPS 380 x 450 | K83: CAJA Nº 15 | L83: BOLSAS DE 120 X 110 | O83: 4 | Q83: =IFERROR(IF(AO83>1,AO83,60*60*8*O83/P83/E83),"") | R83: =IFERROR(60*60*8*O83/E83/Q83,"") | S83: =IFERROR(R83/8,"") | T83: =IFERROR(IF(R83>2,S83,""),"") | CH83: 1 | CI83: 36
A84: 32 | B84: Discontinuado | C84: GN | D84: ART. OP 2050 | E84: 520 | F84: 0.0196 | G84: 0.0159 | H84: =(F84-G84)/F84 -> 0.18877551 | I84: OPS | J84: UNICLEAR CRISTAL OPS 460 x 250 | K84: CAJA Nº 4/1 | L84: BOLSAS DE 120 X 125 | O84: 2 | Q84: =IFERROR(IF(AO84>1,AO84,60*60*8*O84/P84/E84),"") | R84: =IFERROR(60*60*8*O84/E84/Q84,"") | S84: =IFERROR(R84/8,"") | T84: =IFERROR(IF(R84>2,S84,""),"") | CH84: 5 | CI84: 61
A85: 1966 | B85: Venta Normal | C85: GN | D85: ART. OP 2050 | E85: 300 | F85: 0.0196 | G85: 0.0159 | H85: =(F85-G85)/F85 -> 0.18877551 | I85: OPS | J85: UNICLEAR CRISTAL OPS 460 x 250 | K85: CAJA Nº 1/2 | L85: BOLSAS DE 120 X 80 | O85: 2 | P85: 50 | Q85: =IFERROR(IF(AO85>1,AO85,60*60*8*O85/P85/E85),"") -> 3.84 | R85: =IFERROR(60*60*8*O85/E85/Q85,"") -> 50 | S85: =IFERROR(R85/8,"") -> 6.25 | T85: =IFERROR(IF(R85>2,S85,""),"") -> 6.25 | CH85: 3 | CI85: 64
A86: 34 | B86: Discontinuado | C86: GN | D86: ART. OP 2060 | E86: 520 | F86: 0.0196 | G86: 0.0159 | H86: =(F86-G86)/F86 -> 0.18877551 | I86: OPS | J86: UNICLEAR CRISTAL OPS 460 x 250 | K86: CAJA Nº 4/1 | L86: BOLSAS DE 120 X 125 | O86: 2 | Q86: =IFERROR(IF(AO86>1,AO86,60*60*8*O86/P86/E86),"") | R86: =IFERROR(60*60*8*O86/E86/Q86,"") | S86: =IFERROR(R86/8,"") | T86: =IFERROR(IF(R86>2,S86,""),"") | CH86: 6 | CI86: 30
A87: 1967 | B87: Venta Normal | C87: GN | D87: ART. OP 2060 | E87: 300 | F87: 0.0196 | G87: 0.0159 | H87: =(F87-G87)/F87 -> 0.18877551 | I87: OPS | J87: UNICLEAR CRISTAL OPS 460 x 250 | K87: CAJA Nº 1/2 | L87: BOLSAS DE 120 X 80 | O87: 2 | P87: 50 | Q87: =IFERROR(IF(AO87>1,AO87,60*60*8*O87/P87/E87),"") -> 3.84 | R87: =IFERROR(60*60*8*O87/E87/Q87,"") -> 50 | S87: =IFERROR(R87/8,"") -> 6.25 | T87: =IFERROR(IF(R87>2,S87,""),"") -> 6.25 | CH87: 5 | CI87: 82
A88: 36 | B88: Discontinuado | C88: GN | D88: ART. OP 2060 MPH | E88: 520 | F88: 0.0196 | G88: 0.0159 | H88: =(F88-G88)/F88 -> 0.18877551 | I88: OPS | J88: UNICLEAR CRISTAL OPS 460 x 250 | K88: CAJA Nº 4/1 | L88: BOLSAS DE 120 X 125 | O88: 2 | Q88: =IFERROR(IF(AO88>1,AO88,60*60*8*O88/P88/E88),"") | R88: =IFERROR(60*60*8*O88/E88/Q88,"") | S88: =IFERROR(R88/8,"") | T88: =IFERROR(IF(R88>2,S88,""),"") | CH88: 2 | CI88: 40
A89: 1968 | B89: Venta Normal | C89: GN | D89: ART. OP 2060 MPH | E89: 250 | F89: 0.0196 | G89: 0.0159 | H89: =(F89-G89)/F89 -> 0.18877551 | I89: OPS | J89: UNICLEAR CRISTAL OPS 460 x 250 | K89: CAJA Nº 1/2 | L89: BOLSAS DE 120 X 80 | O89: 2 | P89: 60 | Q89: =IFERROR(IF(AO89>1,AO89,60*60*8*O89/P89/E89),"") -> 3.84 | R89: =IFERROR(60*60*8*O89/E89/Q89,"") -> 60 | S89: =IFERROR(R89/8,"") -> 7.5 | T89: =IFERROR(IF(R89>2,S89,""),"") -> 7.5 | CH89: 4 | CI89: 84
A90: 37 | B90: Discontinuado | C90: GN | D90: ART. OP 2075 | E90: 200 | F90: 0.0314 | G90: 0.0264 | H90: =(F90-G90)/F90 -> 0.15923567 | I90: OPS | J90: UNICLEAR CRISTAL OPS 480 x 250 | K90: CAJA Nº 4/1 | L90: BOLSAS DE 120 X 125 | O90: 2 | Q90: =IFERROR(IF(AO90>1,AO90,60*60*8*O90/P90/E90),"") | R90: =IFERROR(60*60*8*O90/E90/Q90,"") | S90: =IFERROR(R90/8,"") | T90: =IFERROR(IF(R90>2,S90,""),"") | CH90: 2 | CI90: 61
A91: 40 | B91: Discontinuado | C91: GN | D91: ART. OP 2095 | E91: 200 | F91: 0.0235 | G91: 0.0189 | H91: =(F91-G91)/F91 -> 0.19574468 | I91: OPS | J91: UNICLEAR CRISTAL OPS 460 x 300 | K91: CAJA Nº 1/2 | L91: BOLSAS DE 120 X 80 | O91: 2 | Q91: =IFERROR(IF(AO91>1,AO91,60*60*8*O91/P91/E91),"") | R91: =IFERROR(60*60*8*O91/E91/Q91,"") | S91: =IFERROR(R91/8,"") | T91: =IFERROR(IF(R91>2,S91,""),"") | CH91: 4 | CI91: 81
A92: 41 | B92: Discontinuado | C92: GN | D92: ART. OP 2440 | E92: 360 | F92: 0.027 | G92: 0.0215 | H92: =(F92-G92)/F92 -> 0.2037037 | I92: OPS | J92: UNICLEAR CRISTAL OPS 560 x 250 | K92: CAJA Nº 4/1 | L92: BOLSAS DE 120 X 125 | O92: 2 | Q92: =IFERROR(IF(AO92>1,AO92,60*60*8*O92/P92/E92),"") | R92: =IFERROR(60*60*8*O92/E92/Q92,"") | S92: =IFERROR(R92/8,"") | T92: =IFERROR(IF(R92>2,S92,""),"") | CH92: 4 | CI92: 44
A93: 42 | B93: Discontinuado | C93: GN | D93: ART. OP 2450 | E93: 360 | F93: 0.027 | G93: 0.0215 | H93: =(F93-G93)/F93 -> 0.2037037 | I93: OPS | J93: UNICLEAR CRISTAL OPS 560 x 250 | K93: CAJA Nº 4/1 | L93: BOLSAS DE 120 X 125 | O93: 2 | Q93: =IFERROR(IF(AO93>1,AO93,60*60*8*O93/P93/E93),"") | R93: =IFERROR(60*60*8*O93/E93/Q93,"") | S93: =IFERROR(R93/8,"") | T93: =IFERROR(IF(R93>2,S93,""),"") | CH93: 5 | CI93: 34
A94: 1969 | B94: Venta Normal | C94: GN | D94: ART. OP 2465 | E94: 300 | F94: 0.0144 | G94: 0.0114 | H94: =(F94-G94)/F94 -> 0.20833333 | I94: OPS | J94: UNICLEAR CRISTAL OPS 420 x 250 | K94: CAJA Nº 2 | L94: BOLSAS DE 120 X 80 | O94: 4 | P94: 60 | Q94: =IFERROR(IF(AO94>1,AO94,60*60*8*O94/P94/E94),"") -> 6.4 | R94: =IFERROR(60*60*8*O94/E94/Q94,"") -> 60 | S94: =IFERROR(R94/8,"") -> 7.5 | T94: =IFERROR(IF(R94>2,S94,""),"") -> 7.5 | CH94: 2 | CI94: 31
A95: 45 | B95: Discontinuado | C95: GN | D95: ART. OP 2475 | E95: 360 | F95: 0.027 | G95: 0.0215 | H95: =(F95-G95)/F95 -> 0.2037037 | I95: OPS | J95: UNICLEAR CRISTAL OPS 560 x 250 | K95: CAJA Nº 4/1 | L95: BOLSAS DE 120 X 125 | O95: 2 | Q95: =IFERROR(IF(AO95>1,AO95,60*60*8*O95/P95/E95),"") | R95: =IFERROR(60*60*8*O95/E95/Q95,"") | S95: =IFERROR(R95/8,"") | T95: =IFERROR(IF(R95>2,S95,""),"") | CH95: 3 | CI95: 45
A96: 48 | B96: Discontinuado | C96: GN | D96: ART. OP 2508 | E96: 200 | F96: 0.0397 | G96: 0.0328 | H96: =(F96-G96)/F96 -> 0.17380353 | I96: OPS | J96: UNICLEAR CRISTAL OPS 560 x 300 | K96: CAJA Nº 3 | L96: BOLSAS DE 120 X 80 | O96: 2 | Q96: =IFERROR(IF(AO96>1,AO96,60*60*8*O96/P96/E96),"") | R96: =IFERROR(60*60*8*O96/E96/Q96,"") | S96: =IFERROR(R96/8,"") | T96: =IFERROR(IF(R96>2,S96,""),"") | CH96: 4 | CI96: 43
A97: 50 | B97: Discontinuado | C97: GN | D97: ART. OP 2510 | E97: 200 | F97: 0.0397 | G97: 0.0328 | H97: =(F97-G97)/F97 -> 0.17380353 | I97: OPS | J97: UNICLEAR CRISTAL OPS 560 x 300 | K97: CAJA Nº 3 | L97: BOLSAS DE 120 X 80 | O97: 2 | Q97: =IFERROR(IF(AO97>1,AO97,60*60*8*O97/P97/E97),"") | R97: =IFERROR(60*60*8*O97/E97/Q97,"") | S97: =IFERROR(R97/8,"") | T97: =IFERROR(IF(R97>2,S97,""),"") | CH97: 4 | CI97: 62
A98: 53 | B98: Discontinuado | C98: GN | D98: ART. OP 3208 | E98: 400 | F98: 0.0297 | G98: 0.0253 | H98: =(F98-G98)/F98 -> 0.14814815 | I98: OPS | J98: UNICLEAR CRISTAL OPS 500 x 300 | K98: CAJA Nº 4 | L98: BOLSAS DE 120 X 125 | O98: 2 | Q98: =IFERROR(IF(AO98>1,AO98,60*60*8*O98/P98/E98),"") | R98: =IFERROR(60*60*8*O98/E98/Q98,"") | S98: =IFERROR(R98/8,"") | T98: =IFERROR(IF(R98>2,S98,""),"") | CH98: 5 | CI98: 44
A99: 1970 | B99: Venta Normal | C99: GN | D99: ART. OP 3208 | E99: 200 | F99: 0.0297 | G99: 0.0253 | H99: =(F99-G99)/F99 -> 0.14814815 | I99: OPS | J99: UNICLEAR CRISTAL OPS 500 x 300 | K99: CAJA Nº 2 | L99: BOLSAS DE 120 X 80 | O99: 2 | P99: 60 | Q99: =IFERROR(IF(AO99>1,AO99,60*60*8*O99/P99/E99),"") -> 4.8 | R99: =IFERROR(60*60*8*O99/E99/Q99,"") -> 60 | S99: =IFERROR(R99/8,"") -> 7.5 | T99: =IFERROR(IF(R99>2,S99,""),"") -> 7.5 | CH99: 3 | CI99: 58
A100: 115 | B100: Discontinuado | C100: GN | D100: ART. OP T 16 | E100: 60 | F100: 0.0629 | G100: 0.0526 | H100: =(F100-G100)/F100 -> 0.16375199 | I100: OPS | J100: UNICLEAR CRISTAL OPS 410 x 450 | O100: 1 | Q100: =IFERROR(IF(AO100>1,AO100,60*60*8*O100/P100/E100),"") | R100: =IFERROR(60*60*8*O100/E100/Q100,"") | S100: =IFERROR(R100/8,"") | T100: =IFERROR(IF(R100>2,S100,""),"") | CH100: 5 | CI100: 49
...

Sheet Productividad
W1: SEMI - TOTAL | X1: =COUNT(O251:O788) -> 538 | Y1: REG | Z1: =COUNT(W251:W788) -> 88 | AD1: =Z1/X1 -> 0.16356877 | AG1: GN | AH1: =COUNT(A4:A237) -> 234 | AI1: REG | AJ1: =COUNT(AE4:AE237) -> 43 | AK1: =AJ1/AH1 -> 0.18376068
A2: 338 | D2: Con mi pad no lo hace | X2: Semiautomáticas
A3: 25 | B3: Estado | C3: Maquina | D3: ARTICULO | E3: UN por CAJA | F3: PESO BR. | G3: PESO NET. | H3: % SCRAP | I3: MATERIAL | J3: MATERIAL DETALLE | K3: CAJAS | L3: BOLSA | M3: Paquete por Caja | N3: Unidades por Paquete | O3: CAV | P3: META | Q3: CICLO Master Darta | R3: Cajas en 8 Horas | S3: Cajas x hora | T3: Cajas x hora | U3: Turnos para fabricar 1000 cajas | V3: Cajas que se fabricarían con las planchas | W3: Seg/ciclo | X3: META | Y3: FECHA | Z3: Registrado por | AD3: FECHA | AE3: MAQ | AF3: Calentamiento | AG3: Ventilador de calor | AH3: Fomación | AI3: Ventilador de forma | AJ3: intervalo de corte | AK3: Retraso de expulsión | AL3: Expulsión | AM3: Transporte | AN3: Retraso de cierre | AO3: Promedio de ciclo | AP3: Molde | AQ3: Zona1 | AR3: Zona2 | AS3: Zona3 | AT3: Precalentador | AU3: Presión de calentamiento | AV3: Presión de formación | AW3: Presión de expusión | AX3: Velocidad | AY3: Recorrido | AZ3: Modo | BA3: Acel/ Desacel | BB3: Velocidad del paso | BC3: Zona4 | BD3: Zona5 | BF3: Registrado por | BG3: FECHA | BH3: MAQ | BI3: Calentamiento | BJ3: Ventilador de calor | BK3: Fomación | BL3: Ventilador de forma | BM3: intervalo de corte | BN3: Retraso de expulsión | BO3: Expulsión | BP3: Transporte | BQ3: Retraso de cierre | BR3: Promedio de ciclo | BS3: Molde | BT3: Zona1 | BU3: Zona2 | BV3: Zona3 | BW3: Precalentador | BX3: Presión de calentamiento | BY3: Presión de formación | BZ3: Presión de expusión | CA3: Velocidad | CB3: Recorrido | CC3: Modo | CD3: Acel/ Desacel | CE3: Velocidad del paso | CF3: Zona4 | CG3: Zona5 | CH3: Acuerdo
A4: 338 | B4: Venta Normal | C4: GN | D4: AP-12 | E4: 1200 | F4: 0.0162 | G4: 0.0135 | H4: =(F4-G4)/F4 -> 0.16666667 | I4: PET | J4: PET CRISTAL 580 x 250 | K4: CAJA Nº 4/1 SIN LOGO | L4: BOLSAS DE 120 X 125 | M4: 6 paq de 174 + 1 paq de 156 unid | O4: 6 | P4: 17 | Q4: =IFERROR(IF(AO4>1,AO4,60*60*8*O4/P4/E4),"") -> 6.3 | R4: =IFERROR(60*60*8*O4/E4/Q4,"") -> 22.857143 | S4: =IFERROR(R4/8,"") -> 2.8571429 | T4: =IFERROR(IF(R4>2,S4,""),"") -> 2.8571429 | AD4: 45612 | AE4: 12 | AF4: 1.6 | AG4: 0.3 | AH4: 1.6 | AI4: 0.4 | AJ4: 0.12 | AK4: 0.18 | AL4: 0.7 | AM4: 0.6 | AN4: 0.3 | AO4: 6.3 | AP4: 56 | AQ4: 110 | AR4: 115 | AS4: 110 | AT4: 37 | AU4: 30 | AV4: 35 | AW4: 42 | AX4: 51 | AY4: 451 | AZ4: Normal | BA4: 2000 | BB4: 14
A5: 398 | B5: Venta Normal | C5: GN | D5: AP-6 | E5: 1600 | F5: 0.0128 | G5: 0.0103 | H5: =(F5-G5)/F5 -> 0.1953125 | I5: PET | J5: PET CRISTAL 520 x 220 | K5: CAJA Nº 4/1 SIN LOGO | L5: BOLSAS DE 120 X 125 | O5: 6 | P5: 12 | Q5: 6.3 | R5: =IFERROR(60*60*8*O5/E5/Q5,"") -> 17.142857 | S5: =IFERROR(R5/8,"") -> 2.1428571 | T5: =IFERROR(IF(R5>2,S5,""),"") -> 2.1428571 | AD5: 45622 | AE5: 12 | AF5: 1.7 | AG5: 0.5 | AH5: 1.5 | AI5: 0.5 | AJ5: 0.17 | AK5: 0.25 | AL5: 0.5 | AM5: 0.6 | AN5: 0.45 | AO5: 6.6 | AP5: 46 | AQ5: 104 | AR5: 105 | AS5: 105 | AT5: 45 | AU5: 30 | AV5: 35 | AW5: 42 | AX5: 51 | AY5: 459 | AZ5: Normal | BA5: 1400 | BB5: 14
A6: 723 | B6: Venta Normal | C6: GN | D6: ART. 1445 | E6: 1320 | F6: 0.0084 | G6: 0.0063 | H6: =(F6-G6)/F6 -> 0.25 | I6: PVC | J6: PVC CRISTAL 500 x 300 | K6: CAJA Nº 3 | L6: BOLSAS DE 120 X 80 | O6: 12 | P6: 18 | Q6: =IFERROR(IF(AO6>1,AO6,60*60*8*O6/P6/E6),"") -> 14.545455 | R6: =IFERROR(60*60*8*O6/E6/Q6,"") -> 18 | S6: =IFERROR(R6/8,"") -> 2.25 | T6: =IFERROR(IF(R6>2,S6,""),"") -> 2.25
A7: 724 | B7: Discontinuado | C7: GN | D7: ART. 1445 OPS | E7: 1320 | F7: 0.0074 | G7: 0.0056 | H7: =(F7-G7)/F7 -> 0.24324324 | I7: OPS | J7: UNICLEAR CRISTAL OPS 480 x 400 | K7: CAJA Nº 3 | L7: BOLSAS DE 120 X 80 | O7: 12 | Q7: =IFERROR(IF(AO7>1,AO7,60*60*8*O7/P7/E7),"") | R7: =IFERROR(60*60*8*O7/E7/Q7,"") | S7: =IFERROR(R7/8,"") | T7: =IFERROR(IF(R7>2,S7,""),"")
A8: 1909 | B8: Venta Normal | C8: GN | D8: ART. 1510 | E8: 400 | F8: 0.0109 | G8: 0.0084 | H8: =(F8-G8)/F8 -> 0.2293578 | I8: PVC | J8: PVC CRISTAL 460 x 300 | K8: CAJA Nº 2 | L8: BOLSAS DE 120 X 80 | O8: 9 | P8: 90 | Q8: =IFERROR(IF(AO8>1,AO8,60*60*8*O8/P8/E8),"") -> 5 | R8: =IFERROR(60*60*8*O8/E8/Q8,"") -> 129.6 | S8: =IFERROR(R8/8,"") -> 16.2 | T8: =IFERROR(IF(R8>2,S8,""),"") -> 16.2 | AD8: 45519 | AE8: 14 | AF8: 1 | AG8: 0.1 | AH8: 1 | AI8: 0.2 | AJ8: 0.75 | AK8: 0.15 | AL8: 0.19 | AM8: 0.75 | AN8: 0.4 | AO8: 5 | AP8: 58 | AQ8: 110 | AR8: 112 | AS8: 112 | AT8: 40 | AU8: 20 | AV8: 40 | AW8: 20 | AX8: 70 | AY8: 465 | AZ8: Normal | BA8: 1100 | BB8: 10
A9: 1934 | B9: Venta Normal | C9: GN | D9: ART. 1510 NEGRO | E9: 400 | F9: 0.01 | G9: 0.0068 | H9: =(F9-G9)/F9 -> 0.32 | I9: PVC | J9: PAI NEGRO 460 x 350 | K9: CAJA Nº 2 | L9: BOLSAS DE 120 X 80 | M9: 4 | N9: 100 | O9: 9 | P9: 25 | Q9: =IFERROR(IF(AO9>1,AO9,60*60*8*O9/P9/E9),"") -> 25.92 | R9: =IFERROR(60*60*8*O9/E9/Q9,"") -> 25 | S9: =IFERROR(R9/8,"") -> 3.125 | T9: =IFERROR(IF(R9>2,S9,""),"") -> 3.125
A10: 727 | B10: Venta Normal | C10: GN | D10: ART. 1510 OPS | E10: 800 | F10: 0.0086 | G10: 0.006 | H10: =(F10-G10)/F10 -> 0.30232558 | I10: OPS | J10: UNICLEAR CRISTAL OPS 460 x 300 | K10: CAJA Nº 12 | L10: BOLSAS DE 120 X 110 | O10: 9 | P10: 20 | Q10: =IFERROR(IF(AO10>1,AO10,60*60*8*O10/P10/E10),"") -> 16.2 | R10: =IFERROR(60*60*8*O10/E10/Q10,"") -> 20 | S10: =IFERROR(R10/8,"") -> 2.5 | T10: =IFERROR(IF(R10>2,S10,""),"") -> 2.5
A11: 728 | B11: Venta Normal | C11: GN | D11: ART. 1510 PAI NEGRO | E11: 800 | F11: 0.0131 | G11: 0.0068 | H11: =(F11-G11)/F11 -> 0.48091603 | I11: HIPST | J11: PAI NEGRO 600 x 350 | K11: CAJA Nº 12 | L11: BOLSAS DE 120 X 110 | O11: 9 | P11: 20 | Q11: =IFERROR(IF(AO11>1,AO11,60*60*8*O11/P11/E11),"") -> 16.2 | R11: =IFERROR(60*60*8*O11/E11/Q11,"") -> 20 | S11: =IFERROR(R11/8,"") -> 2.5 | T11: =IFERROR(IF(R11>2,S11,""),"") -> 2.5
A12: 1910 | B12: Venta Normal | C12: GN | D12: ART. 1550 | E12: 400 | F12: 0.0146 | G12: 0.0105 | H12: =(F12-G12)/F12 -> 0.28082192 | I12: PVC | J12: PVC CRISTAL 460 x 400 | K12: CAJA Nº 2 | L12: BOLSAS DE 120 X 80 | O12: 9 | P12: 70 | Q12: =IFERROR(IF(AO12>1,AO12,60*60*8*O12/P12/E12),"") -> 6.6 | R12: =IFERROR(60*60*8*O12/E12/Q12,"") -> 98.181818 | S12: =IFERROR(R12/8,"") -> 12.272727 | T12: =IFERROR(IF(R12>2,S12,""),"") -> 12.272727 | AD12: 45519 | AE12: 14 | AF12: 1.4 | AG12: 0.4 | AH12: 1.4 | AI12: 0.4 | AJ12: 1 | AK12: 0.15 | AL12: 0.19 | AM12: 0.6 | AN12: 0.4 | AO12: 6.6 | AP12: 58 | AQ12: 109 | AR12: 109 | AS12: 109 | AT12: 40 | AU12: 20 | AV12: 40 | AW12: 20 | AX12: 7' | AY12: 465 | AZ12: Normal | BA12: 1100 | BB12: 10
A13: 726 | B13: Venta Normal | C13: GN | D13: ART. 1550 OPS | E13: 800 | F13: 0.0115 | G13: 0.008 | H13: =(F13-G13)/F13 -> 0.30434783 | I13: OPS | J13: DEXTON PS 825EH | K13: CAJA Nº 4/1 | L13: BOLSAS DE 120 X 125 | O13: 9 | P13: 24 | Q13: =IFERROR(IF(AO13>1,AO13,60*60*8*O13/P13/E13),"") -> 13.5 | R13: =IFERROR(60*60*8*O13/E13/Q13,"") -> 24 | S13: =IFERROR(R13/8,"") -> 3 | T13: =IFERROR(IF(R13>2,S13,""),"") -> 3
A14: 1914 | B14: Venta Normal | C14: GN | D14: ART. 1560 | E14: 300 | F14: 0.0262 | G14: 0.0214 | H14: =(F14-G14)/F14 -> 0.18320611 | I14: PVC | J14: PVC CRISTAL 575 x 250 | K14: CAJA Nº 2 | L14: BOLSAS DE 120 X 80 | M14: 1 | N14: 300 | O14: 3 | P14: 45 | Q14: =IFERROR(IF(AO14>1,AO14,60*60*8*O14/P14/E14),"") -> 4.4 | R14: =IFERROR(60*60*8*O14/E14/Q14,"") -> 65.454545 | S14: =IFERROR(R14/8,"") -> 8.1818182 | T14: =IFERROR(IF(R14>2,S14,""),"") -> 8.1818182 | AD14: 45538 | AE14: 15 | AF14: 0.9 | AG14: 0.2 | AH14: 1 | AI14: 0.2 | AJ14: 0.55 | AK14: 0.17 | AL14: 0.17 | AM14: 0.4 | AN14: 0.3 | AO14: 4.4 | AP14: 61 | AQ14: 103 | AR14: 103 | AS14: 103 | AT14: 38 | AU14: 20 | AV14: 40 | AW14: 20 | AX14: 100 | AY14: 365 | AZ14: Normal | BA14: 1500 | BB14: 10 | BE14: =AO14/4.5-1 -> -0.022222222 | BF14: 20/3/2024 / 22/7/24 | BG14: 13/15 | BH14: 1 / 1,5 | BI14: 0,1 / 0,2 | BJ14: 1,1 /1,3 | BK14: 0,1 / 0,2 | BL14: 0,8 / 1,00 | BM14: 0,2 / 0,18 | BN14: 0,22 / 0,15 | BO14: 0,4 / 0,45 | BP14: 0,3 /0,2 | BQ14: 4,5 / 5,6 | BR14: 59 / 62 | BS14: 104 / 103 | BT14: 104 / 103 | BU14: 104 / 103 | BV14: 45 / 38 | BW14: 20 / 20 | BX14: 40 / 40 | BY14: 20 / 20 | BZ14: 100 / 100 | CA14: 359 / 365 | CB14: Normal | CC14: 700 / 1500 | CD14: 10 / 10
A15: 1825 | B15: Venta Normal | C15: GN | D15: ART. 1560 - OBSOLETO | E15: 500 | F15: 0.0262 | G15: 0.0214 | H15: =(F15-G15)/F15 -> 0.18320611 | I15: PVC | J15: PVC CRISTAL 575 x 250 | K15: CAJA Nº 15 | L15: BOLSAS DE 120 X 110 | O15: 3 | P15: 33 | Q15: =IFERROR(IF(AO15>1,AO15,60*60*8*O15/P15/E15),"") -> 5.2363636 | R15: =IFERROR(60*60*8*O15/E15/Q15,"") -> 33 | S15: =IFERROR(R15/8,"") -> 4.125 | T15: =IFERROR(IF(R15>2,S15,""),"") -> 4.125
A16: 1813 | B16: Discontinuado | C16: GN | D16: ART. 1560 PVC (300M) | E16: 500 | F16: 0.0311 | G16: 0.0254 | H16: =(F16-G16)/F16 -> 0.18327974 | I16: PVC | J16: PVC CRISTAL 570 x 300 | K16: CAJA Nº 16 | L16: BOLSAS DE 120 X 125 | O16: 3 | Q16: =IFERROR(IF(AO16>1,AO16,60*60*8*O16/P16/E16),"") | R16: =IFERROR(60*60*8*O16/E16/Q16,"") | S16: =IFERROR(R16/8,"") | T16: =IFERROR(IF(R16>2,S16,""),"")
A17: 104 | B17: Venta Normal | C17: GN | D17: ART. 1610 (200) | E17: 200 | F17: 0.0115 | G17: 0.0087 | H17: =(F17-G17)/F17 -> 0.24347826 | I17: PVC | J17: PVC CRISTAL 520 x 250 | O17: 6 | P17: 70 | Q17: =IFERROR(IF(AO17>1,AO17,60*60*8*O17/P17/E17),"") -> 7.9 | R17: =IFERROR(60*60*8*O17/E17/Q17,"") -> 109.36709 | S17: =IFERROR(R17/8,"") -> 13.670886 | T17: =IFERROR(IF(R17>2,S17,""),"") -> 13.670886 | AD17: 45607 | AE17: 14 | AF17: 2 | AG17: 0.45 | AH17: 2.7 | AI17: 0.45 | AJ17: 0.6 | AK17: 0.2 | AL17: 0.14 | AM17: 0.6 | AN17: 0.3 | AO17: 7.9 | AP17: 42 | AQ17: 102 | AR17: 102 | AS17: 102 | AT17: 40 | AU17: 20 | AV17: 40 | AW17: 20 | AX17: 70 | AY17: 360 | AZ17: Normal | BA17: 900 | BB17: 10
A18: 43 | B18: Discontinuado | C18: GN | D18: ART. 1610 OPS | E18: 300 | F18: 0.0091 | G18: 0.0064 | H18: =(F18-G18)/F18 -> 0.2967033 | I18: OPS | J18: UNICLEAR CRISTAL OPS 520 x 250 | K18: CAJA Nº 14 | L18: BOLSAS DE 120 X 110 | O18: 6 | Q18: =IFERROR(IF(AO18>1,AO18,60*60*8*O18/P18/E18),"") | R18: =IFERROR(60*60*8*O18/E18/Q18,"") | S18: =IFERROR(R18/8,"") | T18: =IFERROR(IF(R18>2,S18,""),"")
A19: 105 | B19: Venta Normal | C19: GN | D19: ART. 1690 (200) | E19: 200 | F19: 0.0231 | G19: 0.0173 | H19: =(F19-G19)/F19 -> 0.25108225 | I19: PVC | J19: PVC CRISTAL 520 x 500 | K19: CAJA Nº 16 | L19: BOLSAS DE 120 X 110 | M19: 4 | N19: 50 | O19: 6 | P19: 46 | Q19: =IFERROR(IF(AO19>1,AO19,60*60*8*O19/P19/E19),"") -> 11.4 | R19: =IFERROR(60*60*8*O19/E19/Q19,"") -> 75.789474 | S19: =IFERROR(R19/8,"") -> 9.4736842 | T19: =IFERROR(IF(R19>2,S19,""),"") -> 9.4736842 | AD19: 45604 | AE19: 13 | AF19: 3.5 | AG19: 0.4 | AH19: 3.7 | AI19: 0.5 | AJ19: 1.2 | AK19: 0.19 | AL19: 0.16 | AM19: 0.9 | AN19: 0.35 | AO19: 11.4 | AP19: 50 | AQ19: 107 | AR19: 107 | AS19: 107 | AT19: 49 | AU19: 20 | AV19: 40 | AW19: 20 | AX19: 65 | AY19: 386 | AZ19: Normal | BA19: 1000
A20: 113 | B20: Venta Normal | C20: GN | D20: ART. 1690 BASE | E20: 300 | F20: 0.0231 | G20: 0.0173 | H20: =(F20-G20)/F20 -> 0.25108225 | I20: PVC | J20: PVC CRISTAL 520 x 500 | K20: CAJA Nº 15 | L20: BOLSAS DE 120 X 110 | O20: 6 | P20: 26 | Q20: =IFERROR(IF(AO20>1,AO20,60*60*8*O20/P20/E20),"") -> 22.153846 | R20: =IFERROR(60*60*8*O20/E20/Q20,"") -> 26 | S20: =IFERROR(R20/8,"") -> 3.25 | T20: =IFERROR(IF(R20>2,S20,""),"") -> 3.25
A21: 107 | B21: Venta Normal | C21: GN | D21: ART. 1690 BASE Y TAPA | E21: 200 | F21: 0.0346 | G21: 0.026 | H21: =(F21-G21)/F21 -> 0.24855491 | I21: PVC | J21: PVC CRISTAL 100 x 10000 | O21: 6 | P21: 55 | Q21: =IFERROR(IF(AO21>1,AO21,60*60*8*O21/P21/E21),"") -> 15.709091 | R21: =IFERROR(60*60*8*O21/E21/Q21,"") -> 55 | S21: =IFERROR(R21/8,"") -> 6.875 | T21: =IFERROR(IF(R21>2,S21,""),"") -> 6.875
A22: 44 | B22: Venta Normal | C22: GN | D22: ART. 1690 OPS | E22: 300 | F22: 0.0217 | G22: 0.015 | H22: =(F22-G22)/F22 -> 0.30875576 | I22: OPS | J22: UNICLEAR CRISTAL OPS 520 x 600 | K22: CAJA Nº 15 | L22: BOLSAS DE 120 X 110 | O22: 6 | P22: 40 | Q22: =IFERROR(IF(AO22>1,AO22,60*60*8*O22/P22/E22),"") -> 14.4 | R22: =IFERROR(60*60*8*O22/E22/Q22,"") -> 40 | S22: =IFERROR(R22/8,"") -> 5 | T22: =IFERROR(IF(R22>2,S22,""),"") -> 5
A23: 1911 | B23: Venta Normal | C23: GN | D23: ART. 1810 | E23: 300 | F23: 0.0168 | G23: 0.013 | H23: =(F23-G23)/F23 -> 0.22619048 | I23: PVC | J23: PVC CRISTAL 380 x 300 | K23: CAJA Nº 2 | L23: BOLSAS DE 120 X 80 | O23: 4 | P23: 25 | Q23: =IFERROR(IF(AO23>1,AO23,60*60*8*O23/P23/E23),"") -> 15.36 | R23: =IFERROR(60*60*8*O23/E23/Q23,"") -> 25 | S23: =IFERROR(R23/8,"") -> 3.125 | T23: =IFERROR(IF(R23>2,S23,""),"") -> 3.125
A24: 1935 | B24: Venta Normal | C24: GN | D24: ART. 1810 NEGRO | E24: 300 | F24: 0.0154 | G24: 0.0105 | H24: =(F24-G24)/F24 -> 0.31818182 | I24: PVC | J24: PAI NEGRO 380 x 350 | K24: CAJA Nº 2 | L24: BOLSAS DE 120 X 80 | O24: 4 | P24: 30 | Q24: =IFERROR(IF(AO24>1,AO24,60*60*8*O24/P24/E24),"") -> 12.8 | R24: =IFERROR(60*60*8*O24/E24/Q24,"") -> 30 | S24: =IFERROR(R24/8,"") -> 3.75 | T24: =IFERROR(IF(R24>2,S24,""),"") -> 3.75
A25: 731 | B25: Venta Normal | C25: GN | D25: ART. 1810 OPS | E25: 540 | F25: 0.0132 | G25: 0.0094 | H25: =(F25-G25)/F25 -> 0.28787879 | I25: OPS | J25: UNICLEAR CRISTAL OPS 455 x 400 | K25: CAJA Nº 4/1 | L25: BOLSAS DE 120 X 125 | O25: 4 | P25: 28 | Q25: =IFERROR(IF(AO25>1,AO25,60*60*8*O25/P25/E25),"") -> 7.6190476 | R25: =IFERROR(60*60*8*O25/E25/Q25,"") -> 28 | S25: =IFERROR(R25/8,"") -> 3.5 | T25: =IFERROR(IF(R25>2,S25,""),"") -> 3.5
A26: 732 | B26: Venta Normal | C26: GN | D26: ART. 1810 PAI NEGRO | E26: 540 | F26: 0.0243 | G26: 0.0105 | H26: =(F26-G26)/F26 -> 0.56790123 | I26: HIPST | J26: PAI NEGRO 600 x 350 | K26: CAJA Nº 4/1 | L26: BOLSAS DE 120 X 125 | O26: 4 | P26: 28 | Q26: =IFERROR(IF(AO26>1,AO26,60*60*8*O26/P26/E26),"") -> 7.6190476 | R26: =IFERROR(60*60*8*O26/E26/Q26,"") -> 28 | S26: =IFERROR(R26/8,"") -> 3.5 | T26: =IFERROR(IF(R26>2,S26,""),"") -> 3.5
A27: 1912 | B27: Venta Normal | C27: GN | D27: ART. 1845 | E27: 300 | F27: 0.0223 | G27: 0.0162 | H27: =(F27-G27)/F27 -> 0.2735426 | I27: PVC | J27: PVC CRISTAL 380 x 400 | K27: CAJA Nº 15 | L27: BOLSAS DE 120 X 110 | O27: 4 | P27: 25 | Q27: =IFERROR(IF(AO27>1,AO27,60*60*8*O27/P27/E27),"") -> 15.36 | R27: =IFERROR(60*60*8*O27/E27/Q27,"") -> 25 | S27: =IFERROR(R27/8,"") -> 3.125 | T27: =IFERROR(IF(R27>2,S27,""),"") -> 3.125
A28: 729 | B28: Venta Normal | C28: GN | D28: ART. 1845 OPS | E28: 540 | F28: 0.0176 | G28: 0.0128 | H28: =(F28-G28)/F28 -> 0.27272727 | I28: OPS | J28: UNICLEAR CRISTAL OPS 380 x 400 | K28: CAJA Nº 4/1 | L28: BOLSAS DE 120 X 125 | O28: 4 | P28: 30 | Q28: =IFERROR(IF(AO28>1,AO28,60*60*8*O28/P28/E28),"") -> 7.1111111 | R28: =IFERROR(60*60*8*O28/E28/Q28,"") -> 30 | S28: =IFERROR(R28/8,"") -> 3.75 | T28: =IFERROR(IF(R28>2,S28,""),"") -> 3.75
A29: 1913 | B29: Venta Normal | C29: GN | D29: ART. 1860 | E29: 300 | F29: 0.0251 | G29: 0.0182 | H29: =(F29-G29)/F29 -> 0.2749004 | I29: PVC | J29: PVC CRISTAL 380 x 450 | K29: CAJA Nº 15 | L29: BOLSAS DE 120 X 110 | O29: 4 | P29: 25 | Q29: =IFERROR(IF(AO29>1,AO29,60*60*8*O29/P29/E29),"") -> 15.36 | R29: =IFERROR(60*60*8*O29/E29/Q29,"") -> 25 | S29: =IFERROR(R29/8,"") -> 3.125 | T29: =IFERROR(IF(R29>2,S29,""),"") -> 3.125
A30: 730 | B30: Venta Normal | C30: GN | D30: ART. 1860 OPS | E30: 540 | F30: 0.0198 | G30: 0.0155 | H30: =(F30-G30)/F30 -> 0.21717172 | I30: OPS | J30: DEXTON PS945EH | K30: CAJA Nº 4/1 | L30: BOLSAS DE 120 X 125 | O30: 4 | P30: 28 | Q30: =IFERROR(IF(AO30>1,AO30,60*60*8*O30/P30/E30),"") -> 7.6190476 | R30: =IFERROR(60*60*8*O30/E30/Q30,"") -> 28 | S30: =IFERROR(R30/8,"") -> 3.5 | T30: =IFERROR(IF(R30>2,S30,""),"") -> 3.5
A31: 1814 | B31: Venta Normal | C31: GN | D31: ART. 2050 | E31: 520 | F31: 0.025 | G31: 0.0204 | H31: =(F31-G31)/F31 -> 0.184 | I31: PET | J31: PET CRISTAL 460 x 250 | K31: CAJA Nº 12 | L31: BOLSAS DE 120 X 110 | O31: 2 | P31: 34 | Q31: =IFERROR(IF(AO31>1,AO31,60*60*8*O31/P31/E31),"") -> 3.2579186 | R31: =IFERROR(60*60*8*O31/E31/Q31,"") -> 34 | S31: =IFERROR(R31/8,"") -> 4.25 | T31: =IFERROR(IF(R31>2,S31,""),"") -> 4.25
A32: 1915 | B32: Venta Normal | C32: GN | D32: ART. 2050 (X 300) | E32: 300 | F32: 0.025 | G32: 0.0204 | H32: =(F32-G32)/F32 -> 0.184 | I32: PET | J32: PET CRISTAL 460 x 250 | K32: CAJA Nº 1/2 | L32: BOLSAS DE 120 X 80 | M32: 1 | N32: 300 | O32: 2 | P32: 45 | Q32: =IFERROR(IF(AO32>1,AO32,60*60*8*O32/P32/E32),"") -> 4 | R32: =IFERROR(60*60*8*O32/E32/Q32,"") -> 48 | S32: =IFERROR(R32/8,"") -> 6 | T32: =IFERROR(IF(R32>2,S32,""),"") -> 6 | AD32: 45411 | AE32: 16 | AF32: 0.9 | AG32: 0.1 | AH32: 1 | AI32: 0.1 | AJ32: 0.3 | AK32: 0.36 | AL32: 0.2 | AM32: 0.14 | AN32: 0.5 | AO32: 4 | AP32: 45 | AQ32: 104 | AR32: 109 | AS32: 114 | AT32: 40 | AY32: 383 | BC32: 111 | BD32: 112
A33: 1815 | B33: Venta Normal | C33: GN | D33: ART. 2060 | E33: 520 | F33: 0.025 | G33: 0.0204 | H33: =(F33-G33)/F33 -> 0.184 | I33: PET | J33: PET CRISTAL 460 x 250 | K33: CAJA Nº 12 | L33: BOLSAS DE 120 X 110 | O33: 2 | P33: 34 | Q33: =IFERROR(IF(AO33>1,AO33,60*60*8*O33/P33/E33),"") -> 3.2579186 | R33: =IFERROR(60*60*8*O33/E33/Q33,"") -> 34 | S33: =IFERROR(R33/8,"") -> 4.25 | T33: =IFERROR(IF(R33>2,S33,""),"") -> 4.25
A34: 1916 | B34: Venta Normal | C34: GN | D34: ART. 2060 (X 300) | E34: 300 | F34: 0.025 | G34: 0.0204 | H34: =(F34-G34)/F34 -> 0.184 | I34: PET | J34: PET CRISTAL 460 x 250 | K34: CAJA Nº 1/2 | L34: BOLSAS DE 120 X 80 | M34: 1 | N34: 300 | O34: 2 | P34: 50 | Q34: =IFERROR(IF(AO34>1,AO34,60*60*8*O34/P34/E34),"") -> 3.6 | R34: =IFERROR(60*60*8*O34/E34/Q34,"") -> 53.333333 | S34: =IFERROR(R34/8,"") -> 6.6666667 | T34: =IFERROR(IF(R34>2,S34,""),"") -> 6.6666667 | U34: =1000/R34 -> 18.75 | V34: =R34*0.85 -> 45.333333 | AD34: 45378 | AE34: 14 / 15 | AF34: 0.8 | AG34: 0.1 | AH34: 1 | AI34: 0.13 | AJ34: 0.25 | AK34: 0.14 | AL34: 0.21 | AM34: 0.3 | AN34: 0.2 | AO34: 3.6 | AP34: 48 | AQ34: 103 | AR34: 103 | AS34: 103 | AT34: 40 | AU34: 20 | AV34: 40 | AW34: 20 | AX34: 100 | AY34: 294 | AZ34: Normal | BA34: 1200 | BB34: 10
A35: 1138 | B35: Venta Normal | C35: GN | D35: ART. 2060 (X 300) (DISCONTINUADO) | E35: 300 | F35: 0.025 | G35: 0.0204 | H35: =(F35-G35)/F35 -> 0.184 | I35: PET | J35: PET CRISTAL 460 x 250 | K35: CAJA Nº 1/2 | L35: BOLSAS DE 120 X 80 | O35: 2 | P35: 45 | Q35: =IFERROR(IF(AO35>1,AO35,60*60*8*O35/P35/E35),"") -> 4.2666667 | R35: =IFERROR(60*60*8*O35/E35/Q35,"") -> 45 | S35: =IFERROR(R35/8,"") -> 5.625 | T35: =IFERROR(IF(R35>2,S35,""),"") -> 5.625
A36: 1816 | B36: Venta Normal | C36: GN | D36: ART. 2060 MPH | E36: 520 | F36: 0.025 | G36: 0.0204 | H36: =(F36-G36)/F36 -> 0.184 | I36: PVC | J36: PVC CRISTAL 460 x 250 | K36: CAJA Nº 4/1 | L36: BOLSAS DE 120 X 125 | O36: 2 | P36: 28 | Q36: =IFERROR(IF(AO36>1,AO36,60*60*8*O36/P36/E36),"") -> 3.956044 | R36: =IFERROR(60*60*8*O36/E36/Q36,"") -> 28 | S36: =IFERROR(R36/8,"") -> 3.5 | T36: =IFERROR(IF(R36>2,S36,""),"") -> 3.5
A37: 2079 | B37: Venta Normal | C37: GN | D37: ART. 2060 MPH | E37: 200 | F37: 0.025 | G37: 0.0204 | H37: =(F37-G37)/F37 -> 0.184 | I37: PVC | J37: PVC CRISTAL 460 x 250 | K37: CAJA Nº 1/2 | L37: BOLSAS DE 120 X 80 | O37: 2 | P37: 73 | Q37: =IFERROR(IF(AO37>1,AO37,60*60*8*O37/P37/E37),"") -> 3.9452055 | R37: =IFERROR(60*60*8*O37/E37/Q37,"") -> 73 | S37: =IFERROR(R37/8,"") -> 9.125 | T37: =IFERROR(IF(R37>2,S37,""),"") -> 9.125
A38: 1817 | B38: Venta Normal | C38: GN | D38: ART. 2075 | E38: 200 | F38: 0.0403 | G38: 0.0348 | H38: =(F38-G38)/F38 -> 0.13647643 | I38: PVC | J38: PVC CRISTAL 480 x 250 | K38: CAJA Nº 4/1 | L38: BOLSAS DE 120 X 125 | O38: 2 | P38: 40 | Q38: =IFERROR(IF(AO38>1,AO38,60*60*8*O38/P38/E38),"") -> 7.2 | R38: =IFERROR(60*60*8*O38/E38/Q38,"") -> 40 | S38: =IFERROR(R38/8,"") -> 5 | T38: =IFERROR(IF(R38>2,S38,""),"") -> 5
A39: 1818 | B39: Venta Normal | C39: GN | D39: ART. 2095 | E39: 200 | F39: 0.0299 | G39: 0.0247 | H39: =(F39-G39)/F39 -> 0.17391304 | I39: PVC | J39: PVC CRISTAL 460 x 300 | K39: CAJA Nº 1/2 | L39: BOLSAS DE 120 X 80 | M39: 1 | N39: 200 | O39: 2 | P39: 58 | Q39: =IFERROR(IF(AO39>1,AO39,60*60*8*O39/P39/E39),"") -> 4.6 | R39: =IFERROR(60*60*8*O39/E39/Q39,"") -> 62.608696 | S39: =IFERROR(R39/8,"") -> 7.826087 | T39: =IFERROR(IF(R39>2,S39,""),"") -> 7.826087 | Z39: Christian | AD39: 45391 | AE39: 15 | AF39: 1 | AG39: 0.1 | AH39: 1 | AI39: 0.1 | AJ39: 0.5 | AK39: 0.2 | AL39: 0.16 | AM39: 0.7 | AN39: 0.3 | AO39: 4.6 | AP39: 45 | AQ39: 106 | AR39: 106 | AS39: 106 | AT39: 50 | AU39: 20 | AV39: 40 | AW39: 20 | AX39: 100 | AY39: 297 | AZ39: Normal | BA39: 1000 | BB39: 10
A40: 1819 | B40: Venta Normal | C40: GN | D40: ART. 2450 | E40: 360 | F40: 0.0343 | G40: 0.0283 | H40: =(F40-G40)/F40 -> 0.17492711 | I40: PVC | J40: PVC CRISTAL 560 x 250 | K40: CAJA Nº 17 | L40: BOLSAS DE 120 X 110 | M40: 2 | N40: 180 | O40: 2 | P40: 41 | Q40: =IFERROR(IF(AO40>1,AO40,60*60*8*O40/P40/E40),"") -> 3.6 | R40: =IFERROR(60*60*8*O40/E40/Q40,"") -> 44.444444 | S40: =IFERROR(R40/8,"") -> 5.5555556 | T40: =IFERROR(IF(R40>2,S40,""),"") -> 5.5555556 | Z40: Christian | AD40: 45504 | AE40: 12 | AF40: 0.8 | AG40: 0.15 | AH40: 0.8 | AI40: 0.15 | AJ40: 0.4 | AK40: 0.12 | AL40: 0.16 | AM40: 0.33 | AN40: 0.15 | AO40: 3.6 | AP40: 51 | AQ40: 104 | AR40: 104 | AS40: 104 | AT40: 40 | AU40: 30 | AV40: 40 | AW40: 40 | AX40: 100 | AY40: 330 | AZ40: Normal | BA40: 2400 | BB40: 10
A41: 1820 | B41: Venta Normal | C41: GN | D41: ART. 2465 | E41: 900 | F41: 0.0184 | G41: 0.0158 | H41: =(F41-G41)/F41 -> 0.14130435 | I41: PVC | J41: PVC CRISTAL 420 x 250 | K41: CAJA Nº 4/1 | L41: BOLSAS DE 120 X 125 | O41: 4 | P41: 20 | Q41: =IFERROR(IF(AO41>1,AO41,60*60*8*O41/P41/E41),"") -> 6.4 | R41: =IFERROR(60*60*8*O41/E41/Q41,"") -> 20 | S41: =IFERROR(R41/8,"") -> 2.5 | T41: =IFERROR(IF(R41>2,S41,""),"") -> 2.5
A42: 1922 | B42: Venta Normal | C42: GN | D42: ART. 2465 | E42: 300 | F42: 0.0184 | G42: 0.0158 | H42: =(F42-G42)/F42 -> 0.14130435 | I42: PVC | J42: PVC CRISTAL 420 x 250 | K42: CAJA Nº 2 | L42: BOLSAS DE 120 X 80 | M42: 3 | N42: 100 | O42: 4 | P42: 60 | Q42: =IFERROR(IF(AO42>1,AO42,60*60*8*O42/P42/E42),"") -> 5.1 | R42: =IFERROR(60*60*8*O42/E42/Q42,"") -> 75.294118 | S42: =IFERROR(R42/8,"") -> 9.4117647 | T42: =IFERROR(IF(R42>2,S42,""),"") -> 9.4117647 | AD42: 45517 | AE42: 15 | AF42: 1.4 | AG42: 0.3 | AH42: 1.4 | AI42: 0.3 | AJ42: 0.5 | AK42: 0.18 | AL42: 0.18 | AM42: 0.4 | AN42: 0.17 | AO42: 5.1 | AP42: 52 | AQ42: 109 | AR42: 109 | AS42: 107 | AT42: 38 | AU42: 20 | AV42: 40 | AW42: 20 | AX42: 100 | AY42: 450 | AZ42: Normal | BA42: 2000 | BB42: 10 | BE42: =AO42/BQ42-1 -> -0.019230769 | BF42: 45404 | BG42: 12 | BH42: 1.3 | BI42: 0.3 | BJ42: 1.2 | BK42: 0.3 | BL42: 0.7 | BM42: 0.15 | BN42: 0.18 | BO42: 0.4 | BP42: 0.3 | BQ42: 5.2 | BR42: 49 | BS42: 106 | BT42: 106 | BU42: 106 | BV42: 40 | BW42: 38 | BX42: 40 | BY42: 40 | BZ42: 101 | CA42: 459 | CB42: Normal | CC42: 2000 | CD42: 10
A43: 1796 | B43: Discontinuado | C43: GN | D43: ART. 2465 OPS | E43: 900 | F43: 0.0101 | G43: 0.0114 | H43: =(F43-G43)/F43 -> -0.12871287 | I43: OPS | J43: UNICLEAR CRISTAL OPS 460 x 250 | K43: CAJA Nº 4/1 | L43: BOLSAS DE 120 X 125 | O43: 4 | Q43: =IFERROR(IF(AO43>1,AO43,60*60*8*O43/P43/E43),"") | R43: =IFERROR(60*60*8*O43/E43/Q43,"") | S43: =IFERROR(R43/8,"") | T43: =IFERROR(IF(R43>2,S43,""),"")
A44: 2088 | B44: Venta Normal | C44: GN | D44: ART. 2465 PET | E44: 300 | F44: 0.0184 | G44: 0.0158 | H44: =(F44-G44)/F44 -> 0.14130435 | I44: PET | J44: PET CRISTAL 420 x 250 | K44: CAJA Nº 2 | L44: BOLSAS DE 120 X 80 | M44: 3 | N44: 100 | O44: 4 | P44: 60 | Q44: =IFERROR(IF(AO44>1,AO44,60*60*8*O44/P44/E44),"") -> 5.1 | R44: =IFERROR(60*60*8*O44/E44/Q44,"") -> 75.294118 | S44: =IFERROR(R44/8,"") -> 9.4117647 | T44: =IFERROR(IF(R44>2,S44,""),"") -> 9.4117647 | AD44: 45517 | AE44: 15 | AF44: 1.4 | AG44: 0.3 | AH44: 1.4 | AI44: 0.3 | AJ44: 0.5 | AK44: 0.18 | AL44: 0.18 | AM44: 0.4 | AN44: 0.17 | AO44: 5.1 | AP44: 52 | AQ44: 109 | AR44: 109 | AS44: 107 | AT44: 38 | AU44: 20 | AV44: 40 | AW44: 20 | AX44: 100 | AY44: 450 | AZ44: Normal | BA44: 2000 | BB44: 10 | BE44: =AO44/BQ44-1 -> -0.019230769 | BF44: 45404 | BG44: 12 | BH44: 1.3 | BI44: 0.3 | BJ44: 1.2 | BK44: 0.3 | BL44: 0.7 | BM44: 0.15 | BN44: 0.18 | BO44: 0.4 | BP44: 0.3 | BQ44: 5.2 | BR44: 49 | BS44: 106 | BT44: 106 | BU44: 106 | BV44: 40 | BW44: 38 | BX44: 40 | BY44: 40 | BZ44: 101 | CA44: 459 | CB44: Normal | CC44: 2000 | CD44: 10
A45: 1821 | B45: Venta Normal | C45: GN | D45: ART. 2475 | E45: 360 | F45: 0.0343 | G45: 0.0283 | H45: =(F45-G45)/F45 -> 0.17492711 | I45: PVC | J45: PVC CRISTAL 560 x 250 | K45: CAJA Nº 17 | L45: BOLSAS DE 120 X 110 | M45: 2 | N45: 180 | O45: 2 | P45: 41 | Q45: =IFERROR(IF(AO45>1,AO45,60*60*8*O45/P45/E45),"") -> 3.6 | R45: =IFERROR(60*60*8*O45/E45/Q45,"") -> 44.444444 | S45: =IFERROR(R45/8,"") -> 5.5555556 | T45: =IFERROR(IF(R45>2,S45,""),"") -> 5.5555556 | Z45: Christian | AD45: 45376 | AE45: 12 | AF45: 1.1 | AG45: 0.1 | AH45: 1.1 | AI45: 0.1 | AJ45: 0.45 | AK45: 0.12 | AL45: 0.22 | AM45: 0.4 | AN45: 0.18 | AO45: 3.6 | AP45: 46 | AQ45: 106 | AR45: 106 | AS45: 106 | AT45: 40 | AU45: 30 | AV45: 40 | AW45: 40 | AX45: 101 | AY45: 331 | AZ45: Normal | BA45: 2500 | BB45: 10
A46: 2090 | B46: Venta Normal | C46: GN | D46: ART. 2475 PET | E46: 360 | F46: 0.0343 | G46: 0.0283 | H46: =(F46-G46)/F46 -> 0.17492711 | I46: PET | J46: PET CRISTAL 560 x 250 | K46: CAJA Nº 17 | L46: BOLSAS DE 120 X 110 | M46: 2 | N46: 180 | O46: 2 | P46: 41 | Q46: =IFERROR(IF(AO46>1,AO46,60*60*8*O46/P46/E46),"") -> 3.6 | R46: =IFERROR(60*60*8*O46/E46/Q46,"") -> 44.444444 | S46: =IFERROR(R46/8,"") -> 5.5555556 | T46: =IFERROR(IF(R46>2,S46,""),"") -> 5.5555556 | Z46: Christian | AD46: 45376 | AE46: 12 | AF46: 1.1 | AG46: 0.1 | AH46: 1.1 | AI46: 0.1 | AJ46: 0.45 | AK46: 0.12 | AL46: 0.22 | AM46: 0.4 | AN46: 0.18 | AO46: 3.6 | AP46: 46 | AQ46: 106 | AR46: 106 | AS46: 106 | AT46: 40 | AU46: 30 | AV46: 40 | AW46: 40 | AX46: 101 | AY46: 331 | AZ46: Normal | BA46: 2500 | BB46: 10
A47: 1822 | B47: Venta Normal | C47: GN | D47: ART. 2508 | E47: 200 | F47: 0.0506 | G47: 0.0423 | H47: =(F47-G47)/F47 -> 0.16403162 | I47: PET | J47: PET CRISTAL 560 x 300 | K47: CAJA Nº 3 | L47: BOLSAS DE 120 X 80 | M47: 2 | N47: 100 | O47: 2 | P47: 55 | Q47: =IFERROR(IF(AO47>1,AO47,60*60*8*O47/P47/E47),"") -> 4.8 | R47: =IFERROR(60*60*8*O47/E47/Q47,"") -> 60 | S47: =IFERROR(R47/8,"") -> 7.5 | T47: =IFERROR(IF(R47>2,S47,""),"") -> 7.5 | AD47: 45559 | AE47: 13 | AF47: 0.9 | AG47: 0.2 | AH47: 1 | AI47: 0.33 | AJ47: 0.8 | AK47: 0.15 | AL47: 0.21 | AM47: 0.4 | AN47: 0.4 | AO47: 4.8 | AP47: 55 | AQ47: 112 | AR47: 108 | AS47: 109 | AT47: 45 | AU47: 30 | AV47: 80 | AW47: 30 | AX47: 100 | AY47: 400 | AZ47: Normal | BA47: 400 | BB47: 10
A48: 1823 | B48: Venta Normal | C48: GN | D48: ART. 2510 | E48: 200 | F48: 0.0506 | G48: 0.0423 | H48: =(F48-G48)/F48 -> 0.16403162 | I48: PET | J48: PET CRISTAL 560 x 300 | K48: CAJA Nº 3 | L48: BOLSAS DE 120 X 80 | M48: 2 | N48: 100 | O48: 2 | P48: 55 | Q48: =IFERROR(IF(AO48>1,AO48,60*60*8*O48/P48/E48),"") -> 4.6 | R48: =IFERROR(60*60*8*O48/E48/Q48,"") -> 62.608696 | S48: 7,8 | T48: =IFERROR(IF(R48>2,S48,""),"") -> 7,8 | Z48: Christian | AD48: 45419 | AE48: 12 | AF48: 0.9 | AG48: 0.3 | AH48: 1 | AI48: 0.1 | AJ48: 0.14 | AK48: 0.19 | AL48: 0.7 | AM48: 0.6 | AN48: 0.25 | AO48: 4.6 | AP48: 50 | AQ48: 110 | AR48: 110 | AS48: 108 | AT48: 40 | AU48: 30 | AV48: 40 | AW48: 40 | AX48: 100 | AY48: 406 | AZ48: Normal | BA48: 1500 | BB48: 10
A49: 2021 | B49: Venta Normal | C49: GN | D49: ART. 2510 | E49: 200 | F49: 0.0506 | G49: 0.0423 | H49: =(F49-G49)/F49 -> 0.16403162 | I49: PVC | J49: PVC CRISTAL 560 x 300 | K49: CAJA Nº 3 | L49: BOLSAS DE 120 X 80 | M49: 2 | N49: 100 | O49: 2 | P49: 55 | Q49: =IFERROR(IF(AO49>1,AO49,60*60*8*O49/P49/E49),"") -> 4.6 | R49: =IFERROR(60*60*8*O49/E49/Q49,"") -> 62.608696 | S49: =IFERROR(R49/8,"") -> 7.826087 | T49: =IFERROR(IF(R49>2,S49,""),"") -> 7.826087 | Z49: Christian | AD49: 45419 | AE49: 12 | AF49: 0.9 | AG49: 0.3 | AH49: 1 | AI49: 0.1 | AJ49: 0.14 | AK49: 0.19 | AL49: 0.7 | AM49: 0.6 | AN49: 0.25 | AO49: 4.6 | AP49: 50 | AQ49: 110 | AR49: 110 | AS49: 108 | AT49: 40 | AU49: 30 | AV49: 40 | AW49: 40 | AX49: 100 | AY49: 406 | AZ49: Normal | BA49: 1500 | BB49: 10
A50: 1827 | B50: Venta Normal | C50: GN | D50: ART. 3110 | E50: 720 | F50: 0.0115 | G50: 0.009 | H50: =(F50-G50)/F50 -> 0.2173913 | I50: PVC | J50: PVC CRISTAL 520 x 250 | K50: CAJA Nº 4/1 | L50: BOLSAS DE 120 X 125 | O50: 3 | P50: 28 | Q50: =IFERROR(IF(AO50>1,AO50,60*60*8*O50/P50/E50),"") -> 4.2857143 | R50: =IFERROR(60*60*8*O50/E50/Q50,"") -> 28 | S50: =IFERROR(R50/8,"") -> 3.5 | T50: =IFERROR(IF(R50>2,S50,""),"") -> 3.5
A51: 2028 | B51: Venta Normal | C51: GN | D51: ART. 3110 CRISTAL (X 150) | E51: 150 | F51: 0.0115 | G51: 0.009 | H51: =(F51-G51)/F51 -> 0.2173913 | I51: PVC | J51: PVC CRISTAL 520 x 250 | O51: 3 | P51: 110 | Q51: =IFERROR(IF(AO51>1,AO51,60*60*8*O51/P51/E51),"") -> 4.2 | R51: =IFERROR(60*60*8*O51/E51/Q51,"") -> 137.14286 | S51: =IFERROR(R51/8,"") -> 17.142857 | T51: =IFERROR(IF(R51>2,S51,""),"") -> 17.142857 | Z51: Christian | AD51: 45605 | AE51: 12 | AF51: 1 | AG51: 0.2 | AH51: 1 | AI51: 0.2 | AJ51: 0.16 | AK51: 0.22 | AL51: 0.6 | AM51: 0.35 | AN51: 0.15 | AO51: 4.2 | AP51: 48 | AQ51: 100 | AR51: 102 | AS51: 102 | AT51: 36 | AU51: 20 | AV51: 40 | AW51: 20 | AX51: 101 | AY51: 189 | AZ51: Normal | BA51: 2200 | BB51: 10
A52: 2029 | B52: Venta Normal | C52: GN | D52: ART. 3110 CRISTAL (X 180) | E52: 180 | F52: 0.0115 | G52: 0.009 | H52: =(F52-G52)/F52 -> 0.2173913 | I52: PVC | J52: PVC CRISTAL 520 x 250 | O52: 3 | P52: 110 | Q52: =IFERROR(IF(AO52>1,AO52,60*60*8*O52/P52/E52),"") -> 4.2 | R52: =IFERROR(60*60*8*O52/E52/Q52,"") -> 114.28571 | S52: =IFERROR(R52/8,"") -> 14.285714 | T52: =IFERROR(IF(R52>2,S52,""),"") -> 14.285714 | Z52: Christian | AD52: 45605 | AE52: 12 | AF52: 1 | AG52: 0.2 | AH52: 1 | AI52: 0.2 | AJ52: 0.16 | AK52: 0.22 | AL52: 0.6 | AM52: 0.35 | AN52: 0.15 | AO52: 4.2 | AP52: 48 | AQ52: 100 | AR52: 102 | AS52: 102 | AT52: 36 | AU52: 20 | AV52: 40 | AW52: 20 | AX52: 101 | AY52: 189 | AZ52: Normal | BA52: 2200 | BB52: 10
A53: 2026 | B53: Venta Normal | C53: GN | D53: ART. 3110 NEGRO (X 150) | E53: 150 | F53: 0.0109 | G53: 0.0075 | H53: =(F53-G53)/F53 -> 0.31192661 | I53: HIPST | J53: PAI NEGRO 520 x 300 | M53: 6 | N53: 25 | O53: 3 | P53: 120 | Q53: =IFERROR(IF(AO53>1,AO53,60*60*8*O53/P53/E53),"") -> 4 | R53: =IFERROR(60*60*8*O53/E53/Q53,"") -> 144 | S53: =IFERROR(R53/8,"") -> 18 | T53: =IFERROR(IF(R53>2,S53,""),"") -> 18 | Z53: Christian | AD53: 45420 | AE53: 13 | AF53: 1 | AG53: 0.1 | AH53: 1 | AI53: 0.15 | AJ53: 0.45 | AK53: 0.28 | AL53: 0.12 | AM53: 0.41 | AN53: 0.1 | AO53: 4 | AP53: 44 | AQ53: 120 | AR53: 120 | AS53: 122 | AT53: 55 | AU53: 20 | AV53: 40 | AW53: 20 | AX53: 65 | AY53: 178 | AZ53: Normal | BA53: 500 | BB53: 10
A54: 1740 | B54: Discontinuado | C54: GN | D54: ART. 3110 OPS | E54: 720 | F54: 0.0132 | G54: 0.0088 | H54: =(F54-G54)/F54 -> 0.33333333 | I54: OPS | J54: UNICLEAR CRISTAL OPS 540 x 350 | K54: CAJA Nº 4/1 | L54: BOLSAS DE 120 X 125 | O54: 3 | Q54: =IFERROR(IF(AO54>1,AO54,60*60*8*O54/P54/E54),"") | R54: =IFERROR(60*60*8*O54/E54/Q54,"") | S54: =IFERROR(R54/8,"") | T54: =IFERROR(IF(R54>2,S54,""),"")
A55: 1826 | B55: Venta Normal | C55: GN | D55: ART. 3110 PAI NEGRO | E55: 720 | F55: 0.0109 | G55: 0.0075 | H55: =(F55-G55)/F55 -> 0.31192661 | I55: HIPST | J55: PAI NEGRO 520 x 300 | K55: CAJA Nº 4/1 | L55: BOLSAS DE 120 X 125 | O55: 3 | P55: 25 | Q55: =IFERROR(IF(AO55>1,AO55,60*60*8*O55/P55/E55),"") -> 4 | R55: =IFERROR(60*60*8*O55/E55/Q55,"") -> 30 | S55: =IFERROR(R55/8,"") -> 3.75 | T55: =IFERROR(IF(R55>2,S55,""),"") -> 3.75 | Z55: Christian | AD55: 45420 | AE55: 13 | AF55: 1 | AG55: 0.1 | AH55: 1 | AI55: 0.15 | AJ55: 0.45 | AK55: 0.28 | AL55: 0.12 | AM55: 0.41 | AN55: 0.1 | AO55: 4 | AP55: 44 | AQ55: 120 | AR55: 120 | AS55: 122 | AT55: 55 | AU55: 20 | AV55: 40 | AW55: 20 | AX55: 65 | AY55: 178 | AZ55: Normal | BA55: 500 | BB55: 10
A56: 1828 | B56: Venta Normal | C56: GN | D56: ART. 3142 | E56: 720 | F56: 0.0138 | G56: 0.0109 | H56: =(F56-G56)/F56 -> 0.21014493 | I56: PVC | J56: PVC CRISTAL 520 x 300 | K56: CAJA Nº 8 | L56: BOLSAS DE 120 X 125 | O56: 3 | P56: 27 | Q56: =IFERROR(IF(AO56>1,AO56,60*60*8*O56/P56/E56),"") -> 4 | R56: =IFERROR(60*60*8*O56/E56/Q56,"") -> 30 | S56: =IFERROR(R56/8,"") -> 3.75 | T56: =IFERROR(IF(R56>2,S56,""),"") -> 3.75 | Z56: Christian | AD56: 45418 | AE56: 13 | AF56: 1 | AG56: 0.1 | AH56: 1 | AI56: 0.1 | AJ56: 0.46 | AK56: 0.28 | AL56: 0.12 | AM56: 0.4 | AN56: 0.1 | AO56: 4 | AP56: 49 | AQ56: 104 | AR56: 106 | AS56: 106 | AT56: 42 | AU56: 20 | AV56: 40 | AW56: 20 | AX56: 65 | AY56: 181 | AZ56: Normal | BA56: 500 | BB56: 10
A57: 2030 | B57: Venta Normal | C57: GN | D57: ART. 3142 ( X180 ) | E57: 180 | F57: 0.0138 | G57: 0.0109 | H57: =(F57-G57)/F57 -> 0.21014493 | I57: PVC | J57: PVC CRISTAL 520 x 300 | K57: CAJA Nº 14 | L57: BOLSAS DE 120 X 80 | O57: 3 | P57: 27 | Q57: =IFERROR(IF(AO57>1,AO57,60*60*8*O57/P57/E57),"") -> 4 | R57: =IFERROR(60*60*8*O57/E57/Q57,"") -> 120 | S57: =IFERROR(R57/8,"") -> 15 | T57: =IFERROR(IF(R57>2,S57,""),"") -> 15 | Z57: Christian | AD57: 45418 | AE57: 13 | AF57: 1 | AG57: 0.1 | AH57: 1 | AI57: 0.1 | AJ57: 0.46 | AK57: 0.28 | AL57: 0.12 | AM57: 0.4 | AN57: 0.1 | AO57: 4 | AP57: 49 | AQ57: 104 | AR57: 106 | AS57: 106 | AT57: 42 | AU57: 20 | AV57: 40 | AW57: 20 | AX57: 65 | AY57: 181 | AZ57: Normal | BA57: 500 | BB57: 10
A58: 1787 | B58: Discontinuado | C58: GN | D58: ART. 3142 OPS | E58: 720 | F58: 0.015 | G58: 0.0102 | H58: =(F58-G58)/F58 -> 0.32 | I58: OPS | J58: UNICLEAR CRISTAL OPS 540 x 400 | K58: CAJA Nº 8 | L58: BOLSAS DE 120 X 125 | O58: 3 | Q58: =IFERROR(IF(AO58>1,AO58,60*60*8*O58/P58/E58),"") | R58: =IFERROR(60*60*8*O58/E58/Q58,"") | S58: =IFERROR(R58/8,"") | T58: =IFERROR(IF(R58>2,S58,""),"")
A59: 1829 | B59: Venta Normal | C59: GN | D59: ART. 3185 | E59: 720 | F59: 0.0207 | G59: 0.015 | H59: =(F59-G59)/F59 -> 0.27536232 | I59: PVC | J59: PVC CRISTAL 520 x 450 | K59: CAJA Nº 8 | L59: BOLSAS DE 120 X 125 | O59: 3 | P59: 21 | Q59: =IFERROR(IF(AO59>1,AO59,60*60*8*O59/P59/E59),"") -> 4.6 | R59: =IFERROR(60*60*8*O59/E59/Q59,"") -> 26.086957 | S59: =IFERROR(R59/8,"") -> 3.2608696 | T59: =IFERROR(IF(R59>2,S59,""),"") -> 3.2608696 | Z59: Christian | AD59: 45414 | AE59: 13 | AF59: 1 | AG59: 0.2 | AH59: 1 | AI59: 0.2 | AJ59: 0.6 | AK59: 0.28 | AL59: 0.12 | AM59: 0.6 | AN59: 0.2 | AO59: 4.6 | AP59: 48 | AQ59: 106 | AR59: 106 | AS59: 105 | AT59: 42 | AU59: 20 | AV59: 40 | AW59: 20 | AX59: 65 | AY59: 180 | AZ59: Normal | BA59: 400 | BB59: 10
A60: 2031 | B60: Venta Normal | C60: GN | D60: ART. 3185 (X 150) | E60: 150 | F60: 0.0207 | G60: 0.015 | H60: =(F60-G60)/F60 -> 0.27536232 | I60: PVC | J60: PVC CRISTAL 520 x 450 | K60: CAJA Nº 14 | L60: BOLSAS DE 120 X 80 | O60: 3 | P60: 101 | Q60: =IFERROR(IF(AO60>1,AO60,60*60*8*O60/P60/E60),"") -> 4.6 | R60: =IFERROR(60*60*8*O60/E60/Q60,"") -> 125.21739 | S60: =IFERROR(R60/8,"") -> 15.652174 | T60: =IFERROR(IF(R60>2,S60,""),"") -> 15.652174 | Z60: Christian | AD60: 45414 | AE60: 13 | AF60: 1 | AG60: 0.2 | AH60: 1 | AI60: 0.2 | AJ60: 0.6 | AK60: 0.28 | AL60: 0.12 | AM60: 0.6 | AN60: 0.2 | AO60: 4.6 | AP60: 48 | AQ60: 106 | AR60: 106 | AS60: 105 | AT60: 42 | AU60: 20 | AV60: 40 | AW60: 20 | AX60: 65 | AY60: 180 | AZ60: Normal | BA60: 400 | BB60: 10
A61: 2034 | B61: Venta Normal | C61: GN | D61: ART. 3185 / 3110 NEGRO | E61: 150 | F61: 0.0316 | G61: 0.0225 | H61: =(F61-G61)/F61 -> 0.28797468 | I61: PAI-PVC | J61: COMBO | P61: * | Q61: =IFERROR(IF(AO61>1,AO61,60*60*8*O61/P61/E61),"") | R61: =IFERROR(60*60*8*O61/E61/Q61,"") | S61: =IFERROR(R61/8,"") | T61: =IFERROR(IF(R61>2,S61,""),"")
A62: 1739 | B62: Venta Normal | C62: GN | D62: ART. 3185 OPS | E62: 720 | F62: 0.0188 | G62: 0.0125 | H62: =(F62-G62)/F62 -> 0.33510638 | I62: PVC | J62: UNICLEAR CRISTAL OPS 540 x 500 | K62: CAJA Nº 13 | L62: BOLSAS DE 120 X 125 | O62: 3 | P62: 21 | Q62: =IFERROR(IF(AO62>1,AO62,60*60*8*O62/P62/E62),"") -> 5.7142857 | R62: =IFERROR(60*60*8*O62/E62/Q62,"") -> 21 | S62: =IFERROR(R62/8,"") -> 2.625 | T62: =IFERROR(IF(R62>2,S62,""),"") -> 2.625
A63: 1824 | B63: Venta Normal | C63: GN | D63: ART. 3208 | E63: 200 | F63: 0.0378 | G63: 0.0324 | H63: =(F63-G63)/F63 -> 0.14285714 | I63: PVC | J63: PVC CRISTAL 500 x 300 | K63: CAJA Nº 2 | L63: BOLSAS DE 120 X 80 | O63: 2 | P63: 50 | Q63: =IFERROR(IF(AO63>1,AO63,60*60*8*O63/P63/E63),"") -> 5.76 | R63: =IFERROR(60*60*8*O63/E63/Q63,"") -> 50 | S63: =IFERROR(R63/8,"") -> 6.25 | T63: =IFERROR(IF(R63>2,S63,""),"") -> 6.25
A64: 92 | B64: Discontinuado | C64: GN | D64: ART. 6 BASE | E64: 540 | F64: 0.0124 | G64: 0.0079 | H64: =(F64-G64)/F64 -> 0.36290323 | I64: OPS | J64: UNICLEAR CRISTAL OPS 580 x 300 | K64: CAJA Nº 4/1 | L64: BOLSAS DE 120 X 125 | O64: 6 | Q64: =IFERROR(IF(AO64>1,AO64,60*60*8*O64/P64/E64),"") | R64: =IFERROR(60*60*8*O64/E64/Q64,"") | S64: =IFERROR(R64/8,"") | T64: =IFERROR(IF(R64>2,S64,""),"")
A65: 93 | B65: Discontinuado | C65: GN | D65: ART. 6 TAPA | E65: 540 | F65: 0.0104 | G65: 0.0066 | H65: =(F65-G65)/F65 -> 0.36538462 | I65: OPS | J65: UNICLEAR CRISTAL OPS 580 x 250 | K65: CAJA Nº 4/1 | L65: BOLSAS DE 120 X 125 | O65: 6 | Q65: =IFERROR(IF(AO65>1,AO65,60*60*8*O65/P65/E65),"") | R65: =IFERROR(60*60*8*O65/E65/Q65,"") | S65: =IFERROR(R65/8,"") | T65: =IFERROR(IF(R65>2,S65,""),"")
A66: 98 | B66: Venta Normal | C66: GN | D66: ART. B 16 NEGRO | E66: 60 | F66: 0.0577 | G66: 0.046 | H66: =(F66-G66)/F66 -> 0.20277296 | I66: HIPST | J66: PAI NEGRO 320 x 400 | K66: CAJA Nº 4/1 | L66: BOLSAS DE 120 X 125 | O66: 1 | P66: 90 | Q66: 5.4 | R66: =IFERROR(60*60*8*O66/E66/Q66,"") -> 88.888889 | S66: =IFERROR(R66/8,"") -> 11.111111 | T66: =IFERROR(IF(R66>2,S66,""),"") -> 11.111111
A67: 99 | B67: Venta Normal | C67: GN | D67: ART. B 16 NEGRO X 160 | E67: 160 | F67: 0.0577 | G67: 0.046 | H67: =(F67-G67)/F67 -> 0.20277296 | I67: HIPST | J67: PAI NEGRO 320 x 400 | K67: CAJA Nº 4 | L67: BOLSAS DE 120 X 125 | O67: 1 | P67: 37 | Q67: =IFERROR(IF(AO67>1,AO67,60*60*8*O67/P67/E67),"") -> 5.4 | R67: =IFERROR(60*60*8*O67/E67/Q67,"") -> 33.333333 | S67: =IFERROR(R67/8,"") -> 4.1666667 | T67: =IFERROR(IF(R67>2,S67,""),"") -> 4.1666667 | AD67: 45495 | AE67: 13 | AF67: 1.5 | AG67: 0.5 | AH67: 1.5 | AI67: 0.5 | AJ67: 0.8 | AK67: 0.11 | AL67: 0.18 | AM67: 0.4 | AN67: 0.5 | AO67: 5.4 | AP67: 56 | AQ67: 119 | AR67: 128 | AS67: 128 | AT67: 65 | AU67: 20 | AV67: 40 | AW67: 20 | AX67: 65 | AY67: 387 | AZ67: Normal | BA67: 600 | BB67: 10
A68: 51 | B68: Discontinuado | C68: GN | D68: ART. B 21 M | E68: 160 | F68: 0.0528 | G68: 0.0437 | H68: =(F68-G68)/F68 -> 0.17234848 | I68: HIPST | J68: PAI NEGRO 320 x 400 | K68: CAJA Nº 4 | L68: BOLSAS DE 120 X 125 | O68: 1 | P68: 58 | Q68: =IFERROR(IF(AO68>1,AO68,60*60*8*O68/P68/E68),"") -> 3.1034483 | R68: =IFERROR(60*60*8*O68/E68/Q68,"") -> 58 | S68: =IFERROR(R68/8,"") -> 7.25 | T68: =IFERROR(IF(R68>2,S68,""),"") -> 7.25
A69: 628 | B69: Venta Normal | C69: GN | D69: ART. B-23 M | E69: 200 | F69: 0.0372 | G69: 0.026598 | H69: =(F69-G69)/F69 -> 0.285 | I69: HIPST | J69: PAI NEGRO 520 x 400 | K69: CAJA Nº 17 | L69: BOLSAS DE 120 X 110 | O69: 2 | P69: 40 | Q69: =IFERROR(IF(AO69>1,AO69,60*60*8*O69/P69/E69),"") -> 7.2 | R69: =IFERROR(60*60*8*O69/E69/Q69,"") -> 40 | S69: =IFERROR(R69/8,"") -> 5 | T69: =IFERROR(IF(R69>2,S69,""),"") -> 5
A70: 100 | B70: Venta Normal | C70: GN | D70: ART. BR 20 NEGRO | E70: 200 | F70: 0.0289 | G70: 0.0166 | H70: =(F70-G70)/F70 -> 0.42560554 | I70: HIPST | J70: PAI NEGRO 530 x 350 | K70: CAJA Nº 8 | L70: BOLSAS DE 120 X 125 | O70: 4 | P70: 60 | Q70: =IFERROR(IF(AO70>1,AO70,60*60*8*O70/P70/E70),"") -> 9.6 | R70: =IFERROR(60*60*8*O70/E70/Q70,"") -> 60 | S70: =IFERROR(R70/8,"") -> 7.5 | T70: =IFERROR(IF(R70>2,S70,""),"") -> 7.5
A71: 103 | B71: Venta Normal | C71: GN | D71: ART. BR 24 NEGRO | E71: 200 | F71: 0.0396 | G71: 0.0276 | H71: =(F71-G71)/F71 -> 0.3030303 | I71: HIPST | J71: PAI NEGRO 600 x 400 | K71: CAJA Nº 7 | L71: BOLSAS DE 120 X 125 | M71: 2 | N71: 100 | O71: 2 | P71: 40-60 | Q71: =IFERROR(IF(AO71>1,AO71,60*60*8*O71/P71/E71),"") -> 7,1 - 4,4 | R71: 41 / 65 | S71: =IFERROR(R71/8,"") | T71: 5,1 / 8,2 | U71: 65 | AD71: 24/7/2024 - 22/8/2024 | AE71: 17 - 14 | AF71: 1,9 - 1,3 | AG71: 0,15 - 0,25 | AH71: 1,8 - 1 | AI71: 0,15 - 0,25 | AJ71: 1,2 - 0,15 | AK71: 0,28 - 0,15 | AL71: 0,3 - 0,3 | AM71: 0,43 - 0,4 | AN71: 0,5 - 0,5 | AO71: 7,1 - 4,4 | AP71: 41 - 36 | AQ71: 129 - 138 | AR71: 131 - 136 | AS71: 135 -139 | AT71: 50 - 80 | AU71: ? - 20 | AV71: ? - 40 | AW71: ? - 20 | AX71: 200 - 70 | AY71: 309 - 274 | AZ71: Normal | BA71: ? - 1100 | BB71: ? - 10 | BC71: 134 | BD71: 133
A72: 106 | B72: Venta Normal | C72: GN | D72: ART. BR 26 NEGRO | E72: 200 | F72: 0.0479 | G72: 0.032 | H72: =(F72-G72)/F72 -> 0.33194154 | I72: HIPST | J72: PAI NEGRO 340 x 400 | K72: CAJA Nº 9 | L72: BOLSAS DE 120 X 125 | O72: 1 | P72: 40 | Q72: =IFERROR(IF(AO72>1,AO72,60*60*8*O72/P72/E72),"") -> 5.8 | R72: =IFERROR(60*60*8*O72/E72/Q72,"") -> 24.827586 | S72: =IFERROR(R72/8,"") -> 3.1034483 | T72: =IFERROR(IF(R72>2,S72,""),"") -> 3.1034483 | AD72: 45371 | AE72: 12 | AF72: 1.3 | AG72: 0.4 | AH72: 1.3 | AI72: 0.4 | AJ72: 1 | AK72: 0.12 | AL72: 0.22 | AM72: 0.55 | AN72: 0.2 | AO72: 5.8 | AP72: 51 | AQ72: 138 | AR72: 135 | AS72: 135 | AT72: 60 | AU72: 33 | AV72: 40 | AW72: 40 | AX72: 100 | AY72: 310 | AZ72: Normal | BA72: 1600 | BB72: 10
A73: 108 | B73: Venta Normal | C73: GN | D73: ART. BR 29 NEGRO | E73: 100 | F73: 0.0594 | G73: 0.0444 | H73: =(F73-G73)/F73 -> 0.25252525 | I73: HIPST | J73: PAI NEGRO 365 x 400 | K73: CAJA Nº 5 | L73: BOLSAS DE 120 X 125 | M73: 2 | N73: 50 | O73: 1 | P73: 50 | Q73: =IFERROR(IF(AO73>1,AO73,60*60*8*O73/P73/E73),"") -> 4.6 | R73: =IFERROR(60*60*8*O73/E73/Q73,"") -> 62.608696 | S73: =IFERROR(R73/8,"") -> 7.826087 | T73: =IFERROR(IF(R73>2,S73,""),"") -> 7.826087 | AD73: 45391 | AE73: 12 | AF73: 1.1 | AG73: 0.5 | AH73: 1.1 | AI73: 0.3 | AJ73: 0.6 | AK73: 0.11 | AL73: 0.17 | AM73: 0.2 | AN73: 0.12 | AO73: 4.6 | AP73: 45 | AQ73: 132 | AR73: 136 | AS73: 135 | AT73: 60 | AU73: 38 | AV73: 40 | AW73: 40 | AX73: 101 | AY73: 352 | AZ73: Normal | BA73: 3000 | BB73: 10
A74: 109 | B74: Discontinuado | C74: GN | D74: ART. BR 29 NEGRO X 160 | E74: 160 | F74: 0.0594 | G74: 0.0444 | H74: =(F74-G74)/F74 -> 0.25252525 | I74: HIPST | J74: PAI NEGRO 365 x 400 | K74: CAJA Nº 9 | L74: BOLSAS DE 120 X 125 | O74: 1 | P74: 32 | Q74: =IFERROR(IF(AO74>1,AO74,60*60*8*O74/P74/E74),"") -> 5.625 | R74: =IFERROR(60*60*8*O74/E74/Q74,"") -> 32 | S74: =IFERROR(R74/8,"") -> 4 | T74: =IFERROR(IF(R74>2,S74,""),"") -> 4
A75: 126 | B75: Venta Normal | C75: GN | D75: ART. BT 16 | E75: 60 | G75: 0.1065 | I75: HIPST-PET | J75: PAI/PET 100x10000 | O75: 1 | P75: 20 | Q75: =IFERROR(IF(AO75>1,AO75,60*60*8*O75/P75/E75),"") -> 24 | R75: =IFERROR(60*60*8*O75/E75/Q75,"") -> 20 | S75: =IFERROR(R75/8,"") -> 2.5 | T75: =IFERROR(IF(R75>2,S75,""),"") -> 2.5
A76: 1956 | B76: Venta Normal | C76: GN | D76: ART. OP 1445 | E76: 400 | F76: 0.0074 | G76: 0.0056 | H76: =(F76-G76)/F76 -> 0.24324324 | I76: OPS | J76: UNICLEAR CRISTAL OPS 480 x 350 | K76: CAJA Nº 2 | L76: BOLSAS DE 120 X 80 | O76: 12 | Q76: =IFERROR(IF(AO76>1,AO76,60*60*8*O76/P76/E76),"") | R76: =IFERROR(60*60*8*O76/E76/Q76,"") | S76: =IFERROR(R76/8,"") | T76: =IFERROR(IF(R76>2,S76,""),"")
A77: 1957 | B77: Venta Normal | C77: GN | D77: ART. OP 1510 | E77: 400 | F77: 0.0086 | G77: 0.006 | H77: =(F77-G77)/F77 -> 0.30232558 | I77: OPS | J77: UNICLEAR CRISTAL OPS 460 x 300 | K77: CAJA Nº 2 | L77: BOLSAS DE 120 X 80 | O77: 9 | Q77: =IFERROR(IF(AO77>1,AO77,60*60*8*O77/P77/E77),"") | R77: =IFERROR(60*60*8*O77/E77/Q77,"") | S77: =IFERROR(R77/8,"") | T77: =IFERROR(IF(R77>2,S77,""),"")
A78: 1958 | B78: Venta Normal | C78: GN | D78: ART. OP 1550 | E78: 400 | F78: 0.0115 | G78: 0.008 | H78: =(F78-G78)/F78 -> 0.30434783 | I78: OPS | J78: UNICLEAR CRISTAL OPS 460 x 400 | K78: CAJA Nº 2 | L78: BOLSAS DE 120 X 80 | O78: 9 | Q78: =IFERROR(IF(AO78>1,AO78,60*60*8*O78/P78/E78),"") | R78: =IFERROR(60*60*8*O78/E78/Q78,"") | S78: =IFERROR(R78/8,"") | T78: =IFERROR(IF(R78>2,S78,""),"")
A79: 31 | B79: Discontinuado | C79: GN | D79: ART. OP 1560 | E79: 500 | F79: 0.0242 | G79: 0.02 | H79: =(F79-G79)/F79 -> 0.17355372 | I79: OPS | J79: UNICLEAR CRISTAL OPS 570 x 300 | K79: CAJA Nº 4/1 | L79: BOLSAS DE 120 X 125 | O79: 3 | Q79: =IFERROR(IF(AO79>1,AO79,60*60*8*O79/P79/E79),"") | R79: =IFERROR(60*60*8*O79/E79/Q79,"") | S79: =IFERROR(R79/8,"") | T79: =IFERROR(IF(R79>2,S79,""),"")
A80: 1965 | B80: Venta Normal | C80: GN | D80: ART. OP 1560 | E80: 300 | F80: 0.0245 | G80: 0.02 | H80: =(F80-G80)/F80 -> 0.18367347 | I80: OPS | J80: UNICLEAR CRISTAL OPS 570 x 300 | K80: CAJA Nº 2 | L80: BOLSAS DE 120 X 80 | O80: 3 | P80: 50 | Q80: =IFERROR(IF(AO80>1,AO80,60*60*8*O80/P80/E80),"") -> 5.76 | R80: =IFERROR(60*60*8*O80/E80/Q80,"") -> 50 | S80: =IFERROR(R80/8,"") -> 6.25 | T80: =IFERROR(IF(R80>2,S80,""),"") -> 6.25
A81: 1960 | B81: Venta Normal | C81: GN | D81: ART. OP 1810 | E81: 300 | F81: 0.0132 | G81: 0.0094 | H81: =(F81-G81)/F81 -> 0.28787879 | I81: OPS | J81: UNICLEAR CRISTAL OPS 380 x 300 | K81: CAJA Nº 2 | L81: BOLSAS DE 120 X 80 | O81: 4 | Q81: =IFERROR(IF(AO81>1,AO81,60*60*8*O81/P81/E81),"") | R81: =IFERROR(60*60*8*O81/E81/Q81,"") | S81: =IFERROR(R81/8,"") | T81: =IFERROR(IF(R81>2,S81,""),"")
A82: 1961 | B82: Venta Normal | C82: GN | D82: ART. OP 1845 | E82: 300 | F82: 0.0176 | G82: 0.0128 | H82: =(F82-G82)/F82 -> 0.27272727 | I82: OPS | J82: UNICLEAR CRISTAL OPS 380 x 400 | K82: CAJA Nº 15 | L82: BOLSAS DE 120 X 110 | O82: 4 | Q82: =IFERROR(IF(AO82>1,AO82,60*60*8*O82/P82/E82),"") | R82: =IFERROR(60*60*8*O82/E82/Q82,"") | S82: =IFERROR(R82/8,"") | T82: =IFERROR(IF(R82>2,S82,""),"")
A83: 1962 | B83: Venta Normal | C83: GN | D83: ART. OP 1860 | E83: 300 | F83: 0.0198 | G83: 0.0155 | H83: =(F83-G83)/F83 -> 0.21717172 | I83: OPS | J83: UNICLEAR CRISTAL OPS 380 x 450 | K83: CAJA Nº 15 | L83: BOLSAS DE 120 X 110 | O83: 4 | Q83: =IFERROR(IF(AO83>1,AO83,60*60*8*O83/P83/E83),"") | R83: =IFERROR(60*60*8*O83/E83/Q83,"") | S83: =IFERROR(R83/8,"") | T83: =IFERROR(IF(R83>2,S83,""),"")
A84: 32 | B84: Discontinuado | C84: GN | D84: ART. OP 2050 | E84: 520 | F84: 0.0196 | G84: 0.0159 | H84: =(F84-G84)/F84 -> 0.18877551 | I84: OPS | J84: UNICLEAR CRISTAL OPS 460 x 250 | K84: CAJA Nº 4/1 | L84: BOLSAS DE 120 X 125 | O84: 2 | Q84: =IFERROR(IF(AO84>1,AO84,60*60*8*O84/P84/E84),"") | R84: =IFERROR(60*60*8*O84/E84/Q84,"") | S84: =IFERROR(R84/8,"") | T84: =IFERROR(IF(R84>2,S84,""),"")
A85: 1966 | B85: Venta Normal | C85: GN | D85: ART. OP 2050 | E85: 300 | F85: 0.0196 | G85: 0.0159 | H85: =(F85-G85)/F85 -> 0.18877551 | I85: OPS | J85: UNICLEAR CRISTAL OPS 460 x 250 | K85: CAJA Nº 1/2 | L85: BOLSAS DE 120 X 80 | O85: 2 | P85: 50 | Q85: =IFERROR(IF(AO85>1,AO85,60*60*8*O85/P85/E85),"") -> 3.84 | R85: =IFERROR(60*60*8*O85/E85/Q85,"") -> 50 | S85: =IFERROR(R85/8,"") -> 6.25 | T85: =IFERROR(IF(R85>2,S85,""),"") -> 6.25
A86: 34 | B86: Discontinuado | C86: GN | D86: ART. OP 2060 | E86: 520 | F86: 0.0196 | G86: 0.0159 | H86: =(F86-G86)/F86 -> 0.18877551 | I86: OPS | J86: UNICLEAR CRISTAL OPS 460 x 250 | K86: CAJA Nº 4/1 | L86: BOLSAS DE 120 X 125 | O86: 2 | Q86: =IFERROR(IF(AO86>1,AO86,60*60*8*O86/P86/E86),"") | R86: =IFERROR(60*60*8*O86/E86/Q86,"") | S86: =IFERROR(R86/8,"") | T86: =IFERROR(IF(R86>2,S86,""),"")
A87: 1967 | B87: Venta Normal | C87: GN | D87: ART. OP 2060 | E87: 300 | F87: 0.0196 | G87: 0.0159 | H87: =(F87-G87)/F87 -> 0.18877551 | I87: OPS | J87: UNICLEAR CRISTAL OPS 460 x 250 | K87: CAJA Nº 1/2 | L87: BOLSAS DE 120 X 80 | O87: 2 | P87: 50 | Q87: =IFERROR(IF(AO87>1,AO87,60*60*8*O87/P87/E87),"") -> 3.84 | R87: =IFERROR(60*60*8*O87/E87/Q87,"") -> 50 | S87: =IFERROR(R87/8,"") -> 6.25 | T87: =IFERROR(IF(R87>2,S87,""),"") -> 6.25
A88: 36 | B88: Discontinuado | C88: GN | D88: ART. OP 2060 MPH | E88: 520 | F88: 0.0196 | G88: 0.0159 | H88: =(F88-G88)/F88 -> 0.18877551 | I88: OPS | J88: UNICLEAR CRISTAL OPS 460 x 250 | K88: CAJA Nº 4/1 | L88: BOLSAS DE 120 X 125 | O88: 2 | Q88: =IFERROR(IF(AO88>1,AO88,60*60*8*O88/P88/E88),"") | R88: =IFERROR(60*60*8*O88/E88/Q88,"") | S88: =IFERROR(R88/8,"") | T88: =IFERROR(IF(R88>2,S88,""),"")
A89: 1968 | B89: Venta Normal | C89: GN | D89: ART. OP 2060 MPH | E89: 250 | F89: 0.0196 | G89: 0.0159 | H89: =(F89-G89)/F89 -> 0.18877551 | I89: OPS | J89: UNICLEAR CRISTAL OPS 460 x 250 | K89: CAJA Nº 1/2 | L89: BOLSAS DE 120 X 80 | O89: 2 | P89: 60 | Q89: =IFERROR(IF(AO89>1,AO89,60*60*8*O89/P89/E89),"") -> 3.84 | R89: =IFERROR(60*60*8*O89/E89/Q89,"") -> 60 | S89: =IFERROR(R89/8,"") -> 7.5 | T89: =IFERROR(IF(R89>2,S89,""),"") -> 7.5
A90: 37 | B90: Discontinuado | C90: GN | D90: ART. OP 2075 | E90: 200 | F90: 0.0314 | G90: 0.0264 | H90: =(F90-G90)/F90 -> 0.15923567 | I90: OPS | J90: UNICLEAR CRISTAL OPS 480 x 250 | K90: CAJA Nº 4/1 | L90: BOLSAS DE 120 X 125 | O90: 2 | Q90: =IFERROR(IF(AO90>1,AO90,60*60*8*O90/P90/E90),"") | R90: =IFERROR(60*60*8*O90/E90/Q90,"") | S90: =IFERROR(R90/8,"") | T90: =IFERROR(IF(R90>2,S90,""),"")
A91: 40 | B91: Discontinuado | C91: GN | D91: ART. OP 2095 | E91: 200 | F91: 0.0235 | G91: 0.0189 | H91: =(F91-G91)/F91 -> 0.19574468 | I91: OPS | J91: UNICLEAR CRISTAL OPS 460 x 300 | K91: CAJA Nº 1/2 | L91: BOLSAS DE 120 X 80 | O91: 2 | Q91: =IFERROR(IF(AO91>1,AO91,60*60*8*O91/P91/E91),"") | R91: =IFERROR(60*60*8*O91/E91/Q91,"") | S91: =IFERROR(R91/8,"") | T91: =IFERROR(IF(R91>2,S91,""),"")
A92: 41 | B92: Discontinuado | C92: GN | D92: ART. OP 2440 | E92: 360 | F92: 0.027 | G92: 0.0215 | H92: =(F92-G92)/F92 -> 0.2037037 | I92: OPS | J92: UNICLEAR CRISTAL OPS 560 x 250 | K92: CAJA Nº 4/1 | L92: BOLSAS DE 120 X 125 | O92: 2 | Q92: =IFERROR(IF(AO92>1,AO92,60*60*8*O92/P92/E92),"") | R92: =IFERROR(60*60*8*O92/E92/Q92,"") | S92: =IFERROR(R92/8,"") | T92: =IFERROR(IF(R92>2,S92,""),"")
A93: 42 | B93: Discontinuado | C93: GN | D93: ART. OP 2450 | E93: 360 | F93: 0.027 | G93: 0.0215 | H93: =(F93-G93)/F93 -> 0.2037037 | I93: OPS | J93: UNICLEAR CRISTAL OPS 560 x 250 | K93: CAJA Nº 4/1 | L93: BOLSAS DE 120 X 125 | O93: 2 | Q93: =IFERROR(IF(AO93>1,AO93,60*60*8*O93/P93/E93),"") | R93: =IFERROR(60*60*8*O93/E93/Q93,"") | S93: =IFERROR(R93/8,"") | T93: =IFERROR(IF(R93>2,S93,""),"")
A94: 1969 | B94: Venta Normal | C94: GN | D94: ART. OP 2465 | E94: 300 | F94: 0.0144 | G94: 0.0114 | H94: =(F94-G94)/F94 -> 0.20833333 | I94: OPS | J94: UNICLEAR CRISTAL OPS 420 x 250 | K94: CAJA Nº 2 | L94: BOLSAS DE 120 X 80 | O94: 4 | P94: 60 | Q94: =IFERROR(IF(AO94>1,AO94,60*60*8*O94/P94/E94),"") -> 6.4 | R94: =IFERROR(60*60*8*O94/E94/Q94,"") -> 60 | S94: =IFERROR(R94/8,"") -> 7.5 | T94: =IFERROR(IF(R94>2,S94,""),"") -> 7.5
A95: 45 | B95: Discontinuado | C95: GN | D95: ART. OP 2475 | E95: 360 | F95: 0.027 | G95: 0.0215 | H95: =(F95-G95)/F95 -> 0.2037037 | I95: OPS | J95: UNICLEAR CRISTAL OPS 560 x 250 | K95: CAJA Nº 4/1 | L95: BOLSAS DE 120 X 125 | O95: 2 | Q95: =IFERROR(IF(AO95>1,AO95,60*60*8*O95/P95/E95),"") | R95: =IFERROR(60*60*8*O95/E95/Q95,"") | S95: =IFERROR(R95/8,"") | T95: =IFERROR(IF(R95>2,S95,""),"")
A96: 48 | B96: Discontinuado | C96: GN | D96: ART. OP 2508 | E96: 200 | F96: 0.0397 | G96: 0.0328 | H96: =(F96-G96)/F96 -> 0.17380353 | I96: OPS | J96: UNICLEAR CRISTAL OPS 560 x 300 | K96: CAJA Nº 3 | L96: BOLSAS DE 120 X 80 | O96: 2 | Q96: =IFERROR(IF(AO96>1,AO96,60*60*8*O96/P96/E96),"") | R96: =IFERROR(60*60*8*O96/E96/Q96,"") | S96: =IFERROR(R96/8,"") | T96: =IFERROR(IF(R96>2,S96,""),"")
A97: 50 | B97: Discontinuado | C97: GN | D97: ART. OP 2510 | E97: 200 | F97: 0.0397 | G97: 0.0328 | H97: =(F97-G97)/F97 -> 0.17380353 | I97: OPS | J97: UNICLEAR CRISTAL OPS 560 x 300 | K97: CAJA Nº 3 | L97: BOLSAS DE 120 X 80 | O97: 2 | Q97: =IFERROR(IF(AO97>1,AO97,60*60*8*O97/P97/E97),"") | R97: =IFERROR(60*60*8*O97/E97/Q97,"") | S97: =IFERROR(R97/8,"") | T97: =IFERROR(IF(R97>2,S97,""),"")
A98: 53 | B98: Discontinuado | C98: GN | D98: ART. OP 3208 | E98: 400 | F98: 0.0297 | G98: 0.0253 | H98: =(F98-G98)/F98 -> 0.14814815 | I98: OPS | J98: UNICLEAR CRISTAL OPS 500 x 300 | K98: CAJA Nº 4 | L98: BOLSAS DE 120 X 125 | O98: 2 | Q98: =IFERROR(IF(AO98>1,AO98,60*60*8*O98/P98/E98),"") | R98: =IFERROR(60*60*8*O98/E98/Q98,"") | S98: =IFERROR(R98/8,"") | T98: =IFERROR(IF(R98>2,S98,""),"")
A99: 1970 | B99: Venta Normal | C99: GN | D99: ART. OP 3208 | E99: 200 | F99: 0.0297 | G99: 0.0253 | H99: =(F99-G99)/F99 -> 0.14814815 | I99: OPS | J99: UNICLEAR CRISTAL OPS 500 x 300 | K99: CAJA Nº 2 | L99: BOLSAS DE 120 X 80 | O99: 2 | P99: 60 | Q99: =IFERROR(IF(AO99>1,AO99,60*60*8*O99/P99/E99),"") -> 4.8 | R99: =IFERROR(60*60*8*O99/E99/Q99,"") -> 60 | S99: =IFERROR(R99/8,"") -> 7.5 | T99: =IFERROR(IF(R99>2,S99,""),"") -> 7.5
A100: 115 | B100: Discontinuado | C100: GN | D100: ART. OP T 16 | E100: 60 | F100: 0.0629 | G100: 0.0526 | H100: =(F100-G100)/F100 -> 0.16375199 | I100: OPS | J100: UNICLEAR CRISTAL OPS 410 x 450 | O100: 1 | Q100: =IFERROR(IF(AO100>1,AO100,60*60*8*O100/P100/E100),"") | R100: =IFERROR(60*60*8*O100/E100/Q100,"") | S100: =IFERROR(R100/8,"") | T100: =IFERROR(IF(R100>2,S100,""),"")
...

Sheet Hoja3
A1: PRODUCT ID | B1: PRODUCT CODE | C1: Un per case | D1: Gross Weight (gr) | E1: Net Weight (gr) | F1: MATERIAL ( width (mm) thikness x (microns) ) | G1: CAV | H1: Cycle
A2: 692 | B2: POTE 1135 | C2: 500 | D2: 0.017 | E2: 0.01 | F2: PET CRISTAL 860 x 300 | G2: 24 | H2: 6
A3: 1924 | B3: POTE 1140 | C3: 500 | D3: 0.0193 | E3: 0.0111 | F3: PET CRISTAL 860 x 340 | G3: 24 | H3: 6
A4: 693 | B4: POTE 1145 | C4: 500 | D4: 0.0187 | E4: 0.0113 | F4: PET CRISTAL 860 x 330 | G4: 24 | H4: 6
A5: 1925 | B5: POTE 1150 | C5: 500 | D5: 0.0221 | E5: 0.013 | F5: PET CRISTAL 860 x 390 | G5: 24 | H5: 6
A6: 694 | B6: POTE 1165 | C6: 500 | D6: 0.0238 | E6: 0.0139 | F6: PET CRISTAL 860 x 420 | G6: 24 | H6: 6
A7: 1926 | B7: POTE 1170 | C7: 500 | D7: 0.0266 | E7: 0.0147 | F7: PET CRISTAL 860 x 470 | G7: 24 | H7: 6
A9: 1759 | B9: Z F 110 | C9: 720 | D9: 0.0167 | E9: 0.012 | F9: PET CRISTAL 820 x 350 | G9: 24 | H9: 6.6
A10: 1009 | B10: Z F 110 PERFORADA | C10: 720 | D10: 0.0184 | E10: 0.012 | F10: PET CRISTAL 820 x 350 | G10: 24 | H10: 6.6
A11: 1010 | B11: Z F 125 | C11: 720 | D11: 0.0167 | E11: 0.012 | F11: PET CRISTAL 820 x 350 | G11: 24 | H11: 6.6
A12: 1011 | B12: Z F 125 PERFORADA | C12: 720 | D12: 0.0184 | E12: 0.012 | F12: PET CRISTAL 820 x 350 | G12: 24 | H12: 6.6
A13: 1012 | B13: Z F 160 | C13: 720 | D13: 0.0167 | E13: 0.012 | F13: PET CRISTAL 820 x 350 | G13: 24 | H13: 6.6
A14: 1013 | B14: Z F 160 PERFORADA | C14: 720 | D14: 0.0184 | E14: 0.012 | F14: PET CRISTAL 820 x 350 | G14: 24 | H14: 6.6
... A22: 1844 | B22: ZDS TAPA | C22: 500 | D22: 0.0119 | E22: 0.007 | F22: PET CRISTAL 1020 x 400 | G22: 42 | H22: 16.6

Sheet Hoja4

Sheet Hoja2
A1: COD. | B1: ARTICULO | C1: UN por CAJA | D1: PESO BR. | E1: PESO NET. | F1: % SCRAP | G1: MATERIAL | H1: MATERIAL DETALLE | I1: CAJAS | J1: BOLSA | K1: CAV | L1: CAJAS POR TURNO | N1: Peso Promedio Real
A2: 692 | B2: POTE 1135 | C2: 500 | D2: 0.017 | E2: 0.01 | F2: 0.41176471 | G2: PET | H2: PET CRISTAL 860 x 300 | I2: CAJA Nº 11 | J2: BOLSAS DE 120 X 97 | K2: 24 | L2: 180
A3: 693 | B3: POTE 1145 | C3: 500 | D3: 0.0187 | E3: 0.0113 | F3: 0.39572193 | G3: PET | H3: PET CRISTAL 860 x 330 | I3: CAJA Nº 11 | J3: BOLSAS DE 120 X 97 | K3: 24 | L3: 180 | N3: 0.01112 | O3: =N3/E3-1 -> -0.015929204
A4: 694 | B4: POTE 1165 | C4: 500 | D4: 0.0238 | E4: 0.0139 | F4: 0.41596639 | G4: PET | H4: PET CRISTAL 860 x 420 | I4: CAJA Nº 11 | J4: BOLSAS DE 120 X 97 | K4: 24 | L4: 170 | N4: =13.975/1000 -> 0.013975 | O4: =N4/E4-1 -> 0.0053956835
A5: 867 | B5: POTE 1170 | C5: 800 | D5: 0.0266 | E5: 0.0147 | F5: 0.44736842 | G5: PET | H5: PET CRISTAL 860 x 470 | I5: CAJA Nº 13 | J5: BOLSAS DE 120 X 125 | K5: 24 | L5: 113
A6: 1844 | B6: ZDS TAPA | C6: 500 | D6: 0.0119 | E6: 0.007 | F6: 0.41176471 | G6: PET | H6: PET CRISTAL 1020 x 400 | I6: CAJA Nº 18 | J6: BOLSAS DE 25 X 50 | K6: 42 | L6: 110 | N6: 0.00688825 | O6: =N6/E6-1 -> -0.015964286
A7: 1845 | B7: ZDS 240 | C7: 500 | D7: 0.0145 | E7: 0.0085 | F7: 0.4137931 | G7: PET | H7: PET CRISTAL 915 x 450 | I7: CAJA Nº 21 | J7: BOLSAS DE 25 X 65 | K7: 36 | L7: 120
A8: 1846 | B8: ZDS 360 | C8: 500 | D8: 0.0177 | E8: 0.012 | F8: 0.3220339 | G8: PET | H8: PET CRISTAL 915 x 550 | I8: CAJA Nº 21 | J8: BOLSAS DE 25 X 65 | K8: 36 | L8: 117 | N8: =12.075/1000 -> 0.012075 | O8: =N8/E8-1 -> 0.00625
A9: 1847 | B9: ZDS 480 | C9: 500 | D9: 0.0193 | E9: 0.014 | F9: 0.2746114 | G9: PET | H9: PET CRISTAL 915 x 600 | I9: CAJA Nº 20 | J9: BOLSAS DE 25 X 70 | K9: 36 | L9: 116
A10: 1848 | B10: ZDS 720 | C10: 500 | D10: 0.0258 | E10: 0.021 | F10: 0.18604651 | G10: PET | H10: PET CRISTAL 915 x 800 | I10: CAJA Nº 19 | J10: BOLSAS DE 25 X 70 | K10: 36 | L10: 110
B16: Lámina de PET con Silicona en ambas caras
D17: Ancho (mm) | E17: Espesor (micrones)
A18: 867 | B18: POTE 1170 | C18: PET | D18: 860 | E18: 470 | F18: PET CRISTAL 860 x 470 | G18: 1 Rollo
D20: Ancho (mm) | E20: Espesor (micrones)
A21: 692 | B21: POTE 1135 | C21: PET | D21: 860 | E21: 300 | F21: PET CRISTAL 860 x 300 | G21: 10TN
A22: 1924 | B22: POTE 1140 | C22: PET | D22: 860 | E22: 340 | F22: PET CRISTAL 860 x 340 | G22: 10TN
A23: 693 | B23: POTE 1145 | C23: PET | D23: 860 | E23: 330 | F23: PET CRISTAL 860 x 330 | G23: 5TN
B24: Ajustar en proporción

Sheet BASE SEMI

Sheet GN Análisis
A1: COD. | B1: Estado | C1: Maquina | D1: ARTICULO | E1: UN por CAJA | F1: PESO BR. | G1: PESO NET. | H1: % SCRAP | I1: MATERIAL | J1: MATERIAL DETALLE | K1: CAJAS | L1: BOLSA | M1: CAV | N1: META | P1: Registrado por | Q1: FECHA | R1: MAQ | S1: Calentamiento | T1: Ventilador de calor | U1: Fomación | V1: Ventilador de forma | W1: intervalo de corte | X1: Retraso de expulsión | Y1: Expulsión | Z1: Transporte | AA1: Retraso de cierre | AB1: Promedio de ciclo | AC1: Molde | AD1: Zona1 | AE1: Zona2 | AF1: Zona3 | AG1: Precalentador | AH1: Presión de calentamiento | AI1: Presión de formación | AJ1: Presión de expusión | AK1: Velocidad | AL1: Recorrido | AM1: Modo | AN1: Acel/ Desacel | AO1: Velocidad del paso | AP1: Zona4 | AQ1: Zona5 | AZ1: Productos por minuto | BA1: Ciclo por minuto
A2: 1826 | B2: Venta Normal | C2: GN | D2: ART. 3110 PAI NEGRO | E2: 720 | F2: 0.0109 | G2: 0.0075 | H2: =(F2-G2)/F2 -> 0.31192661 | I2: HIPST | J2: PAI NEGRO 520 x 300 | K2: CAJA Nº 4/1 | L2: BOLSAS DE 120 X 125 | M2: 3 | N2: 25 | P2: Christian | Q2: 45420 | R2: 13 | S2: 1 | T2: 0.1 | U2: 1 | V2: 0.15 | W2: 0.45 | X2: 0.28 | Y2: 0.12 | Z2: 0.41 | AA2: 0.1 | AB2: 4 | AC2: 44 | AD2: 120 | AE2: 120 | AF2: 122 | AG2: 55 | AH2: 20 | AI2: 40 | AJ2: 20 | AK2: 65 | AL2: 178 | AM2: Normal | AN2: 500 | AO2: 10 | AY2: 7 | AZ2: =60*M2/AB2 -> 45 | BA2: =60/AB2 -> 15
A3: 1075 | B3: Venta Normal | C3: GN | D3: TAPA 50 OZ PAI NEGRO | E3: 240 | F3: 0.0129 | J3: PAI NEGRO 560 x 300 | M3: 6 | N3: 40 | R3: 12 | AB3: 9.2 | AZ3: =60*M3/AB3 -> 39.130435 | BA3: =60/AB3 -> 6.5217391
A4: 1946 | B4: Venta Normal | C4: GN | D4: Z T 2200 BASE NEGRO X 100 | E4: 100 | F4: 0.0307 | G4: 0.019 | H4: =(F4-G4)/F4 -> 0.38110749 | I4: PAI | J4: PAI NEGRO 550 x 350 | K4: CAJA Nº 8 | L4: BOLSAS DE 120 X 125 | M4: 2 | N4: 110 | P4: Christian | Q4: 44621 | R4: 12 | S4: 1.4 | T4: 0.4 | U4: 1.6 | V4: 0.4 | W4: 0.5 | X4: 0.28 | Y4: 0.14 | Z4: 0.3 | AA4: 0.2 | AB4: 5.6 | AC4: 50 | AD4: 128 | AE4: 128 | AF4: 129 | AG4: 75 | AH4: 30 | AI4: 40 | AJ4: 30 | AK4: 100 | AL4: 260 | AM4: Normal | AN4: 900 | AO4: 10 | AY4: 5 | AZ4: =60*M4/AB4 -> 21.428571 | BA4: =60/AB4 -> 10.714286
A5: 106 | B5: Venta Normal | C5: GN | D5: ART. BR 26 NEGRO | E5: 200 | F5: 0.0479 | G5: 0.032 | H5: =(F5-G5)/F5 -> 0.33194154 | I5: HIPST | J5: PAI NEGRO 340 x 400 | K5: CAJA Nº 9 | L5: BOLSAS DE 120 X 125 | M5: 1 | N5: 40 | P5: Christian | Q5: 45371 | R5: 12 | S5: 1.3 | T5: 0.4 | U5: 1.3 | V5: 0.4 | W5: 1 | X5: 0.12 | Y5: 0.22 | Z5: 0.55 | AA5: 0.2 | AB5: 5.8 | AC5: 51 | AD5: 138 | AE5: 135 | AF5: 135 | AG5: 60 | AH5: 33 | AI5: 40 | AJ5: 40 | AK5: 100 | AL5: 310 | AM5: Normal | AN5: 1600 | AO5: 10 | AY5: 4 | AZ5: =60*M5/AB5 -> 10.344828 | BA5: =60/AB5 -> 10.344828
A6: 108 | B6: Venta Normal | C6: GN | D6: ART. BR 29 NEGRO | E6: 100 | F6: 0.0594 | G6: 0.0444 | H6: =(F6-G6)/F6 -> 0.25252525 | I6: HIPST | J6: PAI NEGRO 365 x 400 | K6: CAJA Nº 5 | L6: BOLSAS DE 120 X 125 | M6: 1 | N6: 50 | P6: Christian | Q6: 45391 | R6: 12 | S6: 1.1 | T6: 0.5 | U6: 1.1 | V6: 0.3 | W6: 0.6 | X6: 0.11 | Y6: 0.17 | Z6: 0.2 | AA6: 0.12 | AB6: 4.6 | AC6: 45 | AD6: 132 | AE6: 136 | AF6: 135 | AG6: 60 | AH6: 38 | AI6: 40 | AJ6: 40 | AK6: 101 | AL6: 352 | AM6: Normal | AN6: 3000 | AO6: 10 | AY6: 6 | AZ6: =60*M6/AB6 -> 13.043478 | BA6: =60/AB6 -> 13.043478
A7: 99 | B7: Venta Normal | C7: GN | D7: ART. B 16 NEGRO X 160 | E7: 160 | F7: 0.0577 | G7: 0.046 | H7: =(F7-G7)/F7 -> 0.20277296 | I7: HIPST | J7: PAI NEGRO 320 x 400 | K7: CAJA Nº 4 | L7: BOLSAS DE 120 X 125 | M7: 1 | N7: 37 | P7: Christian | Q7: 45495 | R7: 13 | S7: 1.5 | T7: 0.5 | U7: 1.5 | V7: 0.5 | W7: 0.8 | X7: 0.11 | Y7: 0.18 | Z7: 0.4 | AA7: 0.5 | AB7: 6.3 | AC7: 56 | AD7: 119 | AE7: 128 | AF7: 128 | AG7: 65 | AH7: 20 | AI7: 40 | AJ7: 20 | AK7: 65 | AL7: 387 | AM7: Normal | AN7: 600 | AO7: 10 | AY7: 3 | AZ7: =60*M7/AB7 -> 9.5238095 | BA7: =60/AB7 -> 9.5238095
A8: 103 | B8: Venta Normal | C8: GN | D8: ART. BR 24 NEGRO | E8: 200 | F8: 0.0396 | G8: 0.0276 | H8: =(F8-G8)/F8 -> 0.3030303 | I8: HIPST | J8: PAI NEGRO 600 x 400 | K8: CAJA Nº 7 | L8: BOLSAS DE 120 X 125 | M8: 2 | N8: 60 | P8: Christian | Q8: 45497 | R8: 17 | S8: 1.9 | T8: 0.15 | U8: 1.8 | V8: 0.15 | W8: 1.2 | X8: 0.28 | Y8: 0.3 | Z8: 0.43 | AA8: 0.5 | AB8: 7.1 | AC8: 41 | AD8: 129 | AE8: 131 | AF8: 135 | AG8: 50 | AH8: ? | AI8: ? | AJ8: ? | AK8: 200 | AL8: 309 | AM8: Normal | AN8: ? | AO8: ? | AY8: 2 | AZ8: =60*M8/AB8 -> 16.901408 | BA8: =60/AB8 -> 8.4507042
A10: 8 | B10: Venta Normal | C10: GN | D10: BANDEJA 4 COMPARTIMENTOS | E10: 850 | F10: 0.0095 | G10: 0.0074 | H10: =(F10-G10)/F10 -> 0.22105263 | I10: PET | J10: PET CRISTAL 550 x 200 | K10: CAJA Nº 1 | L10: BOLSAS DE 120 X 97 | M10: 6 | N10: 25 | P10: Christian | Q10: 45421 | R10: 15 | S10: 1.4 | T10: 0.3 | U10: 1.4 | V10: 0.3 | W10: 0.5 | X10: 0.18 | Y10: 0.15 | Z10: 0.4 | AA10: 0.25 | AB10: 5.3 | AC10: 48 | AD10: 102 | AE10: 102 | AF10: 102 | AG10: 40 | AH10: 20 | AI10: 40 | AJ10: 20 | AK10: 100 | AL10: 338 | AM10: Normal | AN10: 1000 | AO10: 10 | AY10: 5 | AZ10: =60*M10/AB10 -> 67.924528 | BA10: =60/AB10 -> 11.320755
A11: 1135 | B11: Venta Normal | C11: GN | D11: PORCION CHICA | E11: 500 | F11: 0.0118 | G11: 0.0075 | H11: =(F11-G11)/F11 -> 0.36440678 | I11: PET | J11: PET CRISTAL 580 x 250 | K11: CAJA Nº 3 | L11: BOLSAS DE 120 X 97 | M11: 6 | N11: 40 | P11: Christian | Q11: 45499 | R11: 14 | S11: 2.3 | T11: 0.5 | U11: 2.3 | V11: 0.5 | W11: 1 | X11: 0.16 | Y11: 0.17 | Z11: 0.4 | AA11: 0.25 | AB11: 8.1 | AC11: 54 | AD11: 97 | AE11: 97 | AF11: 97 | AG11: 40 | AH11: 20 | AI11: 40 | AJ11: 20 | AK11: 70 | AL11: 315 | AM11: Normal | AN11: 900 | AO11: 10 | AY11: 2 | AZ11: =60*M11/AB11 -> 44.444444 | BA11: =60/AB11 -> 7.4074074
A12: 1915 | B12: Venta Normal | C12: GN | D12: ART. 2050 (X 300) | E12: 300 | F12: 0.025 | G12: 0.0204 | H12: =(F12-G12)/F12 -> 0.184 | I12: PET | J12: PET CRISTAL 460 x 250 | K12: CAJA Nº 1/2 | L12: BOLSAS DE 120 X 97 | M12: 2 | N12: 45 | P12: Christian | Q12: 45411 | R12: 16 | S12: 0.9 | T12: 0.1 | U12: 1 | V12: 0.1 | W12: 0.3 | X12: 0.36 | Y12: 0.2 | Z12: 0.14 | AA12: 0.5 | AB12: 4 | AC12: 45 | AD12: 104 | AE12: 109 | AF12: 114 | AG12: 40 | AL12: 383 | AP12: 111 | AQ12: 112 | AY12: 9 | AZ12: =60*M12/AB12 -> 30 | BA12: =60/AB12 -> 15
A13: 1916 | B13: Venta Normal | C13: GN | D13: ART. 2060 (X 300) | E13: 300 | F13: 0.025 | G13: 0.0204 | H13: =(F13-G13)/F13 -> 0.184 | I13: PET | J13: PET CRISTAL 460 x 250 | K13: CAJA Nº 1/2 | L13: BOLSAS DE 120 X 97 | M13: 2 | N13: 50 | P13: Christian | Q13: 45378 | R13: 15 | S13: 0.8 | T13: 0.1 | U13: 1 | V13: 0.13 | W13: 0.25 | X13: 0.14 | Y13: 0.21 | Z13: 0.3 | AA13: 0.2 | AB13: 3.6 | AC13: 48 | AD13: 103 | AE13: 103 | AF13: 103 | AG13: 40 | AH13: 20 | AI13: 40 | AJ13: 20 | AK13: 100 | AL13: 294 | AM13: Normal | AN13: 1200 | AO13: 10 | AY13: 10 | AZ13: =60*M13/AB13 -> 33.333333 | BA13: =60/AB13 -> 16.666667
A14: 1823 | B14: Venta Normal | C14: GN | D14: ART. 2510 | E14: 200 | F14: 0.0506 | G14: 0.0423 | H14: =(F14-G14)/F14 -> 0.16403162 | I14: PET | J14: PET CRISTAL 560 x 300 | K14: CAJA Nº 3 | L14: BOLSAS DE 120 X 97 | M14: 2 | N14: 55 | P14: Christian | Q14: 45419 | R14: 12 | S14: 0.9 | T14: 0.3 | U14: 1 | V14: 0.1 | W14: 0.14 | X14: 0.19 | Y14: 0.7 | Z14: 0.6 | AA14: 0.25 | AB14: 4.6 | AC14: 50 | AD14: 110 | AE14: 110 | AF14: 108 | AG14: 40 | AH14: 30 | AI14: 40 | AJ14: 40 | AK14: 100 | AL14: 406 | AM14: Normal | AN14: 1500 | AO14: 10 | AY14: 7 | AZ14: =60*M14/AB14 -> 26.086957 | BA14: =60/AB14 -> 13.043478
A15: 1136 | B15: Venta Normal | C15: GN | D15: PORCION GRANDE | E15: 500 | F15: 0.0142 | G15: 0.0088 | H15: =(F15-G15)/F15 -> 0.38028169 | I15: PET | J15: PET CRISTAL 580 x 300 | K15: CAJA Nº 3 | L15: BOLSAS DE 120 X 97 | M15: 6 | N15: 35 | P15: Christian | Q15: 45423 | R15: 14 | S15: 2 | T15: 0.5 | U15: 2 | V15: 0.5 | W15: 1.2 | X15: 0.15 | Y15: 0.17 | Z15: 0.6 | AA15: 0.3 | AB15: 8 | AC15: 55 | AD15: 99 | AE15: 99 | AF15: 99 | AG15: 40 | AH15: 20 | AI15: 40 | AJ15: 20 | AK15: 100 | AL15: 315 | AM15: Normal | AN15: 700 | AO15: 10 | AY15: 3 | AZ15: =60*M15/AB15 -> 45 | BA15: =60/AB15 -> 7.5
A16: 1087 | B16: Venta Normal | C16: GN | D16: Z T 8 | E16: 100 | F16: 0.0799 | G16: 0.0613 | H16: =(F16-G16)/F16 -> 0.23279099 | I16: PET | J16: PET CRISTAL 560 x 300 | K16: CAJA Nº 4/1 | L16: BOLSAS DE 120 X 125 | M16: 1 | N16: 62 | P16: Christian | Q16: 45385 | R16: 14 | S16: 1.3 | T16: 0.1 | U16: 1 | V16: 0.1 | W16: 0.5 | X16: 0.13 | Y16: 0.16 | Z16: 0.3 | AA16: 0.22 | AB16: 4.3 | AC16: 49 | AD16: 114 | AE16: 111 | AF16: 100 | AG16: 48 | AH16: 20 | AI16: 40 | AJ16: 20 | AK16: 100 | AL16: 289 | AM16: Normal | AN16: 1000 | AO16: 10 | AY16: 8 | AZ16: =60*M16/AB16 -> 13.953488 | BA16: =60/AB16 -> 13.953488
A17: 906 | B17: Venta Normal | C17: GN | D17: CERICET | E17: 1080 | F17: 0.0132 | G17: 0.0104 | H17: =(F17-G17)/F17 -> 0.21212121 | I17: PET | J17: PET CRISTAL 470 x 300 | K17: CAJA Nº 6 | L17: BOLSAS DE 120 X 97 | M17: 6 | N17: 24 | P17: Christian | Q17: 45348 | R17: 15 | S17: 1.8 | T17: 0.2 | U17: 2 | V17: 0.3 | W17: 0.6 | X17: 0.16 | Y17: 0.18 | Z17: 0.7 | AA17: 0.28 | AB17: 6.5 | AC17: 41 | AD17: 100 | AE17: 100 | AF17: 100 | AG17: 45 | AH17: 20 | AI17: 40 | AJ17: 20 | AK17: 100 | AL17: 368 | AM17: Normal | AN17: 1200 | AO17: 10 | AY17: 4 | AZ17: =60*M17/AB17 -> 55.384615 | BA17: =60/AB17 -> 9.2307692
A18: 1082 | B18: Venta Normal | C18: GN | D18: Z T 7 | E18: 100 | F18: 0.0933 | G18: 0.072 | H18: =(F18-G18)/F18 -> 0.22829582 | I18: PET | J18: PET CRISTAL 560 x 350 | K18: CAJA Nº 4/1 | L18: BOLSAS DE 120 X 125 | M18: 1 | N18: 50 | P18: Christian | Q18: 45376 | R18: 14 | S18: 1.1 | T18: 0.2 | U18: 1.1 | V18: 0.2 | W18: 0.5 | X18: 0.13 | Y18: 0.18 | Z18: 0.45 | AA18: 0.35 | AB18: 4.8 | AC18: 52 | AD18: 113 | AE18: 11 | AF18: 109 | AG18: 45 | AH18: 20 | AI18: 40 | AJ18: 20 | AK18: 100 | AL18: 288 | AM18: Normal | AN18: 400 | AO18: 10 | AY18: 6 | AZ18: =60*M18/AB18 -> 12.5 | BA18: =60/AB18 -> 12.5
A19: 1033 | B19: Venta Normal | C19: GN | D19: LICORFORT | E19: 960 | F19: 0.0127 | G19: 0.0095 | H19: =(F19-G19)/F19 -> 0.2519685 | I19: PET | J19: PET CRISTAL 580 x 400 | K19: CAJA Nº 4/1 | L19: BOLSAS DE 120 X 125 | M19: 10 | N19: 25 | P19: Christian | Q19: 45360 | R19: 14 | S19: 2.5 | T19: 0.5 | U19: 2 | V19: 0.55 | W19: 0.5 | X19: 0.16 | Y19: 0.3 | Z19: 0.9 | AA19: 0.6 | AB19: 8.5 | AC19: 39 | AD19: 119 | AE19: 119 | AF19: 119 | AG19: 45 | AH19: 20 | AI19: 40 | AJ19: 20 | AK19: 100 | AL19: 340 | AM19: Normal | AN19: 700 | AO19: 10 | AY19: 1 | AZ19: =60*M19/AB19 -> 70.588235 | BA19: =60/AB19 -> 7.0588235
A21: 1914 | B21: Venta Normal | C21: GN | D21: ART. 1560 | E21: 300 | F21: 0.0262 | G21: 0.0214 | H21: =(F21-G21)/F21 -> 0.18320611 | I21: PVC | J21: PVC CRISTAL 575 x 250 | K21: CAJA Nº 2 | L21: BOLSAS DE 120 X 97 | M21: 3 | N21: 45 | P21: Christian | Q21: 20/3/2024 / 22/7/24 | R21: 13/15 | S21: 1 / 1,5 | T21: 0,1 / 0,2 | U21: 1,1 /1,3 | V21: 0,1 / 0,2 | W21: 0,8 / 1,00 | X21: 0,2 / 0,18 | Y21: 0,22 / 0,15 | Z21: 0,4 / 0,45 | AA21: 0,3 /0,2 | AB21: 4,5 / 5,6 | AC21: 59 / 62 | AD21: 104 / 103 | AE21: 104 / 103 | AF21: 104 / 103 | AG21: 45 / 38 | AH21: 20 / 20 | AI21: 40 / 40 | AJ21: 20 / 20 | AK21: 100 / 100 | AL21: 359 / 365 | AM21: Normal | AN21: 700 / 1500 | AO21: 10 / 10 | AY21: 6 | AZ21: =60*M21/AB21 -> #VALUE! | BA21: =60/AB21 -> #VALUE!
A22: 1922 | B22: Venta Normal | C22: GN | D22: ART. 2465 | E22: 300 | F22: 0.0184 | G22: 0.0158 | H22: =(F22-G22)/F22 -> 0.14130435 | I22: PVC | J22: PVC CRISTAL 420 x 250 | K22: CAJA Nº 2 | L22: BOLSAS DE 120 X 97 | M22: 4 | N22: 60 | P22: Christian | Q22: 45404 | R22: 12 | S22: 1.3 | T22: 0.3 | U22: 1.2 | V22: 0.3 | W22: 0.7 | X22: 0.15 | Y22: 0.18 | Z22: 0.4 | AA22: 0.3 | AB22: 5.2 | AC22: 49 | AD22: 106 | AE22: 106 | AF22: 106 | AG22: 40 | AH22: 38 | AI22: 40 | AJ22: 40 | AK22: 101 | AL22: 459 | AM22: Normal | AN22: 2000 | AO22: 10 | AY22: 7 | AZ22: =60*M22/AB22 -> 46.153846 | BA22: =60/AB22 -> 11.538462
A23: 1093 | B23: Venta Normal | C23: GN | D23: TAPA 25 OZ | E23: 300 | F23: 0.0109 | G23: 0.0064 | H23: =(F23-G23)/F23 -> 0.41284404 | I23: PVC | J23: PVC CRISTAL 520 x 250 | K23: CAJA SOLUPLEX 101 (25 OZ) | L23: BOLSAS DE 120 X 97 | M23: 6 | N23: 75 | P23: Christian | Q23: 45348 | R23: 12 | S23: 2 | T23: 1.1 | U23: 2.1 | V23: 1.1 | W23: 0.25 | X23: 0.15 | Y23: 0.18 | Z23: 0.35 | AA23: 0.25 | AB23: 6.8 | AC23: 41 | AD23: 97 | AE23: 98 | AF23: 98 | AG23: 44 | AH23: 38 | AI23: 40 | AJ23: 40 | AK23: 67 | AL23: 328 | AM23: Normal | AN23: 2550 | AO23: 10 | AY23: 2 | AZ23: =60*M23/AB23 -> 52.941176 | BA23: =60/AB23 -> 8.8235294 | BB23: =60*60*M23*7/E23/7 -> 72
A24: 591 | B24: Venta Normal | C24: GN | D24: LICORITA | E24: 1080 | F24: 0.0071 | G24: 0.0055 | H24: =(F24-G24)/F24 -> 0.22535211 | I24: PVC | J24: PVC CRISTAL 575 x 250 | K24: CAJA Nº 12 | L24: BOLSAS DE 120 X 97 | M24: 15 | N24: 30 | P24: Christian | Q24: 45351 | R24: 12 | S24: 1.9 | T24: 0.5 | U24: 2 | V24: 0.8 | W24: 1.3 | X24: 0.16 | Y24: 0.14 | Z24: 0.9 | AA24: 0.6 | AB24: 8.7 | AC24: 52 | AD24: 100 | AE24: 100 | AF24: 100 | AG24: 44 | AH24: 30 | AI24: 40 | AJ24: 40 | AK24: 66 | AL24: 510 | AM24: Normal | AN24: 2500 | AO24: 10 | AY24: 1 | AZ24: =60*M24/AB24 -> 103.44828 | BA24: =60/AB24 -> 6.8965517
A25: 1821 | B25: Venta Normal | C25: GN | D25: ART. 2475 | E25: 360 | F25: 0.0343 | G25: 0.0283 | H25: =(F25-G25)/F25 -> 0.17492711 | I25: PVC | J25: PVC CRISTAL 560 x 250 | K25: CAJA Nº 17 | L25: BOLSAS DE 120 X 97 | M25: 2 | N25: 41 | P25: Christian | Q25: 45376 | R25: 12 | S25: 1.1 | T25: 0.1 | U25: 1.1 | V25: 0.1 | W25: 0.45 | X25: 0.12 | Y25: 0.22 | Z25: 0.4 | AA25: 0.18 | AB25: 3.6 | AC25: 46 | AD25: 106 | AE25: 106 | AF25: 106 | AG25: 40 | AH25: 30 | AI25: 40 | AJ25: 40 | AK25: 101 | AL25: 331 | AM25: Normal | AN25: 2500 | AO25: 10 | AY25: 9 | AZ25: =60*M25/AB25 -> 33.333333 | BA25: =60/AB25 -> 16.666667
A26: 1819 | B26: Venta Normal | C26: GN | D26: ART. 2450 | E26: 360 | F26: 0.0343 | G26: 0.0283 | H26: =(F26-G26)/F26 -> 0.17492711 | I26: PVC | J26: PVC CRISTAL 560 x 250 | K26: CAJA Nº 17 | L26: BOLSAS DE 120 X 97 | M26: 2 | N26: 41 | P26: Christian | Q26: 45504 | R26: 12 | S26: 0.8 | T26: 0.15 | U26: 0.8 | V26: 0.15 | W26: 0.4 | X26: 0.12 | Y26: 0.16 | Z26: 0.33 | AA26: 0.15 | AB26: 3.6 | AC26: 51 | AD26: 104 | AE26: 104 | AF26: 104 | AG26: 40 | AH26: 30 | AI26: 40 | AJ26: 40 | AK26: 100 | AL26: 330 | AM26: Normal | AN26: 2400 | AO26: 10 | AY26: 9 | AZ26: =60*M26/AB26 -> 33.333333 | BA26: =60/AB26 -> 16.666667
A27: 1078 | B27: Venta Normal | C27: GN | D27: TAPA 50 OZ | E27: 240 | F27: 0.0129 | G27: 0.0093 | H27: =(F27-G27)/F27 -> 0.27906977 | I27: HIPST | J27: PVC CRISTAL 560 x 250 | K27: CAJA SOLUPLEX 103 (50 OZ) | L27: BOLSAS DE 120 X 97 | M27: 6 | N27: 40 | P27: Christian | Q27: 45366 | R27: 15 | S27: 3 | T27: 2.5 | U27: 3.8 | V27: 2 | W27: 0.35 | X27: 0.21 | Y27: 0.18 | Z27: 0.55 | AA27: 0.58 | AB27: 6.8 | AC27: 50 | AD27: 125 | AE27: 125 | AF27: 128 | AG27: 50 | AH27: 20 | AI27: 40 | AJ27: 20 | AK27: 100 | AL27: 392 | AM27: Normal | AN27: 1000 | AO27: 10 | AY27: 1 | AZ27: =60*M27/AB27 -> 52.941176 | BA27: =60/AB27 -> 8.8235294 | BB27: =60*60*M27*7/E27/7 -> 90
A28: 1818 | B28: Venta Normal | C28: GN | D28: ART. 2095 | E28: 200 | F28: 0.0299 | G28: 0.0247 | H28: =(F28-G28)/F28 -> 0.17391304 | I28: PVC | J28: PVC CRISTAL 460 x 300 | K28: CAJA Nº 1/2 | L28: BOLSAS DE 120 X 97 | M28: 2 | N28: 58 | P28: Christian | Q28: 45391 | R28: 15 | S28: 1 | T28: 0.1 | U28: 1 | V28: 0.1 | W28: 0.5 | X28: 0.2 | Y28: 0.16 | Z28: 0.7 | AA28: 0.3 | AB28: 4.6 | AC28: 45 | AD28: 106 | AE28: 106 | AF28: 106 | AG28: 50 | AH28: 20 | AI28: 40 | AJ28: 20 | AK28: 100 | AL28: 297 | AM28: Normal | AN28: 1000 | AO28: 10 | AY28: 6 | AZ28: =60*M28/AB28 -> 26.086957 | BA28: =60/AB28 -> 13.043478
A29: 1828 | B29: Venta Normal | C29: GN | D29: ART. 3142 | E29: 720 | F29: 0.0138 | G29: 0.0109 | H29: =(F29-G29)/F29 -> 0.21014493 | I29: PVC | J29: PVC CRISTAL 520 x 300 | K29: CAJA Nº 8 | L29: BOLSAS DE 120 X 125 | M29: 3 | N29: 27 | P29: Christian | Q29: 45418 | R29: 13 | S29: 1 | T29: 0.1 | U29: 1 | V29: 0.1 | W29: 0.46 | X29: 0.28 | Y29: 0.12 | Z29: 0.4 | AA29: 0.1 | AB29: 4 | AC29: 49 | AD29: 104 | AE29: 106 | AF29: 106 | AG29: 42 | AH29: 20 | AI29: 40 | AJ29: 20 | AK29: 65 | AL29: 181 | AM29: Normal | AN29: 500 | AO29: 10 | AY29: 8 | AZ29: =60*M29/AB29 -> 45 | BA29: =60/AB29 -> 15
A30: 1831 | B30: Venta Normal | C30: GN | D30: ART. TR 24 MEDIA | E30: 200 | F30: 0.0384 | G30: 0.0272 | H30: =(F30-G30)/F30 -> 0.29166667 | I30: PVC | J30: PVC CRISTAL 540 x 350 | K30: CAJA Nº 3 | L30: BOLSAS DE 120 X 97 | M30: 2 | N30: 58 | P30: Christian | Q30: 45390 | R30: 13 | S30: 1.2 | T30: 0.1 | U30: 1.2 | V30: 0.1 | W30: 1.2 | X30: 0.18 | Y30: 0.25 | Z30: 0.6 | AA30: 0.25 | AB30: 5.4 | AC30: 35 | AD30: 101 | AE30: 102 | AF30: 107 | AG30: 48 | AH30: 20 | AI30: 40 | AJ30: 20 | AK30: 100 | AL30: 263 | AM30: Normal | AN30: 400 | AO30: 10 | AY30: 5 | AZ30: =60*M30/AB30 -> 22.222222 | BA30: =60/AB30 -> 11.111111
A31: 1084 | B31: Venta Normal | C31: GN | D31: Z T 7 (BRASCA) | E31: 100 | F31: 0.1066 | G31: 0.0827 | H31: =(F31-G31)/F31 -> 0.22420263 | I31: PET | J31: PVC CRISTAL 560 x 400 | K31: CAJA Nº 4/1 | L31: BOLSAS DE 120 X 125 | M31: 1 | N31: 44 | P31: Christian | Q31: 45392 | R31: 14/15 | S31: 1,6 / 1,4 | T31: 0,3 / 0,2 | U31: 1,6 / 1,5 | V31: 0,3 / 0,2 | W31: 0,55 / 0,7 | X31: 0,14 / 0,17 | Y31: 0,25 / 0,21 | Z31: 0,5 / 0,45 | AA31: 0,3 / 0,3 | AB31: 5,9 / 5,6 | AC31: 51 / 49 | AD31: 107 / 120 | AE31: 107 / 107 | AF31: 106 /107 | AG31: 44 / 50 | AH31: 20 / 20 | AI31: 40 / 40 | AJ31: 20 / 20 | AK31: 100 / 100 | AL31: 291 / 292 | AM31: Normal | AN31: 700 / 1000 | AO31: 10 / 10 | AY31: 4 | AZ31: =60*M31/AB31 -> #VALUE! | BA31: =60/AB31 -> #VALUE!
A32: 1832 | B32: Venta Normal | C32: GN | D32: ART. TR 24 ALTA | E32: 200 | F32: 0.0438 | G32: 0.0308 | H32: =(F32-G32)/F32 -> 0.29680365 | I32: PVC | J32: PVC CRISTAL 540 x 400 | K32: CAJA Nº 6 | L32: BOLSAS DE 120 X 97 | M32: 2 | N32: 43 | P32: Christian | Q32: 45372 | R32: 13 | S32: 1.5 | T32: 0.3 | U32: 1.5 | V32: 0.3 | W32: 0.8 | X32: 0.33 | Y32: 0.3 | Z32: 0.9 | AA32: 0.45 | AB32: 6.7 | AC32: 54 | AD32: 108 | AE32: 108 | AF32: 108 | AG32: 45 | AH32: 20 | AI32: 40 | AJ32: 20 | AK32: 100 | AL32: 270 | AM32: Normal | AN32: 700 | AO32: 10 | AY32: 3 | AZ32: =60*M32/AB32 -> 17.910448 | BA32: =60/AB32 -> 8.9552239
A33: 1829 | B33: Venta Normal | C33: GN | D33: ART. 3185 | E33: 720 | F33: 0.0207 | G33: 0.015 | H33: =(F33-G33)/F33 -> 0.27536232 | I33: PVC | J33: PVC CRISTAL 520 x 450 | K33: CAJA Nº 8 | L33: BOLSAS DE 120 X 125 | M33: 3 | N33: 21 | P33: Christian | Q33: 45414 | R33: 13 | S33: 1 | T33: 0.2 | U33: 1 | V33: 0.2 | W33: 0.6 | X33: 0.28 | Y33: 0.12 | Z33: 0.6 | AA33: 0.2 | AB33: 4.6 | AC33: 48 | AD33: 106 | AE33: 106 | AF33: 105 | AG33: 42 | AH33: 20 | AI33: 40 | AJ33: 20 | AK33: 65 | AL33: 180 | AM33: Normal | AN33: 400 | AO33: 10 | AY33: 6 | AZ33: =60*M33/AB33 -> 39.130435 | BA33: =60/AB33 -> 13.043478

Sheet GN Análisis (2)
A1: COD. | B1: Estado | C1: Maquina | D1: ARTICULO | E1: UN por CAJA | F1: PESO BR. | G1: PESO NET. | H1: % SCRAP | I1: MATERIAL | J1: MATERIAL DETALLE | K1: CAJAS | L1: BOLSA | M1: CAV | N1: META | P1: Registrado por | Q1: FECHA | R1: MAQ | S1: Calentamiento | T1: Ventilador de calor | U1: Fomación | V1: Ventilador de forma | W1: intervalo de corte | X1: Retraso de expulsión | Y1: Expulsión | Z1: Transporte | AA1: Retraso de cierre | AB1: Promedio de ciclo | AC1: Molde | AD1: Zona1 | AE1: Zona2 | AF1: Zona3 | AG1: Precalentador | AH1: Presión de calentamiento | AI1: Presión de formación | AJ1: Presión de expusión | AK1: Velocidad | AL1: Recorrido | AM1: Modo | AN1: Acel/ Desacel | AO1: Velocidad del paso | AP1: Zona4 | AQ1: Zona5 | AZ1: Productos por minuto | BA1: Ciclo por minuto
A2: 1914 | B2: Venta Normal | C2: GN | D2: ART. 1560 | E2: 300 | F2: 0.0262 | G2: 0.0214 | H2: =(F2-G2)/F2 -> 0.18320611 | I2: PVC | J2: PVC CRISTAL 575 x 250 | K2: CAJA Nº 2 | L2: BOLSAS DE 120 X 97 | M2: 3 | N2: 45 | P2: Christian | Q2: 20/3/2024 / 22/7/24 | R2: 13/15 | S2: 1 / 1,5 | T2: 0,1 / 0,2 | U2: 1,1 /1,3 | V2: 0,1 / 0,2 | W2: 0,8 / 1,00 | X2: 0,2 / 0,18 | Y2: 0,22 / 0,15 | Z2: 0,4 / 0,45 | AA2: 0,3 /0,2 | AB2: 4,5 / 5,6 | AC2: 59 / 62 | AD2: 104 / 103 | AE2: 104 / 103 | AF2: 104 / 103 | AG2: 45 / 38 | AH2: 20 / 20 | AI2: 40 / 40 | AJ2: 20 / 20 | AK2: 100 / 100 | AL2: 359 / 365 | AM2: Normal | AN2: 700 / 1500 | AO2: 10 / 10 | AY2: 6 | AZ2: =60*M2/AB2 -> #VALUE! | BA2: =60/AB2 -> #VALUE!
A3: 1922 | B3: Venta Normal | C3: GN | D3: ART. 2465 | E3: 300 | F3: 0.0184 | G3: 0.0158 | H3: =(F3-G3)/F3 -> 0.14130435 | I3: PVC | J3: PVC CRISTAL 420 x 250 | K3: CAJA Nº 2 | L3: BOLSAS DE 120 X 97 | M3: 4 | N3: 60 | P3: Christian | Q3: 45404 | R3: 12 | S3: 1.3 | T3: 0.3 | U3: 1.2 | V3: 0.3 | W3: 0.7 | X3: 0.15 | Y3: 0.18 | Z3: 0.4 | AA3: 0.3 | AB3: 5.2 | AC3: 49 | AD3: 106 | AE3: 106 | AF3: 106 | AG3: 40 | AH3: 38 | AI3: 40 | AJ3: 40 | AK3: 101 | AL3: 459 | AM3: Normal | AN3: 2000 | AO3: 10 | AY3: 7 | AZ3: =60*M3/AB3 -> 46.153846 | BA3: =60/AB3 -> 11.538462
A4: 1093 | B4: Venta Normal | C4: GN | D4: TAPA 25 OZ | E4: 300 | F4: 0.0109 | G4: 0.0064 | H4: =(F4-G4)/F4 -> 0.41284404 | I4: PVC | J4: PVC CRISTAL 520 x 250 | K4: CAJA SOLUPLEX 101 (25 OZ) | L4: BOLSAS DE 120 X 97 | M4: 6 | N4: 75 | P4: Christian | Q4: 45348 | R4: 12 | S4: 2 | T4: 1.1 | U4: 2.1 | V4: 1.1 | W4: 0.25 | X4: 0.15 | Y4: 0.18 | Z4: 0.35 | AA4: 0.25 | AB4: 6.8 | AC4: 41 | AD4: 97 | AE4: 98 | AF4: 98 | AG4: 44 | AH4: 38 | AI4: 40 | AJ4: 40 | AK4: 67 | AL4: 328 | AM4: Normal | AN4: 2550 | AO4: 10 | AY4: 2 | AZ4: =60*M4/AB4 -> 52.941176 | BA4: =60/AB4 -> 8.8235294
A5: 591 | B5: Venta Normal | C5: GN | D5: LICORITA | E5: 1080 | F5: 0.0071 | G5: 0.0055 | H5: =(F5-G5)/F5 -> 0.22535211 | I5: PVC | J5: PVC CRISTAL 575 x 250 | K5: CAJA Nº 12 | L5: BOLSAS DE 120 X 97 | M5: 15 | N5: 30 | P5: Christian | Q5: 45351 | R5: 12 | S5: 1.9 | T5: 0.5 | U5: 2 | V5: 0.8 | W5: 1.3 | X5: 0.16 | Y5: 0.14 | Z5: 0.9 | AA5: 0.6 | AB5: 8.7 | AC5: 52 | AD5: 100 | AE5: 100 | AF5: 100 | AG5: 44 | AH5: 30 | AI5: 40 | AJ5: 40 | AK5: 66 | AL5: 510 | AM5: Normal | AN5: 2500 | AO5: 10 | AY5: 1 | AZ5: =60*M5/AB5 -> 103.44828 | BA5: =60/AB5 -> 6.8965517
A6: 1821 | B6: Venta Normal | C6: GN | D6: ART. 2475 | E6: 360 | F6: 0.0343 | G6: 0.0283 | H6: =(F6-G6)/F6 -> 0.17492711 | I6: PVC | J6: PVC CRISTAL 560 x 250 | K6: CAJA Nº 17 | L6: BOLSAS DE 120 X 97 | M6: 2 | N6: 41 | P6: Christian | Q6: 45376 | R6: 12 | S6: 1.1 | T6: 0.1 | U6: 1.1 | V6: 0.1 | W6: 0.45 | X6: 0.12 | Y6: 0.22 | Z6: 0.4 | AA6: 0.18 | AB6: 3.6 | AC6: 46 | AD6: 106 | AE6: 106 | AF6: 106 | AG6: 40 | AH6: 30 | AI6: 40 | AJ6: 40 | AK6: 101 | AL6: 331 | AM6: Normal | AN6: 2500 | AO6: 10 | AY6: 9 | AZ6: =60*M6/AB6 -> 33.333333 | BA6: =60/AB6 -> 16.666667
A7: 1819 | B7: Venta Normal | C7: GN | D7: ART. 2450 | E7: 360 | F7: 0.0343 | G7: 0.0283 | H7: =(F7-G7)/F7 -> 0.17492711 | I7: PVC | J7: PVC CRISTAL 560 x 250 | K7: CAJA Nº 17 | L7: BOLSAS DE 120 X 97 | M7: 2 | N7: 41 | P7: Christian | Q7: 45504 | R7: 12 | S7: 0.8 | T7: 0.15 | U7: 0.8 | V7: 0.15 | W7: 0.4 | X7: 0.12 | Y7: 0.16 | Z7: 0.33 | AA7: 0.15 | AB7: 3.6 | AC7: 51 | AD7: 104 | AE7: 104 | AF7: 104 | AG7: 40 | AH7: 30 | AI7: 40 | AJ7: 40 | AK7: 100 | AL7: 330 | AM7: Normal | AN7: 2400 | AO7: 10 | AY7: 9 | AZ7: =60*M7/AB7 -> 33.333333 | BA7: =60/AB7 -> 16.666667
A8: 1078 | B8: Venta Normal | C8: GN | D8: TAPA 50 OZ | E8: 240 | F8: 0.0129 | G8: 0.0093 | H8: =(F8-G8)/F8 -> 0.27906977 | I8: HIPST | J8: PVC CRISTAL 560 x 250 | K8: CAJA SOLUPLEX 103 (50 OZ) | L8: BOLSAS DE 120 X 97 | M8: 6 | N8: 40 | P8: Christian | Q8: 45366 | R8: 15 | S8: 3 | T8: 2.5 | U8: 3.8 | V8: 2 | W8: 0.35 | X8: 0.21 | Y8: 0.18 | Z8: 0.55 | AA8: 0.58 | AB8: 13.5 | AC8: 50 | AD8: 125 | AE8: 125 | AF8: 128 | AG8: 50 | AH8: 20 | AI8: 40 | AJ8: 20 | AK8: 100 | AL8: 392 | AM8: Normal | AN8: 1000 | AO8: 10 | AY8: 1 | AZ8: =60*M8/AB8 -> 26.666667 | BA8: =60/AB8 -> 4.4444444
A9: 1818 | B9: Venta Normal | C9: GN | D9: ART. 2095 | E9: 200 | F9: 0.0299 | G9: 0.0247 | H9: =(F9-G9)/F9 -> 0.17391304 | I9: PVC | J9: PVC CRISTAL 460 x 300 | K9: CAJA Nº 1/2 | L9: BOLSAS DE 120 X 97 | M9: 2 | N9: 58 | P9: Christian | Q9: 45391 | R9: 15 | S9: 1 | T9: 0.1 | U9: 1 | V9: 0.1 | W9: 0.5 | X9: 0.2 | Y9: 0.16 | Z9: 0.7 | AA9: 0.3 | AB9: 4.6 | AC9: 45 | AD9: 106 | AE9: 106 | AF9: 106 | AG9: 50 | AH9: 20 | AI9: 40 | AJ9: 20 | AK9: 100 | AL9: 297 | AM9: Normal | AN9: 1000 | AO9: 10 | AY9: 6 | AZ9: =60*M9/AB9 -> 26.086957 | BA9: =60/AB9 -> 13.043478
A10: 1828 | B10: Venta Normal | C10: GN | D10: ART. 3142 | E10: 720 | F10: 0.0138 | G10: 0.0109 | H10: =(F10-G10)/F10 -> 0.21014493 | I10: PVC | J10: PVC CRISTAL 520 x 300 | K10: CAJA Nº 8 | L10: BOLSAS DE 120 X 125 | M10: 3 | N10: 27 | P10: Christian | Q10: 45418 | R10: 13 | S10: 1 | T10: 0.1 | U10: 1 | V10: 0.1 | W10: 0.46 | X10: 0.28 | Y10: 0.12 | Z10: 0.4 | AA10: 0.1 | AB10: 4 | AC10: 49 | AD10: 104 | AE10: 106 | AF10: 106 | AG10: 42 | AH10: 20 | AI10: 40 | AJ10: 20 | AK10: 65 | AL10: 181 | AM10: Normal | AN10: 500 | AO10: 10 | AY10: 8 | AZ10: =60*M10/AB10 -> 45 | BA10: =60/AB10 -> 15
A11: 1831 | B11: Venta Normal | C11: GN | D11: ART. TR 24 MEDIA | E11: 200 | F11: 0.0384 | G11: 0.0272 | H11: =(F11-G11)/F11 -> 0.29166667 | I11: PVC | J11: PVC CRISTAL 540 x 350 | K11: CAJA Nº 3 | L11: BOLSAS DE 120 X 97 | M11: 2 | N11: 58 | P11: Christian | Q11: 45390 | R11: 13 | S11: 1.2 | T11: 0.1 | U11: 1.2 | V11: 0.1 | W11: 1.2 | X11: 0.18 | Y11: 0.25 | Z11: 0.6 | AA11: 0.25 | AB11: 5.4 | AC11: 35 | AD11: 101 | AE11: 102 | AF11: 107 | AG11: 48 | AH11: 20 | AI11: 40 | AJ11: 20 | AK11: 100 | AL11: 263 | AM11: Normal | AN11: 400 | AO11: 10 | AY11: 5 | AZ11: =60*M11/AB11 -> 22.222222 | BA11: =60/AB11 -> 11.111111
A12: 1084 | B12: Venta Normal | C12: GN | D12: Z T 7 (BRASCA) | E12: 100 | F12: 0.1066 | G12: 0.0827 | H12: =(F12-G12)/F12 -> 0.22420263 | I12: PET | J12: PVC CRISTAL 560 x 400 | K12: CAJA Nº 4/1 | L12: BOLSAS DE 120 X 125 | M12: 1 | N12: 44 | P12: Christian | Q12: 45392 | R12: 14/15 | S12: 1,6 / 1,4 | T12: 0,3 / 0,2 | U12: 1,6 / 1,5 | V12: 0,3 / 0,2 | W12: 0,55 / 0,7 | X12: 0,14 / 0,17 | Y12: 0,25 / 0,21 | Z12: 0,5 / 0,45 | AA12: 0,3 / 0,3 | AB12: 5,9 / 5,6 | AC12: 51 / 49 | AD12: 107 / 120 | AE12: 107 / 107 | AF12: 106 /107 | AG12: 44 / 50 | AH12: 20 / 20 | AI12: 40 / 40 | AJ12: 20 / 20 | AK12: 100 / 100 | AL12: 291 / 292 | AM12: Normal | AN12: 700 / 1000 | AO12: 10 / 10 | AY12: 4 | AZ12: =60*M12/AB12 -> #VALUE! | BA12: =60/AB12 -> #VALUE!
A13: 1832 | B13: Venta Normal | C13: GN | D13: ART. TR 24 ALTA | E13: 200 | F13: 0.0438 | G13: 0.0308 | H13: =(F13-G13)/F13 -> 0.29680365 | I13: PVC | J13: PVC CRISTAL 540 x 400 | K13: CAJA Nº 6 | L13: BOLSAS DE 120 X 97 | M13: 2 | N13: 43 | P13: Christian | Q13: 45372 | R13: 13 | S13: 1.5 | T13: 0.3 | U13: 1.5 | V13: 0.3 | W13: 0.8 | X13: 0.33 | Y13: 0.3 | Z13: 0.9 | AA13: 0.45 | AB13: 6.7 | AC13: 54 | AD13: 108 | AE13: 108 | AF13: 108 | AG13: 45 | AH13: 20 | AI13: 40 | AJ13: 20 | AK13: 100 | AL13: 270 | AM13: Normal | AN13: 700 | AO13: 10 | AY13: 3 | AZ13: =60*M13/AB13 -> 17.910448 | BA13: =60/AB13 -> 8.9552239
A14: 1829 | B14: Venta Normal | C14: GN | D14: ART. 3185 | E14: 720 | F14: 0.0207 | G14: 0.015 | H14: =(F14-G14)/F14 -> 0.27536232 | I14: PVC | J14: PVC CRISTAL 520 x 450 | K14: CAJA Nº 8 | L14: BOLSAS DE 120 X 125 | M14: 3 | N14: 21 | P14: Christian | Q14: 45414 | R14: 13 | S14: 1 | T14: 0.2 | U14: 1 | V14: 0.2 | W14: 0.6 | X14: 0.28 | Y14: 0.12 | Z14: 0.6 | AA14: 0.2 | AB14: 4.6 | AC14: 48 | AD14: 106 | AE14: 106 | AF14: 105 | AG14: 42 | AH14: 20 | AI14: 40 | AJ14: 20 | AK14: 65 | AL14: 180 | AM14: Normal | AN14: 400 | AO14: 10 | AY14: 6 | AZ14: =60*M14/AB14 -> 39.130435 | BA14: =60/AB14 -> 13.043478

Sheet BASE GN
E1: SISTEMA INTEGRADO DE GESTIÓN AJOVER-DARNEL | I1: AJI: | Q1: SISTEMA INTEGRADO DE GESTIÓN AJOVER-DARNEL | U1: AJI:P16-P40
I2: MAQUINA: | J2: =Masterdata!AE211 -> 0 | U2: MAQUINA: 49
I3: FECHA: | J3: =Masterdata!AD211 -> 0 | U3: FECHA:
I4: Nº de Rev: 1 | U4: Nº de Rev:
E5: PERFIL DE OPERACIÓN TERMOFORMADORA GN | Q5: PERFIL DE OPERACIÓN TERMOFORMADORA GN
C6: Descripción del Producto: | E6: =Masterdata!D211 -> TRAP BULK | J6: =Masterdata!A211 -> 14 | O6: Descripción del Producto:
C8: PROGRAMACION Y AJUSTE DE MAQUINA | O8: PROGRAMACION Y AJUSTE DE MAQUINA
C10: TEMPORIZADORES | E10: VALORES | F10: VALORES | H10: PRESIONES EN PSI | I10: VALORES | O10: TEMPORIZADORES | Q10: VALORES | R10: VALORES | T10: PRESIONES EN PSI | U10: VALORES
E11: MINIMO | F11: ESTANDAR | I11: ESTANDAR | Q11: MINIMO | R11: ESTANDAR | U11: ESTANDAR
C12: CALENTAMIENTO | F12: =Masterdata!AF211 -> 0 | O12: CALENTAMIENTO
C13: VENTILADOR DE CALOR | F13: =Masterdata!AG211 -> 0 | H13: LINEA PRINCIPAL | O13: VENTILADOR DE CALOR | T13: LINEA PRINCIPAL
C14: FORMACION | F14: =Masterdata!AH211 -> 0 | H14: CALENTAMIENTO | I14: =Masterdata!AU211 -> 0 | O14: FORMACION | T14: CALENTAMIENTO
C15: VENTILADOR DE FORMACION | F15: =Masterdata!AI211 -> 0 | H15: FORMACIÓN | I15: =Masterdata!AV211 -> 0 | O15: VENTILADOR DE FORMACION | T15: FORMACIÓN
C16: INTERVALO DE CORTE | F16: =Masterdata!AJ211 -> 0 | H16: EXPULSION | I16: =Masterdata!AW211 -> 0 | O16: INTERVALO DE CORTE | T16: EXPULSION
C17: RETRASO DE EXPULSION | F17: =Masterdata!AK211 -> 0 | H17: Este perfirl puede presentar variaciones en un | O17: INTERVALO DE CORTE | T17: Este perfirl puede presentar variaciones en un
C18: EXPULSION | F18: =Masterdata!AL211 -> 0 | H18: rango de + ó - 70 PSI de presión | O18: EXPULSION | T18: rango de + ó - 70 PSI de presión
C19: TRANSPORTE | F19: =Masterdata!AM211 -> 0 | O19: TRANSPORTE
C20: RETRASO DE CIERRE | F20: =Masterdata!AN211 -> 0 | H20: TRANSPORTE | I20: VALORES | O20: RETRASO DE CIERRE | T20: TRANSPORTE | U20: VALORES
C21: PROMEDIO CICLO | F21: =Masterdata!AO211 -> 0 | I21: ESTANDAR | O21: PROMEDIO CICLO | U21: ESTANDAR
C22: Este perfil puede presentar variaciones en los parametros | H22: VELOCIDAD | I22: =Masterdata!AX211 -> 0 | O22: Este perfil puede presentar variaciones en los parametros | T22: VELOCIDAD
C23: de tiempo con un rango de + ó - 3,00 segundos de tiempo. | H23: RECORRIDO | I23: =Masterdata!AY211 -> 0 | O23: de tiempo con un rango de + ó - 3,00 segundos de tiempo. | T23: GOLPE
H24: ACELERACION DESACELERACION | I24: =Masterdata!BA211 -> 0 | T24: ACELERACION DESACELERACION
C25: TEMPERATURAS EN GRADOS °C | E25: VALORES EN º C | F25: VALORES | H25: VELOCIDAD PASO | I25: =Masterdata!BB211 -> 0 | O25: TEMPERATURAS EN GRADOS °C | Q25: VALORES EN º C | R25: VALORES | T25: VELOCIDAD PASO
E26: ESTANDAR | F26: ESTANDAR | Q26: ESTANDAR | R26: ESTANDAR
C27: MOLDE | F27: =Masterdata!AP211 -> 0 | H27: MATERIA PRIMA | O27: MOLDE | T27: MATERIA PRIMA
C28: PRECALENTADOR | F28: =Masterdata!AT211 -> 0 | H28: MATERIAL LÁMINA | I28: =Masterdata!J211 -> PAI NEGRO 520 x 400 | O28: PRECALENTADOR | T28: MATERIAL LÁMINA
C29: ZONA 1 | F29: =Masterdata!AQ211 -> 0 | H29: CALIBRE LÁMINA (Micrones) | O29: ZONA 1 | T29: CALIBRE LÁMINA (Micrones)
C30: ZONA 2 | F30: =Masterdata!AR211 -> 0 | H30: ANCHO LÁMINA | O30: ZONA 2 | T30: ANCHO LÁMINA
C31: ZONA 3 | F31: =Masterdata!AS211 -> 0
C32: Este perfil puede presentar variaciones en zonas de | O32: Este perfil puede presentar variaciones en zonas de
C33: calentamiento de + ó - 30 grados centigrados | O33: calentamiento de + ó - 30 grados centigrados
F41: Seleccionar toda la página
F42: CONTROL + B = Buscar | I42: Columna1 | J42: Columna2
F43: lUEGO ELEGIR REEMPLAZAR
F44: poner los dos números de líneas
F45: 208
F46: 208

Sheet Hoja1
A1: COD. | B1: Estado | C1: ARTICULO | D1: Maquina | E1: UN por CAJA | F1: PESO BR. | G1: PESO NET. | H1: % SCRAP | I1: MATERIAL | J1: MATERIAL DETALLE | K1: CAJAS | L1: BOLSA | M1: CAV | N1: META | O1: Relación Virgen Reciclado
A2: 49 | B2: Venta Normal | C2: CUNA 172 GRS. NEGRO | D2: GN | E2: 4910 | F2: 0.0035 | G2: 0.0025 | H2: =(F2-G2)/F2 -> 0.28571429 | I2: HIPST | J2: PAI NEGRO 550 x 200 | K2: CAJA Nº 4/1 | L2: BOLSAS DE 120 X 125 | M2: 14 | N2: 16
A3: 170 | B3: Venta Normal | C3: CUNA PARA GALLETITAS NEGRO | D3: GN | E3: 4000 | F3: 0.0037 | G3: 0.0027 | H3: =(F3-G3)/F3 -> 0.27027027 | I3: HIPST | J3: PAI NEGRO 550 x 200 | K3: CAJA Nº 3 | L3: BOLSAS DE 120 X 97 | M3: 21 | N3: 15
A4: 189 | B4: Venta Normal | C4: CUNA POCKET NEGRO | D4: GN | E4: 4030 | F4: 0.0024 | G4: 0.0017 | H4: =(F4-G4)/F4 -> 0.29166667 | I4: HIPST | J4: PAI NEGRO 550 x 240 | K4: CAJA Nº 4/1 | L4: BOLSAS DE 120 X 125 | M4: 2 | N4: 60
A5: 901 | B5: Venta Normal | C5: SABORISIMA PAI | D5: GN | E5: 1500 | F5: 0.0097 | G5: 0.0064 | H5: =(F5-G5)/F5 -> 0.34020619 | I5: HIPST | J5: PAI NEGRO 520 x 300 | K5: CAJA Nº 4/1 | L5: BOLSAS DE 120 X 125 | M5: 10 | N5: 25
A6: 1826 | B6: Venta Normal | C6: ART. 3110 PAI NEGRO | D6: GN | E6: 720 | F6: 0.0109 | G6: 0.0075 | H6: =(F6-G6)/F6 -> 0.31192661 | I6: HIPST | J6: PAI NEGRO 520 x 300 | K6: CAJA Nº 4/1 | L6: BOLSAS DE 120 X 125 | M6: 3 | N6: 25
A7: 1075 | B7: Venta Normal | C7: TAPA 50 OZ PAI NEGRO | D7: GN | E7: 240 | F7: 0.0129 | G7: 0.0093 | H7: =(F7-G7)/F7 -> 0.27906977 | I7: HIPST | J7: PAI NEGRO 560 x 300 | M7: 18 | N7: 130
A8: 1003 | B8: Venta Normal | C8: Z 105 OVALADA BASE PAI NEGRO | D8: GN | E8: 500 | F8: 0.0162 | G8: 0.0108 | H8: =(F8-G8)/F8 -> 0.33333333 | I8: HIPST | J8: PAI NEGRO 600 x 300 | K8: CAJA Nº 3 | L8: BOLSAS DE 120 X 97 | M8: 40 | N8: 11
A9: 100 | B9: Venta Normal | C9: ART. BR 20 NEGRO | D9: GN | E9: 200 | F9: 0.0289 | G9: 0.0166 | H9: =(F9-G9)/F9 -> 0.42560554 | I9: HIPST | J9: PAI NEGRO 530 x 350 | K9: CAJA Nº 8 | L9: BOLSAS DE 120 X 125 | M9: 4 | N9: 60
A10: 1130 | B10: Venta Normal | C10: Z T 2200 BASE NEGRO | D10: GN | E10: 200 | F10: 0.0335 | G10: 0.019 | H10: =(F10-G10)/F10 -> 0.43283582 | I10: HIPST | J10: PAI NEGRO 550 x 350 | K10: CAJA Nº 6 | L10: BOLSAS DE 120 X 97 | M10: 18 | N10: 28
A11: 1946 | B11: Venta Normal | C11: Z T 2200 BASE NEGRO X 100 | D11: GN | E11: 100 | F11: 0.0307 | G11: 0.019 | H11: =(F11-G11)/F11 -> 0.38110749 | I11: HIPST | J11: PAI NEGRO 550 x 350 | K11: CAJA SOLUPLEX 103 (50 OZ) | L11: BOLSAS DE 120 X 97 | M11: 6 | N11: 70
A12: 388 | B12: Discontinuado | C12: BUDIN VALENTE PAI NEGRO | D12: GN | E12: 2400 | F12: 0.0083 | G12: 0.0073 | H12: =(F12-G12)/F12 -> 0.12048193 | I12: HIPST | J12: PAI NEGRO 600 x 350 | K12: CAJA Nº 12 | L12: BOLSAS DE 120 X 97 | M12: 9 | N12: 20
A13: 728 | B13: Venta Normal | C13: ART. 1510 PAI NEGRO | D13: GN | E13: 800 | F13: 0.0131 | G13: 0.0068 | H13: =(F13-G13)/F13 -> 0.48091603 | I13: HIPST | J13: PAI NEGRO 600 x 350 | K13: CAJA Nº 4/1 | L13: BOLSAS DE 120 X 125 | M13: 4 | N13: 28
A14: 732 | B14: Venta Normal | C14: ART. 1810 PAI NEGRO | D14: GN | E14: 540 | F14: 0.0243 | G14: 0.0105 | H14: =(F14-G14)/F14 -> 0.56790123 | I14: HIPST | J14: PAI NEGRO 600 x 350 | K14: CAJA Nº 3 | L14: BOLSAS DE 120 X 97 | M14: 10 | N14: 44
A15: 51 | B15: Discontinuado | C15: ART. B 21 M | D15: GN | E15: 160 | F15: 0.0528 | G15: 0.0437 | H15: =(F15-G15)/F15 -> 0.17234848 | I15: HIPST | J15: PAI NEGRO 320 x 400 | K15: CAJA Nº 4 | L15: BOLSAS DE 120 X 125 | M15: 1 | N15: 58
A16: 98 | B16: Venta Normal | C16: ART. B 16 NEGRO | D16: GN | E16: 60 | F16: 0.0577 | G16: 0.046 | H16: =(F16-G16)/F16 -> 0.20277296 | I16: HIPST | J16: PAI NEGRO 320 x 400 | K16: CAJA Nº 4/1 | L16: BOLSAS DE 120 X 125 | M16: 1 | N16: 90
A17: 99 | B17: Venta Normal | C17: ART. B 16 NEGRO X 160 | D17: GN | E17: 160 | F17: 0.0577 | G17: 0.046 | H17: =(F17-G17)/F17 -> 0.20277296 | I17: HIPST | J17: PAI NEGRO 320 x 400 | K17: CAJA Nº 4 | L17: BOLSAS DE 120 X 125 | M17: 1 | N17: 37
A18: 106 | B18: Venta Normal | C18: ART. BR 26 NEGRO | D18: GN | E18: 200 | F18: 0.0479 | G18: 0.032 | H18: =(F18-G18)/F18 -> 0.33194154 | I18: HIPST | J18: PAI NEGRO 340 x 400 | K18: CAJA Nº 9 | L18: BOLSAS DE 120 X 125 | M18: 1 | N18: 40
A19: 108 | B19: Venta Normal | C19: ART. BR 29 NEGRO | D19: GN | E19: 100 | F19: 0.0594 | G19: 0.0444 | H19: =(F19-G19)/F19 -> 0.25252525 | I19: HIPST | J19: PAI NEGRO 365 x 400 | K19: CAJA Nº 5 | L19: BOLSAS DE 120 X 125 | M19: 1 | N19: 50
... A34: 1055 | B34: Venta Normal | C34: MAMUSCHKA 8 ANIMALITOS | D34: Semiautomaticas | E34: 1000 | F34: 0.0097 | G34: 0.0067 | H34: =(F34-G34)/F34 -> 0.30927835 | I34: HIPST | J34: PAI NEGRO 600 x 300 | K34: CAJA Nº 3 | L34: BOLSAS DE 120 X 97 | M34: 12 | N34: 15
A35: 1805 | B35: Venta Normal | C35: RAPA NUI TRUFAS GRANDE TAPA | D35: Semiautomaticas | E35: 1200 | F35: 0.0124 | G35: 0.0071 | H35: =(F35-G35)/F35 -> 0.42741935 | I35: HIPST | J35: PAI NEGRO 600 x 300 | K35: CAJA Nº 4/1 | L35: BOLSAS DE 120 X 125 | M35: 12
A36: 1054 | B36: Venta Normal | C36: MAMUSCHKA 16 ANIMALITOS | D36: Semiautomaticas | E36: 450 | F36: 0.0162 | G36: 0.0122 | H36: =(F36-G36)/F36 -> 0.24691358 | I36: HIPST | J36: PAI NEGRO 630 x 300 | K36: CAJA Nº 4/1 | L36: BOLSAS DE 120 X 125 | M36: 6 | N36: 26
A37: 725 | B37: Venta Normal | C37: ART. 1410 PAI NEGRO | D37: Semiautomaticas | E37: 1320 | F37: 0.0072 | G37: 0.0054 | H37: =(F37-G37)/F37 -> 0.25 | I37: HIPST | J37: PAI NEGRO 650 x 300 | K37: CAJA Nº 4/1 | L37: BOLSAS DE 120 X 125 | M37: 40 | N37: 20
A38: 888 | B38: Venta Normal | C38: RAPA NUI TRUFAS CHICA TAPA | D38: Semiautomaticas | E38: 3000 | F38: 0.0054 | G38: 0.0032 | H38: =(F38-G38)/F38 -> 0.40740741 | I38: HIPST | J38: PAI NEGRO 650 x 300 | K38: CAJA Nº 4/1 | L38: BOLSAS DE 120 X 125 | M38: 15 | N38: 20
A39: 1089 | B39: Venta Normal | C39: Z T 9 BASE NEGRO | D39: Semiautomaticas | E39: 360 | F39: 0.0284 | G39: 0.0152 | H39: =(F39-G39)/F39 -> 0.46478873 | I39: HIPST | J39: PAI NEGRO 510 x 350 | K39: CAJA Nº 5 | L39: BOLSAS DE 120 X 125 | M39: 10 | N39: 28
A40: 202 | B40: Venta Normal | C40: BANDEJA 3 DIVISIONES NEGRO | D40: Semiautomaticas | E40: 800 | F40: 0.0165 | G40: 0.014 | H40: =(F40-G40)/F40 -> 0.15151515 | I40: HIPST | J40: PAI NEGRO 550 x 350 | K40: CAJA Nº 8 | L40: BOLSAS DE 120 X 125 | M40: 2 | N40: 110
A41: 1121 | B41: Venta Normal | C41: Z T 19 BASE NEGRO X 100 | D41: Semiautomaticas | E41: 100 | F41: 0.0158 | G41: 0.0089 | H41: =(F41-G41)/F41 -> 0.43670886 | I41: HIPST | J41: PAI NEGRO 560 x 350 | K41: CAJA Nº 3 | L41: BOLSAS DE 120 X 97 | M41: 14 | N41: 26
A42: 203 | B42: Venta Normal | C42: BANDEJA 4 DIVISIONES NEGRO | D42: Semiautomaticas | E42: 400 | F42: 0.0256 | G42: 0.0205 | H42: =(F42-G42)/F42 -> 0.19921875 | I42: HIPST | J42: PAI NEGRO 600 x 350 | K42: CAJA Nº 4/1 | L42: BOLSAS DE 120 X 125 | M42: 6 | N42: 22
A43: 225 | B43: Discontinuado | C43: BAND. 505 FOCACHA RECTANGULAR | D43: Semiautomaticas | E43: 810 | F43: 0.0362 | H43: =(F43-G43)/F43 -> 1 | I43: HIPST | J43: PAI NEGRO 600 x 350 | K43: CAJA Nº 4/1 | L43: BOLSAS DE 120 X 125 | M43: 16 | N43: 24
A44: 435 | B44: Venta Normal | C44: COLONIA CAROYA PAI NEGRO | D44: Semiautomaticas | E44: 650 | F44: 0.0149 | G44: 0.0107 | H44: =(F44-G44)/F44 -> 0.28187919 | I44: HIPST | J44: PAI NEGRO 600 x 350 | K44: CAJA Nº 4/1 | L44: BOLSAS DE 120 X 125 | M44: 27 | N44: 20
A45: 672 | B45: Venta Normal | C45: MAGDALENAS X 6 PAI NEGRO | D45: Semiautomaticas | E45: 2000 | F45: 0.0099 | G45: 0.007 | H45: =(F45-G45)/F45 -> 0.29292929 | I45: HIPST | J45: PAI NEGRO 600 x 350 | K45: CAJA Nº 5 | L45: BOLSAS DE 120 X 125 | M45: 12 | N45: 21
A46: 1119 | B46: Venta Normal | C46: Z T 18 BASE NEGRO | D46: Semiautomaticas | E46: 480 | F46: 0.0218 | G46: 0.0149 | H46: =(F46-G46)/F46 -> 0.31651376 | I46: HIPST | J46: PAI NEGRO 600 x 350 | K46: CAJA Nº 4/1 | L46: BOLSAS DE 120 X 125 | M46: 18 | N46: 130
A47: 1123 | B47: Venta Normal | C47: Z T 19 BASE NEGRO | D47: Semiautomaticas | E47: 650 | F47: 0.0158 | G47: 0.0089 | H47: =(F47-G47)/F47 -> 0.43670886 | I47: HIPST | J47: PAI NEGRO 600 x 350 | L47: BOLSAS DE 120 X 97 | M47: 12 | N47: 100
A48: 1973 | B48: Venta Normal | C48: Z T 18 BASE NEGRO X 100 | D48: Semiautomaticas | E48: 100 | F48: 0.0218 | G48: 0.0149 | H48: =(F48-G48)/F48 -> 0.31651376 | I48: HIPST | J48: PAI NEGRO 600 x 350 | K48: CAJA Nº 7 | L48: BOLSAS DE 120 X 125 | M48: 2 | N48: 60
A49: 226 | B49: Discontinuado | C49: BAND. 505 FOCACHA OVALADA NEGRA | D49: Semiautomaticas | E49: 810 | F49: 0.0305 | G49: 0.0253 | H49: =(F49-G49)/F49 -> 0.1704918 | I49: HIPST | J49: PAI NEGRO 630 x 350 | K49: CAJA Nº 4/1 | L49: BOLSAS DE 120 X 125 | M49: 25 | N49: 26
A50: 679 | B50: Venta Normal | C50: MAGDALENAS X 8 PAI NEGRO | D50: Semiautomaticas | E50: 1800 | F50: 0.0116 | G50: 0.0101 | H50: =(F50-G50)/F50 -> 0.12931034 | I50: HIPST | J50: PAI NEGRO 630 x 350 | K50: CAJA Nº 4/1 | L50: BOLSAS DE 120 X 125 | M50: 30 | N50: 8
A51: 1109 | B51: Venta Normal | C51: Z T 14 BASE NEGRO | D51: Semiautomaticas | E51: 350 | F51: 0.0207 | G51: 0.0173 | H51: =(F51-G51)/F51 -> 0.16425121 | I51: HIPST | J51: PAI NEGRO 700 x 350 | K51: CAJA Nº 4/1 | L51: BOLSAS DE 120 X 125 | M51: 12 | N51: 34
A52: 1112 | B52: Venta Normal | C52: Z T 15 BASE NEGRO | D52: Semiautomaticas | E52: 250 | F52: 0.0276 | G52: 0.0236 | H52: =(F52-G52)/F52 -> 0.14492754 | I52: HIPST | J52: PAI NEGRO 700 x 350 | K52: CAJA Nº 5 | L52: BOLSAS DE 120 X 125 | M52: 6 | N52: 44
A53: 1901 | B53: Venta Normal | C53: ART. 2 BASE BAJA NEGRO | D53: Semiautomaticas | E53: 300 | F53: 0.0206 | G53: 0.0121 | H53: =(F53-G53)/F53 -> 0.41262136 | I53: HIPST | J53: PAI NEGRO 560 x 400 | K53: CAJA Nº 3 | L53: BOLSAS DE 120 X 97 | M53: 14 | N53: 24
A54: 78 | B54: Venta Normal | C54: ART. 3 BASE CON SUPLEMENTO NEGRO | D54: Semiautomaticas | E54: 300 | F54: 0.0264 | G54: 0.0173 | H54: =(F54-G54)/F54 -> 0.34469697 | I54: HIPST | J54: PAI NEGRO 600 x 400 | K54: CAJA Nº 3 | L54: BOLSAS DE 120 X 97 | M54: 12 | N54: 26
A55: 79 | B55: Venta Normal | C55: ART. 3 BASE CON DIVISIONES NEGRO | D55: Semiautomaticas | E55: 300 | F55: 0.0264 | G55: 0.0173 | H55: =(F55-G55)/F55 -> 0.34469697 | I55: HIPST | J55: PAI NEGRO 600 x 400 | K55: CAJA Nº 4 SIN LOGO | M55: 6 | N55: 70
A56: 833 | B56: Venta Normal | C56: PLANTINES | D56: Semiautomaticas | E56: 360 | F56: 0.0453 | G56: 0.0404 | H56: =(F56-G56)/F56 -> 0.10816777 | I56: HIPST | J56: PAI NEGRO 600 x 400 | K56: CAJA Nº 3 | L56: BOLSAS DE 120 X 97 | M56: 20 | N56: 18
A57: 1061 | B57: Venta Normal | C57: Z 114 PAI NEGRO | D57: Semiautomaticas | E57: 1000 | F57: 0.0129 | H57: =(F57-G57)/F57 -> 1 | I57: HIPST | J57: PAI NEGRO 600 x 400 | K57: CAJA Nº 3 | L57: BOLSAS DE 120 X 97 | M57: 12 | N57: 26
A58: 1903 | B58: Venta Normal | C58: ART. 3 BASE NEGRO | D58: Semiautomaticas | E58: 300 | F58: 0.0264 | G58: 0.0173 | H58: =(F58-G58)/F58 -> 0.34469697 | I58: HIPST | J58: PAI NEGRO 600 x 400 | K58: CAJA Nº 4 | L58: BOLSAS DE 120 X 125 | M58: 6 | N58: 22
A59: 852 | B59: Venta Normal | C59: POMELO X 4 | D59: Semiautomaticas | E59: 1450 | F59: 0.0204 | G59: 0.0149 | H59: =(F59-G59)/F59 -> 0.26960784 | I59: HIPST | J59: PAI NEGRO 650 x 400 | K59: CAJA Nº 4 | L59: BOLSAS DE 120 X 125 | M59: 20 | N59: 10
A60: 1042 | B60: Venta Normal | C60: Z 12 PAI NEGRO | D60: Semiautomaticas | E60: 1300 | F60: 0.016 | H60: =(F60-G60)/F60 -> 1 | I60: HIPST | J60: PAI NEGRO 650 x 400 | L60: BOLSAS DE 120 X 125 | M60: 8
A61: 1099 | B61: Discontinuado | C61: Z T 12 BASE NEGRO | D61: Semiautomaticas | E61: 160 | F61: 0.0436 | G61: 0.0275 | H61: =(F61-G61)/F61 -> 0.36926606 | I61: HIPST | J61: PAI NEGRO 650 x 400 | K61: CAJA Nº 4/1 | L61: BOLSAS DE 120 X 125 | M61: 6 | N61: 20
A62: 687 | B62: Venta Normal | C62: MAMUSCHKA TRUFAS | D62: Semiautomaticas | E62: 1760 | F62: 0.0041 | G62: 0.0026 | H62: =(F62-G62)/F62 -> 0.36585366 | I62: HIPST | J62: PAI NEGRO 680 x 400 | K62: CAJA Nº 4 | L62: BOLSAS DE 120 X 125 | M62: 16 | N62: 35
A63: 1103 | B63: Venta Normal | C63: Z T 13 BASE NEGRO | D63: Semiautomaticas | E63: 160 | F63: 0.0544 | G63: 0.0409 | H63: =(F63-G63)/F63 -> 0.24816176 | I63: HIPST | J63: PAI NEGRO 700 x 400 | K63: CAJA Nº 5 | L63: BOLSAS DE 120 X 125 | M63: 12 | N63: 25
A64: 1899 | B64: Venta Normal | C64: ART. 2 BASE ALTA NEGRO | D64: Semiautomaticas | E64: 300 | F64: 0.0257 | G64: 0.0202 | H64: =(F64-G64)/F64 -> 0.21400778 | I64: HIPST | J64: PAI NEGRO 560 x 500 | K64: CAJA Nº 4 | L64: BOLSAS DE 120 X 125 | M64: 2 | N64: 40
A65: 1758 | B65: Discontinuado | C65: BAND. 505 FOCACHA RECTANGULAR REF. | D65: Semiautomaticas | E65: 540 | F65: 0.0517 | H65: =(F65-G65)/F65 -> 1 | I65: HIPST | J65: PAI NEGRO 600 x 500 | K65: CAJA Nº 2 | L65: BOLSAS DE 120 X 97 | M65: 28 | N65: 6
A66: 1782 | B66: Discontinuado | C66: BAND. 505 PIZZA CUADRADA NEGRA REF. | D66: Semiautomaticas | E66: 360 | F66: 0.059 | H66: =(F66-G66)/F66 -> 1 | I66: HIPST | J66: PAI NEGRO 650 x 500 | K66: CAJA Nº 5 | L66: BOLSAS DE 120 X 125 | M66: 30 | N66: 5
A67: 1006 | B67: Venta Normal | C67: Z 12 PAI NEGRO (500M) | D67: Semiautomaticas | E67: 1300 | F67: 0.0203 | G67: 0.0151 | H67: =(F67-G67)/F67 -> 0.25615764 | I67: HIPST | J67: PAI NEGRO 660 x 500 | K67: CAJA Nº 3 | L67: BOLSAS DE 120 X 125 | M67: 84 | N67: 7
A68: 204 | B68: Venta Normal | C68: BANDEJA 4 QUESOS | D68: Semiautomaticas | E68: 540 | F68: 0.0298 | G68: 0.0197 | H68: =(F68-G68)/F68 -> 0.33892617 | I68: HIPST | J68: PAI NEGRO 700 x 500 | K68: CAJA Nº 4 SIN LOGO | L68: BOLSAS DE 120 X 125 | M68: 26
A69: 66 | B69: Venta Normal | C69: BLISTER BRACKETS BASE NEGRO | D69: Semiautomaticas | E69: 1850 | F69: 0.007 | H69: =(F69-G69)/F69 -> 1 | I69: HIPST | J69: PAI NEGRO 600 x 600 | K69: CAJA Nº 4/1 | L69: BOLSAS DE 120 X 125 | M69: 8 | N69: 20
A70: 213 | B70: Venta Normal | C70: BANDEJA 6 DIVISIONES NEGRO | D70: Semiautomaticas | E70: 250 | F70: 0.0554 | G70: 0.036 | H70: =(F70-G70)/F70 -> 0.35018051 | I70: HIPST | J70: PAI NEGRO 600 x 600 | K70: CAJA Nº 5 | L70: BOLSAS DE 120 X 125 | M70: 12 | N70: 12
A71: 684 | B71: Venta Normal | C71: MAMUSCHKA BOMBEE MEDIANA 600 | D71: Semiautomaticas | E71: 770 | F71: 0.0254 | G71: 0.0139 | H71: =(F71-G71)/F71 -> 0.45275591 | I71: HIPST | J71: PAI NEGRO 600 x 600 | K71: CAJA Nº 3 | L71: BOLSAS DE 120 X 97 | M71: 48 | N71: 25
A72: 751 | B72: Venta Normal | C72: MAMUSCHKA MUÑECAS BASE | D72: Semiautomaticas | E72: 480 | F72: 0.0065 | G72: 0.003 | H72: =(F72-G72)/F72 -> 0.53846154 | I72: HIPST | J72: PAI NEGRO 600 x 600 | M72: 70 | N72: 25
A73: 752 | B73: Venta Normal | C73: MAMUSCHKA MUÑECAS SOPORTE | D73: Semiautomaticas | E73: 480 | F73: 0.0046 | G73: 0.002 | H73: =(F73-G73)/F73 -> 0.56521739 | I73: HIPST | J73: PAI NEGRO 600 x 600 | M73: 48 | N73: 20
A74: 753 | B74: Venta Normal | C74: MAMUSCHKA MUÑECAS TAPA | D74: Semiautomaticas | E74: 480 | F74: 0.0065 | G74: 0.003 | H74: =(F74-G74)/F74 -> 0.53846154 | I74: HIPST | J74: PAI NEGRO 600 x 600 | M74: 1 | N74: 20
A75: 877 | B75: Venta Normal | C75: MAMUSCHKA MUÑECAS | D75: Semiautomaticas | E75: 480 | F75: 0.0176 | G75: 0.008 | H75: =(F75-G75)/F75 -> 0.54545455 | I75: HIPST | J75: PAI NEGRO 600 x 600 | K75: CAJA Nº 4/1 | L75: BOLSAS DE 120 X 125 | M75: 12 | N75: 8
A76: 1804 | B76: Venta Normal | C76: RAPA NUI TRUFAS GRANDE BASE | D76: Semiautomaticas | E76: 1200 | F76: 0.0254 | G76: 0.0181 | H76: =(F76-G76)/F76 -> 0.28740157 | I76: HIPST | J76: PAI NEGRO 600 x 600 | K76: CAJA Nº 4/1 | L76: BOLSAS DE 120 X 125 | M76: 96 | N76: 7
A77: 683 | B77: Venta Normal | C77: MAMUSCHKA 7 BOMBONES | D77: Semiautomaticas | E77: 2100 | F77: 0.011 | G77: 0.0069 | H77: =(F77-G77)/F77 -> 0.37272727 | I77: HIPST | J77: PAI NEGRO 650 x 600 | K77: CAJA Nº 4/1 | L77: BOLSAS DE 120 X 125 | M77: 20 | N77: 5
A78: 685 | B78: Venta Normal | C78: MAMUSCHKA CERISETTE 600 | D78: Semiautomaticas | E78: 1500 | F78: 0.0116 | G78: 0.0066 | H78: =(F78-G78)/F78 -> 0.43103448 | I78: HIPST | J78: PAI NEGRO 650 x 600 | K78: CAJA Nº 4/1 | L78: BOLSAS DE 120 X 125 | M78: 20 | N78: 5
A79: 686 | B79: Venta Normal | C79: MAMUSCHKA MENTITAS 600 | D79: Semiautomaticas | E79: 1500 | F79: 0.0116 | G79: 0.0066 | H79: =(F79-G79)/F79 -> 0.43103448 | I79: HIPST | J79: PAI NEGRO 650 x 600 | K79: CAJA Nº 4/1 | L79: BOLSAS DE 120 X 125 | M79: 40 | N79: 20
A80: 887 | B80: Venta Normal | C80: RAPA NUI TRUFAS CHICA BASE | D80: Semiautomaticas | E80: 3000 | F80: 0.0107 | G80: 0.0062 | H80: =(F80-G80)/F80 -> 0.42056075 | I80: HIPST | J80: PAI NEGRO 650 x 600 | K80: CAJA Nº 15 | L80: BOLSAS DE 120 X 97 | M80: 12 | N80: 20
A81: 1043 | B81: Venta Normal | C81: MAMUSCHKA POTE 1 KG HELADO | D81: Semiautomaticas | E81: 500 | F81: 0.0307 | G81: 0.0165 | H81: =(F81-G81)/F81 -> 0.46254072 | I81: HIPST | J81: PAI NEGRO 650 x 600 | K81: CAJA Nº 4 | L81: BOLSAS DE 120 X 125 | M81: 20 | N81: 10
A82: 1806 | B82: Venta Normal | C82: TABLILLA GRANDE | D82: Semiautomaticas | E82: 4800 | F82: 0.0033 | G82: 0.0019 | H82: =(F82-G82)/F82 -> 0.42424242 | I82: HIPST | J82: PAI NEGRO 600 x 700 | K82: CAJA Nº 4/1 | L82: BOLSAS DE 120 X 125 | M82: 112 | N82: 6
A83: 1807 | B83: Venta Normal | C83: TABLILLA CHICA | D83: Semiautomaticas | E83: 5600 | F83: 0.003 | G83: 0.0015 | H83: =(F83-G83)/F83 -> 0.5 | I83: HIPST | J83: PAI NEGRO 600 x 700 | K83: CAJA Nº 4 SIN LOGO | L83: BOLSAS DE 120 X 125 | M83: 4 | N83: 45
A84: 1774 | B84: Discontinuado | C84: DISPLAY BRANDPLAN NEGRO (048) | D84: Semiautomaticas | E84: 1140 | F84: 0.0277 | H84: =(F84-G84)/F84 -> 1 | I84: HIPST | J84: PAI NEGRO 700 x 800 | K84: CAJA Nº 0 | L84: BOLSAS SOBRE DE 20 X 25 (PP) | M84: 24 | N84: 40
A85: 651 | B85: Venta Normal | C85: LINEA FIX BASE | D85: Semiautomaticas | E85: 35 | F85: 0.3086 | G85: 0.21 | H85: =(F85-G85)/F85 -> 0.31950745 | I85: HIPST | J85: PAI NEGRO 600 x 1100 | K85: CAJA Nº 4 | L85: BOLSAS DE 120 X 125 | M85: 4 | N85: 20
A86: 899 | B86: Venta Normal | C86: SKF BLISTER PARA KLT | D86: Semiautomaticas | E86: 100 | F86: 0.1465 | G86: 0.0952 | H86: =(F86-G86)/F86 -> 0.35017065 | I86: HIPST | J86: PAI NEGRO 600 x 1200 | K86: CAJA Nº 4/1 | L86: BOLSAS DE 120 X 125 | M86: 3 | N86: 20
A87: 137 | B87: Venta Normal | C87: BANDEJA N° 17 F.V. NEGRO | D87: Semiautomaticas | E87: 40 | F87: 0.2936 | G87: 0.242 | H87: =(F87-G87)/F87 -> 0.17574932 | I87: HIPST | J87: PAI NEGRO 550 x 1400 | K87: CAJA Nº 4 | L87: BOLSAS DE 120 X 125 | M87: 14 | N87: 12
A88: 247 | B88: Venta Normal | C88: BANDEJA N° 24 F.V. NEGRO | D88: Semiautomaticas | E88: 40 | F88: 0.3465 | G88: 0.242 | H88: =(F88-G88)/F88 -> 0.3015873 | I88: HIPST | J88: PAI NEGRO 600 x 1400 | K88: CAJA Nº 4/1 | L88: BOLSAS DE 120 X 125 | M88: 3 | N88: 20
A89: 138 | B89: Venta Normal | C89: BANDEJA N° 46 F.V. NEGRO | D89: Semiautomaticas | E89: 40 | F89: 0.2936 | G89: 0.242 | H89: =(F89-G89)/F89 -> 0.17574932 | I89: HIPST | J89: PAI NEGRO 600 x 1400 | K89: CAJA Nº 4/1 | L89: BOLSAS DE 120 X 125 | M89: 2 | N89: 20
A90: 237 | B90: Venta Normal | C90: BANDEJA N° 10 F.V. NEGRO | D90: Semiautomaticas | E90: 40 | F90: 0.3234 | G90: 0.242 | H90: =(F90-G90)/F90 -> 0.25170068 | I90: HIPST | J90: PAI NEGRO 600 x 1400 | K90: CAJA Nº 4/1 | L90: BOLSAS DE 120 X 125 | M90: 3 | N90: 20
A91: 238 | B91: Venta Normal | C91: BANDEJA N° 14 F.V. NEGRO | D91: Semiautomaticas | E91: 52 | F91: 0.3234 | G91: 0.242 | H91: =(F91-G91)/F91 -> 0.25170068 | I91: HIPST | J91: PAI NEGRO 600 x 1400 | K91: CAJA Nº 4/1 | L91: BOLSAS DE 120 X 125 | M91: 3 | N91: 20
A92: 241 | B92: Venta Normal | C92: BANDEJA N° 18 F.V. NEGRO | D92: Semiautomaticas | E92: 30 | F92: 0.3234 | G92: 0.242 | H92: =(F92-G92)/F92 -> 0.25170068 | I92: HIPST | J92: PAI NEGRO 600 x 1400 | K92: CAJA Nº 4/1 | L92: BOLSAS DE 120 X 125 | M92: 3 | N92: 20
A93: 251 | B93: Venta Normal | C93: BANDEJA N° 49 F.V. NEGRO | D93: Semiautomaticas | E93: 30 | F93: 0.3203 | G93: 0.242 | H93: =(F93-G93)/F93 -> 0.24445832 | I93: HIPST | J93: PAI NEGRO 600 x 1400 | K93: CAJA Nº 4/1 | L93: BOLSAS DE 120 X 125 | M93: 3 | N93: 20
A94: 254 | B94: Venta Normal | C94: BANDEJA N° 50 F.V. NEGRO | D94: Semiautomaticas | E94: 40 | F94: 0.3234 | G94: 0.242 | H94: =(F94-G94)/F94 -> 0.25170068 | I94: HIPST | J94: PAI NEGRO 600 x 1400 | K94: CAJA Nº 4/1 | L94: BOLSAS DE 120 X 125 | M94: 3 | N94: 20
A95: 256 | B95: Venta Normal | C95: BANDEJA N° 51 F.V. NEGRO | D95: Semiautomaticas | E95: 40 | F95: 0.3234 | G95: 0.242 | H95: =(F95-G95)/F95 -> 0.25170068 | I95: HIPST | J95: PAI NEGRO 600 x 1400 | K95: CAJA Nº 4/1 | L95: BOLSAS DE 120 X 125 | M95: 3 | N95: 20
A96: 257 | B96: Venta Normal | C96: BANDEJA N° 52 F.V. NEGRO | D96: Semiautomaticas | E96: 50 | F96: 0.3234 | G96: 0.242 | H96: =(F96-G96)/F96 -> 0.25170068 | I96: HIPST | J96: PAI NEGRO 600 x 1400 | K96: CAJA Nº 4/1 | L96: BOLSAS DE 120 X 125 | M96: 3 | N96: 20
... A116: 962 | B116: Venta Normal | C116: TRIANGULITO X 150 NUEVO PAI | D116: GN | E116: 700 | F116: 0.0168 | G116: 0.0132 | H116: =(F116-G116)/F116 -> 0.21428571 | I116: HIPST | J116: PAI BLANCO 600 x 300 | K116: CAJA Nº 4 | L116: BOLSAS DE 120 X 125 | M116: 6 | N116: 20
A117: 1002 | B117: Venta Normal | C117: Z 105 OVALADA BASE PAI BLANCO | D117: GN | E117: 500 | F117: 0.0162 | G117: 0.0108 | H117: =(F117-G117)/F117 -> 0.33333333 | I117: HIPST | J117: PAI BLANCO 600 x 300 | K117: CAJA Nº 4 | L117: BOLSAS DE 120 X 125 | M117: 16
A118: 790 | B118: Venta Normal | C118: PALMERITA X 150 INVERTIDA PAI | D118: GN | E118: 1680 | F118: 0.0132 | G118: 0.0068 | H118: =(F118-G118)/F118 -> 0.48484848 | I118: HIPST | J118: PAI BLANCO 510 x 350 | K118: CAJA Nº 5 | L118: BOLSAS DE 120 X 125 | M118: 5 | N118: 23
A119: 798 | B119: Venta Normal | C119: PALMERITA X 150 PAI | D119: GN | E119: 840 | F119: 0.0123 | G119: 0.0093 | H119: =(F119-G119)/F119 -> 0.24390244 | I119: HIPST | J119: PAI BLANCO 600 x 400 | K119: CAJA Nº 4/1 | L119: BOLSAS DE 120 X 125 | M119: 8
A120: 950 | B120: Discontinuado | C120: TRAPEZOIDE X 4 KALEU | D120: GN | E120: 1500 | F120: 0.0165 | H120: =(F120-G120)/F120 -> 1 | I120: HIPST | J120: PAI BLANCO 600 x 400 | K120: CAJA Nº 4/1 | L120: BOLSAS DE 120 X 125 | M120: 8
A121: 951 | B121: Discontinuado | C121: TRAPEZOIDE X 400 GRS. | D121: GN | E121: 1500 | F121: 0.0165 | H121: =(F121-G121)/F121 -> 1 | I121: HIPST | J121: PAI BLANCO 600 x 400 | K121: CAJA Nº 4 SIN LOGO | L121: BOLSAS DE 120 X 125 | M121: 8
A122: 1730 | B122: Discontinuado | C122: KALEU COD. LOINS PAI | D122: GN | E122: 1500 | F122: 0.0165 | H122: =(F122-G122)/F122 -> 1 | I122: HIPST | J122: PAI BLANCO 600 x 400 | K122: CAJA Nº 4/1 | L122: BOLSAS DE 120 X 125 | M122: 24 | N122: 14
A124: 837 | B124: Venta Normal | C124: PLATO 17 CM. BLANCO | D124: Semiautomaticas | E124: 1000 | F124: 0.0066 | G124: 0.0042 | H124: =(F124-G124)/F124 -> 0.36363636 | I124: HIPST | J124: PAI BLANCO 710 x 170 | K124: CAJA Nº 7 | L124: BOLSAS DE 120 X 125 | M124: 2 | N124: 20
A125: 475 | B125: Venta Normal | C125: CUNA X 60 GRS. | D125: Semiautomaticas | E125: 3500 | F125: 0.002 | G125: 0.0017 | H125: =(F125-G125)/F125 -> 0.15 | I125: HIPST | J125: PAI BLANCO 600 x 180 | K125: CAJA Nº 3 | L125: BOLSAS DE 120 X 97 | M125: 72 | N125: 16
A126: 841 | B126: Venta Normal | C126: PLATO 22 CM. BLANCO | D126: Semiautomaticas | E126: 1000 | F126: 0.0108 | G126: 0.0067 | H126: =(F126-G126)/F126 -> 0.37962963 | I126: HIPST | J126: PAI BLANCO 710 x 180 | K126: CAJA Nº 4/1 | L126: BOLSAS DE 120 X 125 | M126: 15 | N126: 20
A127: 19 | B127: Venta Normal | C127: ALFAJOR LIA CHICO PAI | D127: Semiautomaticas | E127: 7560 | F127: 0.0025 | G127: 0.0022 | H127: =(F127-G127)/F127 -> 0.12 | I127: HIPST | J127: PAI BLANCO 600 x 200 | K127: CAJA Nº 4/1 | L127: BOLSAS DE 120 X 125 | M127: 54 | N127: 8
A128: 476 | B128: Venta Normal | C128: CUNA X 90 GRS. | D128: Semiautomaticas | E128: 3100 | F128: 0.0027 | G128: 0.0023 | H128: =(F128-G128)/F128 -> 0.14814815 | I128: HIPST | J128: PAI BLANCO 600 x 200 | K128: CAJA Nº 12 | L128: BOLSAS DE 120 X 97 | M128: 48 | N128: 14
A129: 519 | B129: Discontinuado | C129: DULCYPAS X 12 PAI | D129: Semiautomaticas | E129: 2000 | F129: 0.0143 | H129: =(F129-G129)/F129 -> 1 | I129: HIPST | J129: PAI BLANCO 600 x 200 | K129: CAJA Nº 4 | L129: BOLSAS DE 120 X 125 | M129: 10 | N129: 20
A130: 671 | B130: Venta Normal | C130: MAGDALENAS X 6 PAI BLANCO (200M) | D130: Semiautomaticas | E130: 4000 | F130: 0.0057 | G130: 0.004 | H130: =(F130-G130)/F130 -> 0.29824561 | I130: HIPST | J130: PAI BLANCO 600 x 200 | K130: CAJA Nº 4/1 | L130: BOLSAS DE 120 X 125 | M130: 27 | N130: 20
A131: 691 | B131: Venta Normal | C131: MANTECADO X 6 PAI BLANCO | D131: Semiautomaticas | E131: 3500 | F131: 0.0071 | G131: 0.0055 | H131: =(F131-G131)/F131 -> 0.22535211 | I131: HIPST | J131: PAI BLANCO 600 x 200 | K131: CAJA Nº 4/1 | L131: BOLSAS DE 120 X 125 | M131: 20 | N131: 24
A132: 848 | B132: Venta Normal | C132: PLATO PARA TORTA | D132: Semiautomaticas | E132: 900 | F132: 0.0179 | G132: 0.0102 | H132: =(F132-G132)/F132 -> 0.4301676 | I132: HIPST | J132: PAI BLANCO 600 x 200 | K132: CAJA Nº 2 | L132: BOLSAS DE 120 X 97 | M132: 8 | N132: 20
A133: 894 | B133: Venta Normal | C133: RELLENAS X 150 | D133: Semiautomaticas | E133: 6400 | F133: 0.0034 | G133: 0.0024 | H133: =(F133-G133)/F133 -> 0.29411765 | I133: HIPST | J133: PAI BLANCO 600 x 200 | K133: CAJA Nº 4/1 | L133: BOLSAS DE 120 X 125 | M133: 40 | N133: 20
A134: 675 | B134: Venta Normal | C134: MAGDALENAS X 12 | D134: Semiautomaticas | E134: 2000 | F134: 0.0108 | G134: 0.0094 | H134: =(F134-G134)/F134 -> 0.12962963 | I134: HIPST | J134: PAI BLANCO 600 x 200 | K134: CAJA Nº 3 | L134: BOLSAS DE 120 X 97 | M134: 8
...

Sheet Hoja6
A1: COD. | B1: Estado | C1: Maquina | D1: ARTICULO | E1: UN por CAJA | F1: PESO BR. | G1: PESO NET. | H1: % SCRAP | I1: MATERIAL | J1: MATERIAL DETALLE | K1: CAJAS | L1: BOLSA | M1: CAV | N1: META | P1: FECHA | Q1: MAQ | R1: Calentamiento | S1: Ventilador de calor | T1: Fomación | U1: Ventilador de forma | V1: intervalo de corte | W1: Retraso de expulsión | X1: Expulsión | Y1: Transporte | Z1: Retraso de cierre | AA1: Promedio de ciclo | AB1: Molde | AC1: Zona1 | AD1: Zona2 | AE1: Zona3 | AF1: Precalentador | AG1: Presión de calentamiento | AH1: Presión de formación | AI1: Presión de expusión | AJ1: Velocidad | AK1: Recorrido | AL1: Modo | AM1: Acel/ Desacel | AN1: Velocidad del paso
A2: 1075 | B2: Venta Normal | C2: GN | D2: TAPA 50 OZ PAI NEGRO | E2: 240 | F2: 0.0129 | G2: 0.0093 | H2: =(F2-G2)/F2 -> 0.27906977 | I2: HIPST | J2: PAI NEGRO 560 x 300 | K2: CAJA SOLUPLEX 103 (50 OZ) | L2: BOLSAS DE 120 X 97 | M2: 6 | N2: 40 | P2: 45366 | Q2: 15 | R2: 3 | S2: 2.5 | T2: 3.8 | U2: 2 | V2: 0.35 | W2: 0.21 | X2: 0.18 | Y2: 0.55 | Z2: 0.58 | AA2: 13.5 | AB2: 50 | AC2: 125 | AD2: 125 | AE2: 128 | AF2: 50 | AG2: 20 | AH2: 40 | AI2: 20 | AJ2: 100 | AK2: 392 | AL2: Normal | AM2: 1000 | AN2: 10
A3: 1093 | B3: Venta Normal | C3: GN | D3: TAPA 25 OZ | E3: 300 | F3: 0.0109 | G3: 0.0064 | H3: =(F3-G3)/F3 -> 0.41284404 | I3: PVC | J3: PVC CRISTAL 520 x 250 | K3: CAJA SOLUPLEX 101 (25 OZ) | L3: BOLSAS DE 120 X 97 | M3: 6 | N3: 75 | P3: 45348 | Q3: 12 | R3: 2 | S3: 1.1 | T3: 2.1 | U3: 1.1 | V3: 0.25 | W3: 0.15 | X3: 0.18 | Y3: 0.35 | Z3: 0.25 | AA3: 6.8 | AB3: 41 | AC3: 97 | AD3: 98 | AE3: 98 | AF3: 44 | AG3: 38 | AH3: 40 | AI3: 40 | AJ3: 67 | AK3: 328 | AL3: Normal | AM3: 2550 | AN3: 10

Sheet Hoja5
K1: PESO (g) | N1: ESPESOR DE FONDO (mm) | Q1: ESPESOR DE PARED (mm) | T1: ESPESOR DE TAPA (mm)
A2: COD. | B2: Maquina | C2: ARTICULO | D2: UN por CAJA | E2: PESO NET. | F2: MATERIAL | G2: MATERIAL DETALLE | I2: Código | J2: DESCRIPCION PRODUCTO | K2: Min | L2: Meta | M2: Max | N2: Min | O2: Meta | P2: Max | Q2: Min | R2: Meta | S2: Max | T2: Min | U2: Meta | V2: Max
A3: 338 | B3: GN | C3: AP-12 | D3: 1200 | E3: 0.0135 | F3: PET | G3: PET CRISTAL 580 x 250
A4: 398 | B4: GN | C4: AP-6 | D4: 1600 | E4: 0.0103 | F4: PET | G4: PET CRISTAL 520 x 220
A5: 1814 | B5: GN | C5: ART. 2050 | D5: 520 | E5: 0.0204 | F5: PET | G5: PET CRISTAL 460 x 250
A6: 1915 | B6: GN | C6: ART. 2050 (X 300) | D6: 300 | E6: 0.0204 | F6: PET | G6: PET CRISTAL 460 x 250
A7: 1815 | B7: GN | C7: ART. 2060 | D7: 520 | E7: 0.0204 | F7: PET | G7: PET CRISTAL 460 x 250
A8: 1916 | B8: GN | C8: ART. 2060 (X 300) | D8: 300 | E8: 0.0204 | F8: PET | G8: PET CRISTAL 460 x 250
A9: 1823 | B9: GN | C9: ART. 2510 | D9: 200 | E9: 0.0423 | F9: PET | G9: PET CRISTAL 560 x 300
A10: 101 | B10: GN | C10: ART. T 16 | D10: 60 | E10: 0.0605 | F10: PET | G10: PET CRISTAL 410 x 450
A11: 38 | B11: GN | C11: ART. T 17 | D11: 160 | E11: 0.0743 | F11: PET | G11: PET CRISTAL 410 x 550
A12: 629 | B12: GN | C12: ART. T-23 M | D12: 200 | E12: 0.0493 | F12: PET | G12: PET CRISTAL 490 x 600
A13: 8 | B13: GN | C13: BANDEJA 4 COMPARTIMENTOS | D13: 850 | E13: 0.0074 | F13: PET | G13: PET CRISTAL 550 x 200 | I13: 8 | J13: BANDEJA 4 COMPARTIMENTOS | K13: 7.03 | L13: 7.4 | M13: 7.77 | N13: 0.12788889 | O13: 0.14788889 | P13: 0.16788889 | T13: NA | U13: NA | V13: NA
A14: 906 | B14: GN | C14: CERICET | D14: 1080 | E14: 0.0104 | F14: PET | G14: PET CRISTAL 470 x 300
A15: 252 | B15: GN | C15: GY-12 | D15: 560 | E15: 0.0174 | F15: PET | G15: PET CRISTAL 550 x 350
A16: 1033 | B16: GN | C16: LICORFORT | D16: 960 | E16: 0.0095 | F16: PET | G16: PET CRISTAL 580 x 400
A17: 35 | B17: GN | C17: MASCARA COVID-19 | D17: 400 | E17: 0.0454 | F17: PET | G17: PET CRISTAL 720 x 300
A18: 1135 | B18: GN | C18: PORCION CHICA | D18: 500 | E18: 0.0075 | F18: PET | G18: PET CRISTAL 580 x 250 | I18: 1135 | J18: PORCION CHICA | K18: 68.4 | L18: 72 | M18: 75.6 | N18: 0.1205 | O18: 0.1405 | P18: 0.1605
A19: 1136 | B19: GN | C19: PORCION GRANDE | D19: 500 | E19: 0.0088 | F19: PET | G19: PET CRISTAL 580 x 300 | I19: 1136 | J19: PORCION GRANDE | K19: 8.36 | L19: 8.8 | M19: 9.24 | N19: 0.09075 | O19: 0.11075 | P19: 0.13075 | Q19: 0.071 | R19: 0.091 | S19: 0.111 | T19: 0.173 | U19: 0.193 | V19: 0.213
A20: 1895 | B20: GN | C20: SEPARADOR DE INGREDIENTES | D20: 850 | E20: 0.0074 | F20: PET | G20: PET CRISTAL 550 x 200
A21: 1082 | B21: GN | C21: Z T 7 | D21: 100 | E21: 0.072 | F21: PET | G21: PET CRISTAL 560 x 350 | I21: 1082 | J21: Z T 7 | K21: 66.975 | L21: 70.5 | M21: 74.025
A22: 1087 | B22: GN | C22: Z T 8 | D22: 100 | E22: 0.0613 | F22: PET | G22: PET CRISTAL 560 x 300 | I22: 1087 | J22: Z T 8 | K22: 58.235 | L22: 61.3 | M22: 64.365 | N22: 0.177 | O22: 0.197 | P22: 0.217 | Q22: 0.156 | R22: 0.176 | S22: 0.196 | T22: 0.185 | U22: 0.205 | V22: 0.225
A24: 11 | B24: Semiautomaticas | C24: M-SHAPE | D24: 600 | F24: PET | G24: PET CRISTAL 860 x 470
A25: 1871 | B25: Semiautomaticas | C25: ZC-45 | D25: 450 | E25: 0.0257 | F25: PET | G25: PET CRISTAL 535 x 500
A26: 1955 | B26: Semiautomaticas | C26: ZC-45 | D26: 450 | E26: 0.0257 | F26: PET | G26: PET CRISTAL 535 x 500
A27: 208 | B27: Semiautomaticas | C27: ZC-61 | D27: 450 | E27: 0.0297 | F27: PET | G27: PET CRISTAL 535 x 550
A28: 842 | B28: Semiautomaticas | C28: ZC-61 (TIERRA GAUCHA) | D28: 450 | E28: 0.0297 | F28: PET | G28: PET CRISTAL 535 x 550 | I28: 842 | J28: ZC-61 (TIERRA GAUCHA) | K28: 28.215 | L28: 29.7 | M28: 31.185 | N28: 0.34142857 | O28: 0.36142857 | P28: 0.38142857 | Q28: 0.21614286 | R28: 0.23614286 | S28: 0.25614286 | T28: NA | U28: NA | V28: NA
A29: 209 | B29: Semiautomaticas | C29: ZC-83 | D29: 400 | E29: 0.0323 | F29: PET | G29: PET CRISTAL 535 x 600
A30: 843 | B30: Semiautomaticas | C30: ZC-83 | D30: 400 | E30: 0.0323 | F30: PET | G30: PET CRISTAL 535 x 600
A31: 178 | B31: Semiautomaticas | C31: ZV-40 | D31: 400 | E31: 0.029 | F31: PET | G31: PET CRISTAL 635 x 450
A32: 844 | B32: Semiautomaticas | C32: ZV-40 (TIERRA GAUCHA) | D32: 400 | E32: 0.029 | F32: PET | G32: PET CRISTAL 635 x 450
A33: 1060 | B33: Semiautomaticas | C33: ZV-40 NEGRO | D33: 400 | E33: 0.029 | F33: PET | G33: PET NEGRO 635 x 450
A34: 179 | B34: Semiautomaticas | C34: ZV-60 | D34: 360 | E34: 0.0318 | F34: PET | G34: PET CRISTAL 635 x 500 | I34: 179 | J34: ZV-60 | K34: 30.21 | L34: 31.8 | M34: 33.39 | N34: 0.312625 | O34: 0.332625 | P34: 0.352625 | Q34: 0.22575 | R34: 0.24575 | S34: 0.26575
A35: 845 | B35: Semiautomaticas | C35: ZV-60 (TIERRA GAUCHA) | D35: 360 | E35: 0.0318 | F35: PET | G35: PET CRISTAL 635 x 500
A36: 1953 | B36: Semiautomaticas | C36: ZW-250 | D36: 760 | E36: 0.0168 | F36: PET | G36: PET CRISTAL 660 x 500
A37: 961 | B37: Semiautomaticas | C37: ZW-250 TIERRA GAUCHA | D37: 760 | E37: 0.0168 | F37: PET | G37: PET CRISTAL 660 x 500
A38: 180 | B38: Semiautomaticas | C38: ZW-500 | D38: 700 | E38: 0.018 | F38: PET | G38: PET CRISTAL 660 x 500
A39: 857 | B39: Semiautomaticas | C39: ZW-500 | D39: 700 | E39: 0.018 | F39: PET | G39: PET CRISTAL 660 x 500
A40: 1943 | B40: Semiautomaticas | C40: ZW-500 (10141860CI) | D40: 342 | E40: 0.0228 | F40: PET | G40: PET CRISTAL 660 x 660 (FASON)
A41: 847 | B41: Semiautomaticas | C41: ZW-500 (400M) | D41: 700 | E41: 0.014 | F41: PET | G41: PET CRISTAL 660 x 400
A42: 905 | B42: Semiautomaticas | C42: ZW-500 (450M) | D42: 700 | E42: 0.0157 | F42: PET | G42: PET CRISTAL 660 x 450
A43: 172 | B43: Semiautomaticas | C43: ZW-500 (550M) | D43: 700 | E43: 0.0188 | F43: PET | G43: PET CRISTAL 660 x 550
A44: 583 | B44: Semiautomaticas | C44: ZW-500 (600M) | D44: 700 | E44: 0.0204 | F44: PET | G44: PET CRISTAL 660 x 600
A45: 1050 | B45: Semiautomaticas | C45: ZW-500 NEGRO | D45: 700 | E45: 0.018 | F45: PET | G45: PET NEGRO 660 x 500
A46: 1954 | B46: Semiautomaticas | C46: ZW-ALBONDIGAS | D46: 760 | E46: 0.0168 | F46: PET | G46: PET CRISTAL 660 x 500
A48: 692 | B48: Termo | C48: POTE 1135 | D48: 500 | E48: 0.01 | F48: PET | G48: PET CRISTAL 860 x 300 | I48: 692 | J48: POTE 1135 | K48: 9.5 | L48: 10 | M48: 10.5 | N48: 0.1454 | O48: 0.1654 | P48: 0.1854 | Q48: 0.1152 | R48: 0.1352 | S48: 0.1552 | T48: 0.1916 | U48: 0.2116 | V48: 0.2316
A49: 1983 | B49: Termo | C49: POTE 1135 (X200) | D49: 200 | E49: 0.01 | F49: PET | G49: PET CRISTAL 860 x 300
A50: 2002 | B50: Termo | C50: POTE 1135 X400 PARA EXPORTACIÓN | D50: 400 | E50: 0.01 | F50: PET | G50: PET CRISTAL 860 x 300
A51: 1924 | B51: Termo | C51: POTE 1140 | D51: 500 | E51: 0.0111 | F51: PET | G51: PET CRISTAL 860 x 340
A52: 1986 | B52: Termo | C52: POTE 1140 (X200) | D52: 200 | E52: 0.0111 | F52: PET | G52: PET CRISTAL 860 x 340
A53: 693 | B53: Termo | C53: POTE 1145 | D53: 500 | E53: 0.0113 | F53: PET | G53: PET CRISTAL 860 x 330 | I53: 693 | J53: POTE 1145 | K53: 10.735 | L53: 11.3 | M53: 11.865 | N53: 0.216 | O53: 0.236 | P53: 0.256 | Q53: 0.168 | R53: 0.188 | S53: 0.208 | T53: 0.221125 | U53: 0.241125 | V53: 0.261125
A54: 1984 | B54: Termo | C54: POTE 1145 (X200) | D54: 200 | E54: 0.0113 | F54: PET | G54: PET CRISTAL 860 x 330
A55: 2003 | B55: Termo | C55: POTE 1145 X400 PARA EXPORTACIÓN | D55: 400 | E55: 0.0113 | F55: PET | G55: PET CRISTAL 860 x 330
A56: 1925 | B56: Termo | C56: POTE 1150 | D56: 500 | E56: 0.013 | F56: PET | G56: PET CRISTAL 860 x 390
A57: 1987 | B57: Termo | C57: POTE 1150 (X200) | D57: 200 | E57: 0.013 | F57: PET | G57: PET CRISTAL 860 x 390
A58: 694 | B58: Termo | C58: POTE 1165 | D58: 500 | E58: 0.0139 | F58: PET | G58: PET CRISTAL 860 x 420 | I58: 694 | J58: POTE 1165 | K58: 13.3 | L58: 14 | M58: 14.7 | N58: 0.265 | O58: 0.285 | P58: 0.305 | Q58: 0.175 | R58: 0.195 | S58: 0.215 | T58: 0.215 | U58: 0.235 | V58: 0.255
A59: 1985 | B59: Termo | C59: POTE 1165 (X 200) | D59: 200 | E59: 0.0139 | F59: PET | G59: PET CRISTAL 860 x 420
A60: 2004 | B60: Termo | C60: POTE 1165 x 400 EXPORTACIÓN | D60: 400 | E60: 0.0139 | F60: PET | G60: PET CRISTAL 860 x 420
A61: 1926 | B61: Termo | C61: POTE 1170 | D61: 500 | E61: 0.0147 | F61: PET | G61: PET CRISTAL 860 x 470
A62: 1988 | B62: Termo | C62: POTE 1170 (X200) | D62: 200 | E62: 0.0147 | F62: PET | G62: PET CRISTAL 860 x 470
A63: 1008 | B63: Termo | C63: Z F 1000 | D63: 400 | E63: 0.0323 | F63: PET | G63: PET CRISTAL 900 x 490
A64: 1759 | B64: Termo | C64: Z F 110 | D64: 720 | E64: 0.012 | F64: PET | G64: PET CRISTAL 820 x 350
A65: 1009 | B65: Termo | C65: Z F 110 PERFORADA | D65: 720 | E65: 0.012 | F65: PET | G65: PET CRISTAL 820 x 350
A66: 1920 | B66: Termo | C66: Z F 110 PERFORADA (TREVIPLAST) | D66: 720 | E66: 0.012 | F66: PET | G66: PET CRISTAL 820 x 420 (FASON)
A67: 1010 | B67: Termo | C67: Z F 125 | D67: 720 | E67: 0.012 | F67: PET | G67: PET CRISTAL 820 x 385
A68: 1011 | B68: Termo | C68: Z F 125 PERFORADA | D68: 720 | E68: 0.012 | F68: PET | G68: PET CRISTAL 820 x 390
A69: 1012 | B69: Termo | C69: Z F 160 | D69: 720 | E69: 0.012 | F69: PET | G69: PET CRISTAL 820 x 350
A70: 1013 | B70: Termo | C70: Z F 160 PERFORADA | D70: 720 | E70: 0.012 | F70: PET | G70: PET CRISTAL 820 x 390
... A83: 1863 | B83: Termo | C83: ZDS 720 DARNEL | D83: 500 | E83: 0.021 | F83: PET | G83: PET CRISTAL 915 x 800 (FASON)
A84: 1844 | B84: Termo | C84: ZDS TAPA | D84: 500 | E84: 0.007 | F84: PET | G84: PET CRISTAL 1020 x 400 | I84: 1844 | J84: ZDS TAPA | K84: 6.65 | L84: 7 | M84: 7.35 | N84: NA | O84: NA | P84: NA | Q84: NA | R84: NA | S84: NA | T84: 0.34471429 | U84: 0.36471429 | V84: 0.38471429
A85: 1864 | B85: Termo | C85: ZDS TAPA (105TPCEA) | D85: 500 | E85: 0.007 | F85: PET | G85: PET CRISTAL 1020 x 400 (FASON)
A86: 1859 | B86: Termo | C86: ZDS TAPA DARNEL | D86: 500 | E86: 0.007 | F86: PET | G86: PET CRISTAL 1020 x 400 (FASON)
I99: 1847 | J99: ZDS 480 | K99: 13.3 | L99: 14 | M99: 14.7 | N99: 0.198 | O99: 0.218 | P99: 0.238 | Q99: 0.155 | R99: 0.175 | S99: 0.195 | T99: NA | U99: NA | V99: NA
I100: 1848 | J100: ZDS 720 | K100: 19.95 | L100: 21 | M100: 22.05 | N100: 0.4106 | O100: 0.4306 | P100: 0.4506 | Q100: 0.1622 | R100: 0.1822 | S100: 0.2022 | T100: NA | U100: NA | V100: NA
I101: 1864 | J101: ZDS TAPA (105TPCEA) | K101: 6.65 | L101: 7 | M101: 7.35 | N101: NA | O101: NA | P101: NA | Q101: NA | R101: NA | S101: NA | T101: 0.34471429 | U101: 0.36471429 | V101: 0.38471429
I102: 1865 | J102: ZDS 240 (105PCEA240) | K102: 8.075 | L102: 8.5 | M102: 8.925 | N102: 0.268 | O102: 0.288 | P102: 0.308 | Q102: 0.2 | R102: 0.22 | S102: 0.24 | T102: 0.268 | U102: 0.288 | V102: 0.308
I103: 1866 | J103: ZDS 360 (105PCEA360) | K103: 11.4 | L103: 12 | M103: 12.6 | N103: 0.285 | O103: 0.305 | P103: 0.325 | Q103: 0.24 | R103: 0.26 | S103: 0.28 | T103: 0.24 | U103: 0.26 | V103: 0.28
I104: 1867 | J104: ZDS 480 (105PCEA480) | K104: 13.3 | L104: 14 | M104: 14.7 | N104: 0.1917 | O104: 0.2117 | P104: 0.2317 | Q104: 0.1547 | R104: 0.1747 | S104: 0.1947 | T104: NA | U104: NA | V104: NA
I105: 1915 | J105: ART. 2050 (X 300) | K105: 19.38 | L105: 20.4 | M105: 21.42 | N105: 0.104125 | O105: 0.124125 | P105: 0.144125 | Q105: 0.14425 | R105: 0.16425 | S105: 0.18425 | T105: 0.19885714 | U105: 0.21885714 | V105: 0.23885714
I106: 1916 | J106: ART. 2060 (X 300) | K106: 19.475 | L106: 20.5 | M106: 21.525 | N106: 0.1022 | O106: 0.1222 | P106: 0.1422 | Q106: 0.0994 | R106: 0.1194 | S106: 0.1394 | T106: 0.1857 | U106: 0.2057 | V106: 0.2257
I107: 1924 | J107: POTE 1140 | K107: 10.545 | L107: 11.1 | M107: 11.655 | N107: 0.2 | O107: 0.22 | P107: 0.24 | Q107: 0.126 | R107: 0.146 | S107: 0.166 | T107: 0.205 | U107: 0.225 | V107: 0.245
I108: 1925 | J108: POTE 1150 | K108: 12.35 | L108: 13 | M108: 13.65 | N108: 0.218 | O108: 0.238 | P108: 0.258 | Q108: 0.149 | R108: 0.169 | S108: 0.189 | T108: 0.259 | U108: 0.279 | V108: 0.299
I109: 1926 | J109: POTE 1170 | K109: 15.037143 | L109: 15.828571 | M109: 16.62 | N109: 0.3031 | O109: 0.3231 | P109: 0.3431 | Q109: 0.1724 | R109: 0.1924 | S109: 0.2124 | T109: 0.3153 | U109: 0.3353 | V109: 0.3553
I110: 1985 | J110: POTE 1165 (X 200) | K110: 13.3 | L110: 14 | M110: 14.7 | N110: 0.265 | O110: 0.285 | P110: 0.305 | Q110: 0.175 | R110: 0.195 | S110: 0.215 | T110: 0.215 | U110: 0.235 | V110: 0.255
I111: 1986 | J111: POTE 1140 (X200) | K111: 10.545 | L111: 11.1 | M111: 11.655 | N111: 0.2 | O111: 0.22 | P111: 0.24 | Q111: 0.126 | R111: 0.146 | S111: 0.166 | T111: 0.205 | U111: 0.225 | V111: 0.245
I112: 2002 | J112: POTE 1135 X400 PARA EXPORTACIÓN | K112: 9.5 | L112: 10 | M112: 10.5 | N112: 0.2044 | O112: 0.2244 | P112: 0.2444 | Q112: 0.126 | R112: 0.146 | S112: 0.166 | T112: 0.2381 | U112: 0.2581 | V112: 0.2781
I113: 2003 | J113: POTE 1145 X400 PARA EXPORTACIÓN | K113: 10.735 | L113: 11.3 | M113: 11.865 | N113: 0.1375 | O113: 0.1575 | P113: 0.1775 | Q113: 0.1269 | R113: 0.1469 | S113: 0.1669 | T113: 0.26445 | U113: 0.28445 | V113: 0.30445
I114: 2004 | J114: POTE 1165 x 400 EXPORTACIÓN | K114: 13.3 | L114: 14 | M114: 14.7 | N114: 0.265 | O114: 0.285 | P114: 0.305 | Q114: 0.175 | R114: 0.195 | S114: 0.215 | T114: 0.215 | U114: 0.235 | V114: 0.255
I115: 1822 | J115: ART. 2508 | K115: 40.185 | L115: 42.3 | M115: 44.415 | N115: 0.2193 | O115: 0.2393 | P115: 0.2593 | Q115: 0.1613 | R115: 0.1813 | S115: 0.2013 | T115: 0.1443 | U115: 0.1643 | V115: 0.1843
I116: 1823 | J116: ART. 2510 | K116: 40.185 | L116: 42.3 | M116: 44.415 | N116: 0.154 | O116: 0.174 | P116: 0.194 | Q116: 0.154 | R116: 0.174 | S116: 0.194 | T116: 0.156 | U116: 0.176 | V116: 0.196
